Workbook

Sheet Dashboard
A1: 💰 FINANCIAL DASHBOARD 2026
A2: =TODAY() | H2: Version 6.0 | Multi-currency Personal Finance Tracker
A4: THIS MONTH — GBP
B5: GBP EXPENSES | E5: GBP INCOME | H5: NET SAVINGS | K5: SAVINGS RATE
B6: =SUMPRODUCT((Expenses!E$3:E$999="GBP")*(MONTH(Expenses!A$3:A$999)=MONTH(TODAY()))*(YEAR(Expenses!A$3:A$999)=2026)*(Expenses!A$3:A$999<>"")*Expenses!D$3:D$999) | E6: =SUMPRODUCT((Income!D$3:D$502="GBP")*(MONTH(Income!A$3:A$502)=MONTH(TODAY()))*(YEAR(Income!A$3:A$502)=2026)*(Income!A$3:A$502<>"")*Income!C$3:C$502) | H6: =E6-B6 | K6: =IFERROR((E6-B6)/E6,0)
A10: ACCOUNT BALANCES SUMMARY
B11: TOTAL GBP ASSETS | E11: GBP CC DEBT | H11: NET GBP WORTH | K11: COMBINED GBP EQUIV
B12: =Balances!B21 | E12: =Balances!B22 | H12: =Balances!B21-Balances!B22 | K12: =Balances!B26
A16: YEAR TO DATE — 2026
B17: YTD GBP EXPENSES | E17: YTD GBP INCOME | H17: YTD NET SAVINGS | K17: YTD SAVINGS RATE
B18: =SUMPRODUCT((Expenses!E$3:E$999="GBP")*(YEAR(Expenses!A$3:A$999)=2026)*(Expenses!A$3:A$999<>"")*Expenses!D$3:D$999) | E18: =SUMPRODUCT((Income!D$3:D$502="GBP")*(YEAR(Income!A$3:A$502)=2026)*(Income!A$3:A$502<>"")*Income!C$3:C$502) | H18: =E18-B18 | K18: =IFERROR((E18-B18)/E18,0)
A54: 📊 Chart data below (do not edit)
A55: Category | B55: This Month (GBP) | D55: Account | E55: Balance (GBP)
A56: Rent | B56: =SUMPRODUCT((Expenses!C$3:C$999=A56)*(Expenses!E$3:E$999="GBP")*(MONTH(Expenses!A$3:A$999)=MONTH(TODAY()))*(YEAR(Expenses!A$3:A$999)=2026)*(Expenses!A$3:A$999<>"")*Expenses!D$3:D$999) | D56: Lloyds Bank (GBP) | E56: =IFERROR(INDEX(Balances!G$3:G$19,MATCH(D56,Balances!A$3:A$19,0)),0)
A57: Transport | B57: =SUMPRODUCT((Expenses!C$3:C$999=A57)*(Expenses!E$3:E$999="GBP")*(MONTH(Expenses!A$3:A$999)=MONTH(TODAY()))*(YEAR(Expenses!A$3:A$999)=2026)*(Expenses!A$3:A$999<>"")*Expenses!D$3:D$999) | D57: HSBC Bank (GBP) | E57: =IFERROR(INDEX(Balances!G$3:G$19,MATCH(D57,Balances!A$3:A$19,0)),0)
A58: Travel | B58: =SUMPRODUCT((Expenses!C$3:C$999=A58)*(Expenses!E$3:E$999="GBP")*(MONTH(Expenses!A$3:A$999)=MONTH(TODAY()))*(YEAR(Expenses!A$3:A$999)=2026)*(Expenses!A$3:A$999<>"")*Expenses!D$3:D$999) | D58: Barclays Bank (GBP) | E58: =IFERROR(INDEX(Balances!G$3:G$19,MATCH(D58,Balances!A$3:A$19,0)),0)
A59: Shopping | B59: =SUMPRODUCT((Expenses!C$3:C$999=A59)*(Expenses!E$3:E$999="GBP")*(MONTH(Expenses!A$3:A$999)=MONTH(TODAY()))*(YEAR(Expenses!A$3:A$999)=2026)*(Expenses!A$3:A$999<>"")*Expenses!D$3:D$999) | D59: Klarna Pay (GBP) | E59: =IFERROR(INDEX(Balances!G$3:G$19,MATCH(D59,Balances!A$3:A$19,0)),0)
A60: Electronics | B60: =SUMPRODUCT((Expenses!C$3:C$999=A60)*(Expenses!E$3:E$999="GBP")*(MONTH(Expenses!A$3:A$999)=MONTH(TODAY()))*(YEAR(Expenses!A$3:A$999)=2026)*(Expenses!A$3:A$999<>"")*Expenses!D$3:D$999) | D60: Oyster Travel Card (GBP) | E60: =IFERROR(INDEX(Balances!G$3:G$19,MATCH(D60,Balances!A$3:A$19,0)),0)
A61: Subscriptions | B61: =SUMPRODUCT((Expenses!C$3:C$999=A61)*(Expenses!E$3:E$999="GBP")*(MONTH(Expenses!A$3:A$999)=MONTH(TODAY()))*(YEAR(Expenses!A$3:A$999)=2026)*(Expenses!A$3:A$999<>"")*Expenses!D$3:D$999) | D61: Chase Bank (GBP) | E61: =IFERROR(INDEX(Balances!G$3:G$19,MATCH(D61,Balances!A$3:A$19,0)),0)
A62: Bills | B62: =SUMPRODUCT((Expenses!C$3:C$999=A62)*(Expenses!E$3:E$999="GBP")*(MONTH(Expenses!A$3:A$999)=MONTH(TODAY()))*(YEAR(Expenses!A$3:A$999)=2026)*(Expenses!A$3:A$999<>"")*Expenses!D$3:D$999) | D62: Monzo (GBP) | E62: =IFERROR(INDEX(Balances!G$3:G$19,MATCH(D62,Balances!A$3:A$19,0)),0)
A63: Entertainment | B63: =SUMPRODUCT((Expenses!C$3:C$999=A63)*(Expenses!E$3:E$999="GBP")*(MONTH(Expenses!A$3:A$999)=MONTH(TODAY()))*(YEAR(Expenses!A$3:A$999)=2026)*(Expenses!A$3:A$999<>"")*Expenses!D$3:D$999)
A64: Food and Drinks | B64: =SUMPRODUCT((Expenses!C$3:C$999=A64)*(Expenses!E$3:E$999="GBP")*(MONTH(Expenses!A$3:A$999)=MONTH(TODAY()))*(YEAR(Expenses!A$3:A$999)=2026)*(Expenses!A$3:A$999<>"")*Expenses!D$3:D$999)
A65: Groceries | B65: =SUMPRODUCT((Expenses!C$3:C$999=A65)*(Expenses!E$3:E$999="GBP")*(MONTH(Expenses!A$3:A$999)=MONTH(TODAY()))*(YEAR(Expenses!A$3:A$999)=2026)*(Expenses!A$3:A$999<>"")*Expenses!D$3:D$999)
A66: Others | B66: =SUMPRODUCT((Expenses!C$3:C$999=A66)*(Expenses!E$3:E$999="GBP")*(MONTH(Expenses!A$3:A$999)=MONTH(TODAY()))*(YEAR(Expenses!A$3:A$999)=2026)*(Expenses!A$3:A$999<>"")*Expenses!D$3:D$999)
A67: Gifts | B67: =SUMPRODUCT((Expenses!C$3:C$999=A67)*(Expenses!E$3:E$999="GBP")*(MONTH(Expenses!A$3:A$999)=MONTH(TODAY()))*(YEAR(Expenses!A$3:A$999)=2026)*(Expenses!A$3:A$999<>"")*Expenses!D$3:D$999)
A68: Donations | B68: =SUMPRODUCT((Expenses!C$3:C$999=A68)*(Expenses!E$3:E$999="GBP")*(MONTH(Expenses!A$3:A$999)=MONTH(TODAY()))*(YEAR(Expenses!A$3:A$999)=2026)*(Expenses!A$3:A$999<>"")*Expenses!D$3:D$999)
A69: Investments | B69: =SUMPRODUCT((Expenses!C$3:C$999=A69)*(Expenses!E$3:E$999="GBP")*(MONTH(Expenses!A$3:A$999)=MONTH(TODAY()))*(YEAR(Expenses!A$3:A$999)=2026)*(Expenses!A$3:A$999<>"")*Expenses!D$3:D$999)

Sheet Grocery Planner
A1: GROCERY PROCUREMENT CALENDAR
A2: Plan purchases · Track daily consumption · Auto reprocurement alerts
A3: Reference Date: | B3: =TODAY() | E3: Monthly Grocery Budget: | I3: ='Monthly Overview GBP'!K18 | K3: Version 5.1 — Multi-purchase pooling
A5: GROCERY BUDGET SNAPSHOT — THIS MONTH
A6: Monthly Budget | C6: ='Monthly Overview GBP'!K18 | E6: Spent This Month | G6: =SUMPRODUCT((TEXT(Expenses!A3:A200,"YYYY-MM")=TEXT(TODAY(),"YYYY-MM"))*(Expenses!C3:C200="Groceries")*IF(ISNUMBER(Expenses!H3:H200),Expenses!H3:H200,0)) | I6: Remaining Budget | K6: =C6-G6 | M6: =COUNTIF(K10:K44,"DEPLETED")+COUNTIF(K10:K44,"TODAY!")+COUNTIF(K10:K44,"URGENT")
A8: GROCERY INVENTORY & PURCHASE LOG (add same item in multiple rows — pooled below)
A9: Item Name | B9: Category | C9: Unit | D9: Qty Purchased | E9: Purchase Date | F9: Price Paid (£) | G9: Daily Consumption (same unit) | H9: Days Supply | I9: Depletion Date | J9: Days Left | K9: Status | L9: Reprocure By | M9: Est. Monthly Cost (£)
A10: Chicken (Whole) | B10: Protein | C10: g | D10: 2000 | E10: 46153 | F10: 12.29 | G10: 400 | H10: =IFERROR(ROUND(D10/G10,0),"") | I10: =IFERROR(DATEVALUE(E10)+H10,"") | J10: =IFERROR(I10-TODAY(),"") | K10: =IFERROR(IF(J10<0,"DEPLETED",IF(J10=0,"TODAY!",IF(J10<=3,"URGENT",IF(J10<=7,"LOW","OK")))),"") | L10: =IFERROR(TEXT(I10,"DD/MM/YYYY"),"") | M10: =IFERROR(ROUND((F10/H10)*30,2),"")
A11: Eggs (30 Pack) | B11: Protein | C11: units | D11: 30 | E11: 46153 | F11: 4.5 | G11: 4 | H11: =IFERROR(ROUND(D11/G11,0),"") | I11: =IFERROR(DATEVALUE(E11)+H11,"") | J11: =IFERROR(I11-TODAY(),"") | K11: =IFERROR(IF(J11<0,"DEPLETED",IF(J11=0,"TODAY!",IF(J11<=3,"URGENT",IF(J11<=7,"LOW","OK")))),"") | L11: =IFERROR(TEXT(I11,"DD/MM/YYYY"),"") | M11: =IFERROR(ROUND((F11/H11)*30,2),"")
A12: Sweet Potatoes | B12: Protein | C12: units | D12: 4 | E12: 46153 | F12: 1.19 | G12: 1 | H12: =IFERROR(ROUND(D12/G12,0),"") | I12: =IFERROR(DATEVALUE(E12)+H12,"") | J12: =IFERROR(I12-TODAY(),"") | K12: =IFERROR(IF(J12<0,"DEPLETED",IF(J12=0,"TODAY!",IF(J12<=3,"URGENT",IF(J12<=7,"LOW","OK")))),"") | L12: =IFERROR(TEXT(I12,"DD/MM/YYYY"),"") | M12: =IFERROR(ROUND((F12/H12)*30,2),"")
A13: Yellow Pepper | B13: Vegetables | C13: units | D13: 2 | E13: 46153 | F13: =1.4-0.22 | G13: 1 | H13: =IFERROR(ROUND(D13/G13,0),"") | I13: =IFERROR(DATEVALUE(E13)+H13,"") | J13: =IFERROR(I13-TODAY(),"") | K13: =IFERROR(IF(J13<0,"DEPLETED",IF(J13=0,"TODAY!",IF(J13<=3,"URGENT",IF(J13<=7,"LOW","OK")))),"") | L13: =IFERROR(TEXT(I13,"DD/MM/YYYY"),"") | M13: =IFERROR(ROUND((F13/H13)*30,2),"")
A14: Full Fat Greek yougurt | B14: Dairy | C14: g | D14: 1000 | E14: 46152 | F14: 2.69 | G14: 200 | H14: =IFERROR(ROUND(D14/G14,0),"") | I14: =IFERROR(DATEVALUE(E14)+H14,"") | J14: =IFERROR(I14-TODAY(),"") | K14: =IFERROR(IF(J14<0,"DEPLETED",IF(J14=0,"TODAY!",IF(J14<=3,"URGENT",IF(J14<=7,"LOW","OK")))),"") | L14: =IFERROR(TEXT(I14,"DD/MM/YYYY"),"") | M14: =IFERROR(ROUND((F14/H14)*30,2),"")
A15: Blueberries | B15: Fruits | C15: g | D15: 350 | E15: 46152 | F15: 2.95 | G15: 50 | H15: =IFERROR(ROUND(D15/G15,0),"") | I15: =IFERROR(DATEVALUE(E15)+H15,"") | J15: =IFERROR(I15-TODAY(),"") | K15: =IFERROR(IF(J15<0,"DEPLETED",IF(J15=0,"TODAY!",IF(J15<=3,"URGENT",IF(J15<=7,"LOW","OK")))),"") | L15: =IFERROR(TEXT(I15,"DD/MM/YYYY"),"") | M15: =IFERROR(ROUND((F15/H15)*30,2),"")
A16: Mango Fruit | B16: Fruits | C16: g | D16: 1000 | E16: 46149 | F16: 3.49 | G16: 100 | H16: =IFERROR(ROUND(D16/G16,0),"") | I16: =IFERROR(DATEVALUE(E16)+H16,"") | J16: =IFERROR(I16-TODAY(),"") | K16: =IFERROR(IF(J16<0,"DEPLETED",IF(J16=0,"TODAY!",IF(J16<=3,"URGENT",IF(J16<=7,"LOW","OK")))),"") | L16: =IFERROR(TEXT(I16,"DD/MM/YYYY"),"") | M16: =IFERROR(ROUND((F16/H16)*30,2),"")
A17: Sweet Corn | B17: Vegetables | C17: units | D17: 8 | E17: 46153 | F17: 3.38 | G17: 1 | H17: =IFERROR(ROUND(D17/G17,0),"") | I17: =IFERROR(DATEVALUE(E17)+H17,"") | J17: =IFERROR(I17-TODAY(),"") | K17: =IFERROR(IF(J17<0,"DEPLETED",IF(J17=0,"TODAY!",IF(J17<=3,"URGENT",IF(J17<=7,"LOW","OK")))),"") | L17: =IFERROR(TEXT(I17,"DD/MM/YYYY"),"") | M17: =IFERROR(ROUND((F17/H17)*30,2),"")
A18: Garden Peas | B18: Vegetables | C18: g | D18: 800 | E18: 46153 | F18: 2.25 | G18: 200 | H18: =IFERROR(ROUND(D18/G18,0),"") | I18: =IFERROR(DATEVALUE(E18)+H18,"") | J18: =IFERROR(I18-TODAY(),"") | K18: =IFERROR(IF(J18<0,"DEPLETED",IF(J18=0,"TODAY!",IF(J18<=3,"URGENT",IF(J18<=7,"LOW","OK")))),"") | L18: =IFERROR(TEXT(I18,"DD/MM/YYYY"),"") | M18: =IFERROR(ROUND((F18/H18)*30,2),"")
A19: Chicken (Whole) | B19: Protein | C19: g | D19: 2000 | E19: 46159 | F19: 12.29 | G19: 400 | H19: =IFERROR(ROUND(D19/G19,0),"") | I19: =IFERROR(DATEVALUE(E19)+H19,"") | J19: =IFERROR(I19-TODAY(),"") | K19: =IFERROR(IF(J19<0,"DEPLETED",IF(J19=0,"TODAY!",IF(J19<=3,"URGENT",IF(J19<=7,"LOW","OK")))),"") | L19: =IFERROR(TEXT(I19,"DD/MM/YYYY"),"")
A20: Garden Peas | B20: Vegetables | C20: g | D20: 800 | E20: 46159 | F20: 2.25 | G20: 200 | H20: =IFERROR(ROUND(D20/G20,0),"") | I20: =IFERROR(DATEVALUE(E20)+H20,"") | J20: =IFERROR(I20-TODAY(),"") | K20: =IFERROR(IF(J20<0,"DEPLETED",IF(J20=0,"TODAY!",IF(J20<=3,"URGENT",IF(J20<=7,"LOW","OK")))),"") | L20: =IFERROR(TEXT(I20,"DD/MM/YYYY"),"") | M20: =IFERROR(ROUND((F20/H20)*30,2),"")
A21: Blueberries | B21: Fruits | C21: g | D21: 350 | E21: 46159 | F21: 2.95 | G21: 50 | H21: =IFERROR(ROUND(D21/G21,0),"") | I21: =IFERROR(DATEVALUE(E21)+H21,"") | J21: =IFERROR(I21-TODAY(),"") | K21: =IFERROR(IF(J21<0,"DEPLETED",IF(J21=0,"TODAY!",IF(J21<=3,"URGENT",IF(J21<=7,"LOW","OK")))),"") | L21: =IFERROR(TEXT(I21,"DD/MM/YYYY"),"") | M21: =IFERROR(ROUND((F21/H21)*30,2),"")
A22: Mango Fruit | B22: Fruits | C22: g | D22: 500 | E22: 46159 | F22: 1.75 | G22: 100 | H22: =IFERROR(ROUND(D22/G22,0),"") | I22: =IFERROR(DATEVALUE(E22)+H22,"") | J22: =IFERROR(I22-TODAY(),"") | K22: =IFERROR(IF(J22<0,"DEPLETED",IF(J22=0,"TODAY!",IF(J22<=3,"URGENT",IF(J22<=7,"LOW","OK")))),"") | L22: =IFERROR(TEXT(I22,"DD/MM/YYYY"),"") | M22: =IFERROR(ROUND((F22/H22)*30,2),"")
A23: Sweet Potatoes | B23: Protein | C23: units | D23: 4 | E23: 46159 | F23: 1.19 | G23: 1 | H23: =IFERROR(ROUND(D23/G23,0),"") | I23: =IFERROR(DATEVALUE(E23)+H23,"") | J23: =IFERROR(I23-TODAY(),"") | K23: =IFERROR(IF(J23<0,"DEPLETED",IF(J23=0,"TODAY!",IF(J23<=3,"URGENT",IF(J23<=7,"LOW","OK")))),"") | L23: =IFERROR(TEXT(I23,"DD/MM/YYYY"),"") | M23: =IFERROR(ROUND((F23/H23)*30,2),"")
H24: =IFERROR(ROUND(D24/G24,0),"") | I24: =IFERROR(DATEVALUE(E24)+H24,"") | J24: =IFERROR(I24-TODAY(),"") | K24: =IFERROR(IF(J24<0,"DEPLETED",IF(J24=0,"TODAY!",IF(J24<=3,"URGENT",IF(J24<=7,"LOW","OK")))),"") | L24: =IFERROR(TEXT(I24,"DD/MM/YYYY"),"") | M24: =IFERROR(ROUND((F24/H24)*30,2),"")
H25: =IFERROR(ROUND(D25/G25,0),"") | I25: =IFERROR(DATEVALUE(E25)+H25,"") | J25: =IFERROR(I25-TODAY(),"") | K25: =IFERROR(IF(J25<0,"DEPLETED",IF(J25=0,"TODAY!",IF(J25<=3,"URGENT",IF(J25<=7,"LOW","OK")))),"") | L25: =IFERROR(TEXT(I25,"DD/MM/YYYY"),"") | M25: =IFERROR(ROUND((F25/H25)*30,2),"")
H26: =IFERROR(ROUND(D26/G26,0),"") | I26: =IFERROR(DATEVALUE(E26)+H26,"") | J26: =IFERROR(I26-TODAY(),"") | K26: =IFERROR(IF(J26<0,"DEPLETED",IF(J26=0,"TODAY!",IF(J26<=3,"URGENT",IF(J26<=7,"LOW","OK")))),"") | L26: =IFERROR(TEXT(I26,"DD/MM/YYYY"),"") | M26: =IFERROR(ROUND((F26/H26)*30,2),"")
H27: =IFERROR(ROUND(D27/G27,0),"") | I27: =IFERROR(DATEVALUE(E27)+H27,"") | J27: =IFERROR(I27-TODAY(),"") | K27: =IFERROR(IF(J27<0,"DEPLETED",IF(J27=0,"TODAY!",IF(J27<=3,"URGENT",IF(J27<=7,"LOW","OK")))),"") | L27: =IFERROR(TEXT(I27,"DD/MM/YYYY"),"") | M27: =IFERROR(ROUND((F27/H27)*30,2),"")
H28: =IFERROR(ROUND(D28/G28,0),"") | I28: =IFERROR(DATEVALUE(E28)+H28,"") | J28: =IFERROR(I28-TODAY(),"") | K28: =IFERROR(IF(J28<0,"DEPLETED",IF(J28=0,"TODAY!",IF(J28<=3,"URGENT",IF(J28<=7,"LOW","OK")))),"") | L28: =IFERROR(TEXT(I28,"DD/MM/YYYY"),"") | M28: =IFERROR(ROUND((F28/H28)*30,2),"")
H29: =IFERROR(ROUND(D29/G29,0),"") | I29: =IFERROR(DATEVALUE(E29)+H29,"") | J29: =IFERROR(I29-TODAY(),"") | K29: =IFERROR(IF(J29<0,"DEPLETED",IF(J29=0,"TODAY!",IF(J29<=3,"URGENT",IF(J29<=7,"LOW","OK")))),"") | L29: =IFERROR(TEXT(I29,"DD/MM/YYYY"),"") | M29: =IFERROR(ROUND((F29/H29)*30,2),"")
H30: =IFERROR(ROUND(D30/G30,0),"") | I30: =IFERROR(DATEVALUE(E30)+H30,"") | J30: =IFERROR(I30-TODAY(),"") | K30: =IFERROR(IF(J30<0,"DEPLETED",IF(J30=0,"TODAY!",IF(J30<=3,"URGENT",IF(J30<=7,"LOW","OK")))),"") | L30: =IFERROR(TEXT(I30,"DD/MM/YYYY"),"") | M30: =IFERROR(ROUND((F30/H30)*30,2),"")
H31: =IFERROR(ROUND(D31/G31,0),"") | I31: =IFERROR(DATEVALUE(E31)+H31,"") | J31: =IFERROR(I31-TODAY(),"") | K31: =IFERROR(IF(J31<0,"DEPLETED",IF(J31=0,"TODAY!",IF(J31<=3,"URGENT",IF(J31<=7,"LOW","OK")))),"") | L31: =IFERROR(TEXT(I31,"DD/MM/YYYY"),"") | M31: =IFERROR(ROUND((F31/H31)*30,2),"")
H32: =IFERROR(ROUND(D32/G32,0),"") | I32: =IFERROR(DATEVALUE(E32)+H32,"") | J32: =IFERROR(I32-TODAY(),"") | K32: =IFERROR(IF(J32<0,"DEPLETED",IF(J32=0,"TODAY!",IF(J32<=3,"URGENT",IF(J32<=7,"LOW","OK")))),"") | L32: =IFERROR(TEXT(I32,"DD/MM/YYYY"),"") | M32: =IFERROR(ROUND((F32/H32)*30,2),"")
H33: =IFERROR(ROUND(D33/G33,0),"") | I33: =IFERROR(DATEVALUE(E33)+H33,"") | J33: =IFERROR(I33-TODAY(),"") | K33: =IFERROR(IF(J33<0,"DEPLETED",IF(J33=0,"TODAY!",IF(J33<=3,"URGENT",IF(J33<=7,"LOW","OK")))),"") | L33: =IFERROR(TEXT(I33,"DD/MM/YYYY"),"") | M33: =IFERROR(ROUND((F33/H33)*30,2),"")
H34: =IFERROR(ROUND(D34/G34,0),"") | I34: =IFERROR(DATEVALUE(E34)+H34,"") | J34: =IFERROR(I34-TODAY(),"") | K34: =IFERROR(IF(J34<0,"DEPLETED",IF(J34=0,"TODAY!",IF(J34<=3,"URGENT",IF(J34<=7,"LOW","OK")))),"") | L34: =IFERROR(TEXT(I34,"DD/MM/YYYY"),"") | M34: =IFERROR(ROUND((F34/H34)*30,2),"")
H35: =IFERROR(ROUND(D35/G35,0),"") | I35: =IFERROR(DATEVALUE(E35)+H35,"") | J35: =IFERROR(I35-TODAY(),"") | K35: =IFERROR(IF(J35<0,"DEPLETED",IF(J35=0,"TODAY!",IF(J35<=3,"URGENT",IF(J35<=7,"LOW","OK")))),"") | L35: =IFERROR(TEXT(I35,"DD/MM/YYYY"),"") | M35: =IFERROR(ROUND((F35/H35)*30,2),"")
... H44: =IFERROR(ROUND(D44/G44,0),"") | I44: =IFERROR(DATEVALUE(E44)+H44,"") | J44: =IFERROR(I44-TODAY(),"") | K44: =IFERROR(IF(J44<0,"DEPLETED",IF(J44=0,"TODAY!",IF(J44<=3,"URGENT",IF(J44<=7,"LOW","OK")))),"") | L44: =IFERROR(TEXT(I44,"DD/MM/YYYY"),"") | M44: =IFERROR(ROUND((F44/H44)*30,2),"")
A46: CONSOLIDATED ITEM SUMMARY — same item across multiple rows is pooled here
A47: Enter each unique item name once below (must match spelling in the log above). Remaining stock = Σ MAX(0, Qty − DailyRate × days elapsed) across ALL matching rows.
A48: Item Name (type to match) | B48: Purchases Logged | C48: Unit | D48: Total Qty Bought | E48: Daily Rate | F48: Total Stock Remaining | G48: Days Left | H48: Depletion Date | I48: Status | J48: Avg Cost /Unit (£) | K48: Est. Monthly Cost (£) | L48: Next Procure By | M48: Notes
A49: Chicken (Whole) | B49: =IFERROR(COUNTIF($A$10:$A$44,A49),"") | C49: =IFERROR(INDEX($C$10:$C$44,MATCH(A49,$A$10:$A$44,0)),"") | D49: =IFERROR(SUMIF($A$10:$A$44,A49,$D$10:$D$44),"") | E49: =IFERROR(INDEX($G$10:$G$44,MATCH(A49,$A$10:$A$44,0)),"") | F49: =IFERROR(SUMPRODUCT(($A$10:$A$44=A49)*IF($D$10:$D$44-$G$10:$G$44*(TODAY()-IFERROR(DATEVALUE($E$10:$E$44),TODAY()))>0,$D$10:$D$44-$G$10:$G$44*(TODAY()-IFERROR(DATEVALUE($E$10:$E$44),TODAY())),0)),"") | G49: =IFERROR(ROUND(F49/E49,0),"") | H49: =IFERROR(TODAY()+G49,"") | I49: =IFERROR(IF(G49<0,"DEPLETED",IF(G49=0,"TODAY!",IF(G49<=3,"URGENT",IF(G49<=7,"LOW","OK")))),"") | J49: =IFERROR(SUMIF($A$10:$A$44,A49,$F$10:$F$44)/SUMIF($A$10:$A$44,A49,$D$10:$D$44),"") | K49: =IFERROR(ROUND(E49*30*J49,2),"") | L49: =IFERROR(TEXT(H49,"DD/MM/YYYY"),"")
A50: Basmati Rice | B50: =IFERROR(COUNTIF($A$10:$A$44,A50),"") | C50: =IFERROR(INDEX($C$10:$C$44,MATCH(A50,$A$10:$A$44,0)),"") | D50: =IFERROR(SUMIF($A$10:$A$44,A50,$D$10:$D$44),"") | E50: =IFERROR(INDEX($G$10:$G$44,MATCH(A50,$A$10:$A$44,0)),"") | F50: =IFERROR(SUMPRODUCT(($A$10:$A$44=A50)*IF($D$10:$D$44-$G$10:$G$44*(TODAY()-IFERROR(DATEVALUE($E$10:$E$44),TODAY()))>0,$D$10:$D$44-$G$10:$G$44*(TODAY()-IFERROR(DATEVALUE($E$10:$E$44),TODAY())),0)),"") | G50: =IFERROR(ROUND(F50/E50,0),"") | H50: =IFERROR(TODAY()+G50,"") | I50: =IFERROR(IF(G50<0,"DEPLETED",IF(G50=0,"TODAY!",IF(G50<=3,"URGENT",IF(G50<=7,"LOW","OK")))),"") | J50: =IFERROR(SUMIF($A$10:$A$44,A50,$F$10:$F$44)/SUMIF($A$10:$A$44,A50,$D$10:$D$44),"") | K50: =IFERROR(ROUND(E50*30*J50,2),"") | L50: =IFERROR(TEXT(H50,"DD/MM/YYYY"),"")
A51: Eggs (30 Pack) | B51: =IFERROR(COUNTIF($A$10:$A$44,A51),"") | C51: =IFERROR(INDEX($C$10:$C$44,MATCH(A51,$A$10:$A$44,0)),"") | D51: =IFERROR(SUMIF($A$10:$A$44,A51,$D$10:$D$44),"") | E51: =IFERROR(INDEX($G$10:$G$44,MATCH(A51,$A$10:$A$44,0)),"") | F51: =IFERROR(SUMPRODUCT(($A$10:$A$44=A51)*IF($D$10:$D$44-$G$10:$G$44*(TODAY()-IFERROR(DATEVALUE($E$10:$E$44),TODAY()))>0,$D$10:$D$44-$G$10:$G$44*(TODAY()-IFERROR(DATEVALUE($E$10:$E$44),TODAY())),0)),"") | G51: =IFERROR(ROUND(F51/E51,0),"") | H51: =IFERROR(TODAY()+G51,"") | I51: =IFERROR(IF(G51<0,"DEPLETED",IF(G51=0,"TODAY!",IF(G51<=3,"URGENT",IF(G51<=7,"LOW","OK")))),"") | J51: =IFERROR(SUMIF($A$10:$A$44,A51,$F$10:$F$44)/SUMIF($A$10:$A$44,A51,$D$10:$D$44),"") | K51: =IFERROR(ROUND(E51*30*J51,2),"") | L51: =IFERROR(TEXT(H51,"DD/MM/YYYY"),"")
A52: Onions | B52: =IFERROR(COUNTIF($A$10:$A$44,A52),"") | C52: =IFERROR(INDEX($C$10:$C$44,MATCH(A52,$A$10:$A$44,0)),"") | D52: =IFERROR(SUMIF($A$10:$A$44,A52,$D$10:$D$44),"") | E52: =IFERROR(INDEX($G$10:$G$44,MATCH(A52,$A$10:$A$44,0)),"") | F52: =IFERROR(SUMPRODUCT(($A$10:$A$44=A52)*IF($D$10:$D$44-$G$10:$G$44*(TODAY()-IFERROR(DATEVALUE($E$10:$E$44),TODAY()))>0,$D$10:$D$44-$G$10:$G$44*(TODAY()-IFERROR(DATEVALUE($E$10:$E$44),TODAY())),0)),"") | G52: =IFERROR(ROUND(F52/E52,0),"") | H52: =IFERROR(TODAY()+G52,"") | I52: =IFERROR(IF(G52<0,"DEPLETED",IF(G52=0,"TODAY!",IF(G52<=3,"URGENT",IF(G52<=7,"LOW","OK")))),"") | J52: =IFERROR(SUMIF($A$10:$A$44,A52,$F$10:$F$44)/SUMIF($A$10:$A$44,A52,$D$10:$D$44),"") | K52: =IFERROR(ROUND(E52*30*J52,2),"") | L52: =IFERROR(TEXT(H52,"DD/MM/YYYY"),"")
A53: Full Fat Milk | B53: =IFERROR(COUNTIF($A$10:$A$44,A53),"") | C53: =IFERROR(INDEX($C$10:$C$44,MATCH(A53,$A$10:$A$44,0)),"") | D53: =IFERROR(SUMIF($A$10:$A$44,A53,$D$10:$D$44),"") | E53: =IFERROR(INDEX($G$10:$G$44,MATCH(A53,$A$10:$A$44,0)),"") | F53: =IFERROR(SUMPRODUCT(($A$10:$A$44=A53)*IF($D$10:$D$44-$G$10:$G$44*(TODAY()-IFERROR(DATEVALUE($E$10:$E$44),TODAY()))>0,$D$10:$D$44-$G$10:$G$44*(TODAY()-IFERROR(DATEVALUE($E$10:$E$44),TODAY())),0)),"") | G53: =IFERROR(ROUND(F53/E53,0),"") | H53: =IFERROR(TODAY()+G53,"") | I53: =IFERROR(IF(G53<0,"DEPLETED",IF(G53=0,"TODAY!",IF(G53<=3,"URGENT",IF(G53<=7,"LOW","OK")))),"") | J53: =IFERROR(SUMIF($A$10:$A$44,A53,$F$10:$F$44)/SUMIF($A$10:$A$44,A53,$D$10:$D$44),"") | K53: =IFERROR(ROUND(E53*30*J53,2),"") | L53: =IFERROR(TEXT(H53,"DD/MM/YYYY"),"")
A54: Brown Bread | B54: =IFERROR(COUNTIF($A$10:$A$44,A54),"") | C54: =IFERROR(INDEX($C$10:$C$44,MATCH(A54,$A$10:$A$44,0)),"") | D54: =IFERROR(SUMIF($A$10:$A$44,A54,$D$10:$D$44),"") | E54: =IFERROR(INDEX($G$10:$G$44,MATCH(A54,$A$10:$A$44,0)),"") | F54: =IFERROR(SUMPRODUCT(($A$10:$A$44=A54)*IF($D$10:$D$44-$G$10:$G$44*(TODAY()-IFERROR(DATEVALUE($E$10:$E$44),TODAY()))>0,$D$10:$D$44-$G$10:$G$44*(TODAY()-IFERROR(DATEVALUE($E$10:$E$44),TODAY())),0)),"") | G54: =IFERROR(ROUND(F54/E54,0),"") | H54: =IFERROR(TODAY()+G54,"") | I54: =IFERROR(IF(G54<0,"DEPLETED",IF(G54=0,"TODAY!",IF(G54<=3,"URGENT",IF(G54<=7,"LOW","OK")))),"") | J54: =IFERROR(SUMIF($A$10:$A$44,A54,$F$10:$F$44)/SUMIF($A$10:$A$44,A54,$D$10:$D$44),"") | K54: =IFERROR(ROUND(E54*30*J54,2),"") | L54: =IFERROR(TEXT(H54,"DD/MM/YYYY"),"")
A55: Tomatoes | B55: =IFERROR(COUNTIF($A$10:$A$44,A55),"") | C55: =IFERROR(INDEX($C$10:$C$44,MATCH(A55,$A$10:$A$44,0)),"") | D55: =IFERROR(SUMIF($A$10:$A$44,A55,$D$10:$D$44),"") | E55: =IFERROR(INDEX($G$10:$G$44,MATCH(A55,$A$10:$A$44,0)),"") | F55: =IFERROR(SUMPRODUCT(($A$10:$A$44=A55)*IF($D$10:$D$44-$G$10:$G$44*(TODAY()-IFERROR(DATEVALUE($E$10:$E$44),TODAY()))>0,$D$10:$D$44-$G$10:$G$44*(TODAY()-IFERROR(DATEVALUE($E$10:$E$44),TODAY())),0)),"") | G55: =IFERROR(ROUND(F55/E55,0),"") | H55: =IFERROR(TODAY()+G55,"") | I55: =IFERROR(IF(G55<0,"DEPLETED",IF(G55=0,"TODAY!",IF(G55<=3,"URGENT",IF(G55<=7,"LOW","OK")))),"") | J55: =IFERROR(SUMIF($A$10:$A$44,A55,$F$10:$F$44)/SUMIF($A$10:$A$44,A55,$D$10:$D$44),"") | K55: =IFERROR(ROUND(E55*30*J55,2),"") | L55: =IFERROR(TEXT(H55,"DD/MM/YYYY"),"")
A56: Greek Yogurt | B56: =IFERROR(COUNTIF($A$10:$A$44,A56),"") | C56: =IFERROR(INDEX($C$10:$C$44,MATCH(A56,$A$10:$A$44,0)),"") | D56: =IFERROR(SUMIF($A$10:$A$44,A56,$D$10:$D$44),"") | E56: =IFERROR(INDEX($G$10:$G$44,MATCH(A56,$A$10:$A$44,0)),"") | F56: =IFERROR(SUMPRODUCT(($A$10:$A$44=A56)*IF($D$10:$D$44-$G$10:$G$44*(TODAY()-IFERROR(DATEVALUE($E$10:$E$44),TODAY()))>0,$D$10:$D$44-$G$10:$G$44*(TODAY()-IFERROR(DATEVALUE($E$10:$E$44),TODAY())),0)),"") | G56: =IFERROR(ROUND(F56/E56,0),"") | H56: =IFERROR(TODAY()+G56,"") | I56: =IFERROR(IF(G56<0,"DEPLETED",IF(G56=0,"TODAY!",IF(G56<=3,"URGENT",IF(G56<=7,"LOW","OK")))),"") | J56: =IFERROR(SUMIF($A$10:$A$44,A56,$F$10:$F$44)/SUMIF($A$10:$A$44,A56,$D$10:$D$44),"") | K56: =IFERROR(ROUND(E56*30*J56,2),"") | L56: =IFERROR(TEXT(H56,"DD/MM/YYYY"),"")
A57: Olive Oil | B57: =IFERROR(COUNTIF($A$10:$A$44,A57),"") | C57: =IFERROR(INDEX($C$10:$C$44,MATCH(A57,$A$10:$A$44,0)),"") | D57: =IFERROR(SUMIF($A$10:$A$44,A57,$D$10:$D$44),"") | E57: =IFERROR(INDEX($G$10:$G$44,MATCH(A57,$A$10:$A$44,0)),"") | F57: =IFERROR(SUMPRODUCT(($A$10:$A$44=A57)*IF($D$10:$D$44-$G$10:$G$44*(TODAY()-IFERROR(DATEVALUE($E$10:$E$44),TODAY()))>0,$D$10:$D$44-$G$10:$G$44*(TODAY()-IFERROR(DATEVALUE($E$10:$E$44),TODAY())),0)),"") | G57: =IFERROR(ROUND(F57/E57,0),"") | H57: =IFERROR(TODAY()+G57,"") | I57: =IFERROR(IF(G57<0,"DEPLETED",IF(G57=0,"TODAY!",IF(G57<=3,"URGENT",IF(G57<=7,"LOW","OK")))),"") | J57: =IFERROR(SUMIF($A$10:$A$44,A57,$F$10:$F$44)/SUMIF($A$10:$A$44,A57,$D$10:$D$44),"") | K57: =IFERROR(ROUND(E57*30*J57,2),"") | L57: =IFERROR(TEXT(H57,"DD/MM/YYYY"),"")
A58: Garlic | B58: =IFERROR(COUNTIF($A$10:$A$44,A58),"") | C58: =IFERROR(INDEX($C$10:$C$44,MATCH(A58,$A$10:$A$44,0)),"") | D58: =IFERROR(SUMIF($A$10:$A$44,A58,$D$10:$D$44),"") | E58: =IFERROR(INDEX($G$10:$G$44,MATCH(A58,$A$10:$A$44,0)),"") | F58: =IFERROR(SUMPRODUCT(($A$10:$A$44=A58)*IF($D$10:$D$44-$G$10:$G$44*(TODAY()-IFERROR(DATEVALUE($E$10:$E$44),TODAY()))>0,$D$10:$D$44-$G$10:$G$44*(TODAY()-IFERROR(DATEVALUE($E$10:$E$44),TODAY())),0)),"") | G58: =IFERROR(ROUND(F58/E58,0),"") | H58: =IFERROR(TODAY()+G58,"") | I58: =IFERROR(IF(G58<0,"DEPLETED",IF(G58=0,"TODAY!",IF(G58<=3,"URGENT",IF(G58<=7,"LOW","OK")))),"") | J58: =IFERROR(SUMIF($A$10:$A$44,A58,$F$10:$F$44)/SUMIF($A$10:$A$44,A58,$D$10:$D$44),"") | K58: =IFERROR(ROUND(E58*30*J58,2),"") | L58: =IFERROR(TEXT(H58,"DD/MM/YYYY"),"")
B59: =IFERROR(COUNTIF($A$10:$A$44,A59),"") | C59: =IFERROR(INDEX($C$10:$C$44,MATCH(A59,$A$10:$A$44,0)),"") | D59: =IFERROR(SUMIF($A$10:$A$44,A59,$D$10:$D$44),"") | E59: =IFERROR(INDEX($G$10:$G$44,MATCH(A59,$A$10:$A$44,0)),"") | F59: =IFERROR(SUMPRODUCT(($A$10:$A$44=A59)*IF($D$10:$D$44-$G$10:$G$44*(TODAY()-IFERROR(DATEVALUE($E$10:$E$44),TODAY()))>0,$D$10:$D$44-$G$10:$G$44*(TODAY()-IFERROR(DATEVALUE($E$10:$E$44),TODAY())),0)),"") | G59: =IFERROR(ROUND(F59/E59,0),"") | H59: =IFERROR(TODAY()+G59,"") | I59: =IFERROR(IF(G59<0,"DEPLETED",IF(G59=0,"TODAY!",IF(G59<=3,"URGENT",IF(G59<=7,"LOW","OK")))),"") | J59: =IFERROR(SUMIF($A$10:$A$44,A59,$F$10:$F$44)/SUMIF($A$10:$A$44,A59,$D$10:$D$44),"") | K59: =IFERROR(ROUND(E59*30*J59,2),"") | L59: =IFERROR(TEXT(H59,"DD/MM/YYYY"),"")
B60: =IFERROR(COUNTIF($A$10:$A$44,A60),"") | C60: =IFERROR(INDEX($C$10:$C$44,MATCH(A60,$A$10:$A$44,0)),"") | D60: =IFERROR(SUMIF($A$10:$A$44,A60,$D$10:$D$44),"") | E60: =IFERROR(INDEX($G$10:$G$44,MATCH(A60,$A$10:$A$44,0)),"") | F60: =IFERROR(SUMPRODUCT(($A$10:$A$44=A60)*IF($D$10:$D$44-$G$10:$G$44*(TODAY()-IFERROR(DATEVALUE($E$10:$E$44),TODAY()))>0,$D$10:$D$44-$G$10:$G$44*(TODAY()-IFERROR(DATEVALUE($E$10:$E$44),TODAY())),0)),"") | G60: =IFERROR(ROUND(F60/E60,0),"") | H60: =IFERROR(TODAY()+G60,"") | I60: =IFERROR(IF(G60<0,"DEPLETED",IF(G60=0,"TODAY!",IF(G60<=3,"URGENT",IF(G60<=7,"LOW","OK")))),"") | J60: =IFERROR(SUMIF($A$10:$A$44,A60,$F$10:$F$44)/SUMIF($A$10:$A$44,A60,$D$10:$D$44),"") | K60: =IFERROR(ROUND(E60*30*J60,2),"") | L60: =IFERROR(TEXT(H60,"DD/MM/YYYY"),"")
B61: =IFERROR(COUNTIF($A$10:$A$44,A61),"") | C61: =IFERROR(INDEX($C$10:$C$44,MATCH(A61,$A$10:$A$44,0)),"") | D61: =IFERROR(SUMIF($A$10:$A$44,A61,$D$10:$D$44),"") | E61: =IFERROR(INDEX($G$10:$G$44,MATCH(A61,$A$10:$A$44,0)),"") | F61: =IFERROR(SUMPRODUCT(($A$10:$A$44=A61)*IF($D$10:$D$44-$G$10:$G$44*(TODAY()-IFERROR(DATEVALUE($E$10:$E$44),TODAY()))>0,$D$10:$D$44-$G$10:$G$44*(TODAY()-IFERROR(DATEVALUE($E$10:$E$44),TODAY())),0)),"") | G61: =IFERROR(ROUND(F61/E61,0),"") | H61: =IFERROR(TODAY()+G61,"") | I61: =IFERROR(IF(G61<0,"DEPLETED",IF(G61=0,"TODAY!",IF(G61<=3,"URGENT",IF(G61<=7,"LOW","OK")))),"") | J61: =IFERROR(SUMIF($A$10:$A$44,A61,$F$10:$F$44)/SUMIF($A$10:$A$44,A61,$D$10:$D$44),"") | K61: =IFERROR(ROUND(E61*30*J61,2),"") | L61: =IFERROR(TEXT(H61,"DD/MM/YYYY"),"")
B62: =IFERROR(COUNTIF($A$10:$A$44,A62),"") | C62: =IFERROR(INDEX($C$10:$C$44,MATCH(A62,$A$10:$A$44,0)),"") | D62: =IFERROR(SUMIF($A$10:$A$44,A62,$D$10:$D$44),"") | E62: =IFERROR(INDEX($G$10:$G$44,MATCH(A62,$A$10:$A$44,0)),"") | F62: =IFERROR(SUMPRODUCT(($A$10:$A$44=A62)*IF($D$10:$D$44-$G$10:$G$44*(TODAY()-IFERROR(DATEVALUE($E$10:$E$44),TODAY()))>0,$D$10:$D$44-$G$10:$G$44*(TODAY()-IFERROR(DATEVALUE($E$10:$E$44),TODAY())),0)),"") | G62: =IFERROR(ROUND(F62/E62,0),"") | H62: =IFERROR(TODAY()+G62,"") | I62: =IFERROR(IF(G62<0,"DEPLETED",IF(G62=0,"TODAY!",IF(G62<=3,"URGENT",IF(G62<=7,"LOW","OK")))),"") | J62: =IFERROR(SUMIF($A$10:$A$44,A62,$F$10:$F$44)/SUMIF($A$10:$A$44,A62,$D$10:$D$44),"") | K62: =IFERROR(ROUND(E62*30*J62,2),"") | L62: =IFERROR(TEXT(H62,"DD/MM/YYYY"),"")
B63: =IFERROR(COUNTIF($A$10:$A$44,A63),"") | C63: =IFERROR(INDEX($C$10:$C$44,MATCH(A63,$A$10:$A$44,0)),"") | D63: =IFERROR(SUMIF($A$10:$A$44,A63,$D$10:$D$44),"") | E63: =IFERROR(INDEX($G$10:$G$44,MATCH(A63,$A$10:$A$44,0)),"") | F63: =IFERROR(SUMPRODUCT(($A$10:$A$44=A63)*IF($D$10:$D$44-$G$10:$G$44*(TODAY()-IFERROR(DATEVALUE($E$10:$E$44),TODAY()))>0,$D$10:$D$44-$G$10:$G$44*(TODAY()-IFERROR(DATEVALUE($E$10:$E$44),TODAY())),0)),"") | G63: =IFERROR(ROUND(F63/E63,0),"") | H63: =IFERROR(TODAY()+G63,"") | I63: =IFERROR(IF(G63<0,"DEPLETED",IF(G63=0,"TODAY!",IF(G63<=3,"URGENT",IF(G63<=7,"LOW","OK")))),"") | J63: =IFERROR(SUMIF($A$10:$A$44,A63,$F$10:$F$44)/SUMIF($A$10:$A$44,A63,$D$10:$D$44),"") | K63: =IFERROR(ROUND(E63*30*J63,2),"") | L63: =IFERROR(TEXT(H63,"DD/MM/YYYY"),"")
A66: 📅 MONTHLY PROCUREMENT CALENDAR — MAY 2026
A67: Highlighted = items depleting that day | RED = urgent/depleted | AMBER = 1–3 days | YELLOW = 4–7 days
A68: Week | B68: MON | C68: TUE | D68: WED | E68: THU | F68: FRI | G68: SAT | H68: SUN
A69: W1 | F69: 1 | G69: 2 | H69: 3
F70: =IFERROR(TEXTJOIN(", ",TRUE,IF(INT($I$10:$I$44)=DATE(2026,5,1),$A$10:$A$44,"")),"—") | G70: =IFERROR(TEXTJOIN(", ",TRUE,IF(INT($I$10:$I$44)=DATE(2026,5,2),$A$10:$A$44,"")),"—") | H70: =IFERROR(TEXTJOIN(", ",TRUE,IF(INT($I$10:$I$44)=DATE(2026,5,3),$A$10:$A$44,"")),"—")
A71: W2 | B71: 4 | C71: 5 | D71: 6 | E71: 7 | F71: 8 | G71: 9 | H71: 10
B72: =IFERROR(TEXTJOIN(", ",TRUE,IF(INT($I$10:$I$44)=DATE(2026,5,4),$A$10:$A$44,"")),"—") | C72: =IFERROR(TEXTJOIN(", ",TRUE,IF(INT($I$10:$I$44)=DATE(2026,5,5),$A$10:$A$44,"")),"—") | D72: =IFERROR(TEXTJOIN(", ",TRUE,IF(INT($I$10:$I$44)=DATE(2026,5,6),$A$10:$A$44,"")),"—") | E72: =IFERROR(TEXTJOIN(", ",TRUE,IF(INT($I$10:$I$44)=DATE(2026,5,7),$A$10:$A$44,"")),"—") | F72: =IFERROR(TEXTJOIN(", ",TRUE,IF(INT($I$10:$I$44)=DATE(2026,5,8),$A$10:$A$44,"")),"—") | G72: =IFERROR(TEXTJOIN(", ",TRUE,IF(INT($I$10:$I$44)=DATE(2026,5,9),$A$10:$A$44,"")),"—") | H72: =IFERROR(TEXTJOIN(", ",TRUE,IF(INT($I$10:$I$44)=DATE(2026,5,10),$A$10:$A$44,"")),"—")
A73: W3 | B73: 11 | C73: 12 | D73: 13 | E73: 14 | F73: 15 | G73: 16 | H73: 17
B74: =IFERROR(TEXTJOIN(", ",TRUE,IF(INT($I$10:$I$44)=DATE(2026,5,11),$A$10:$A$44,"")),"—") | C74: =IFERROR(TEXTJOIN(", ",TRUE,IF(INT($I$10:$I$44)=DATE(2026,5,12),$A$10:$A$44,"")),"—") | D74: =IFERROR(TEXTJOIN(", ",TRUE,IF(INT($I$10:$I$44)=DATE(2026,5,13),$A$10:$A$44,"")),"—") | E74: =IFERROR(TEXTJOIN(", ",TRUE,IF(INT($I$10:$I$44)=DATE(2026,5,14),$A$10:$A$44,"")),"—") | F74: =IFERROR(TEXTJOIN(", ",TRUE,IF(INT($I$10:$I$44)=DATE(2026,5,15),$A$10:$A$44,"")),"—") | G74: =IFERROR(TEXTJOIN(", ",TRUE,IF(INT($I$10:$I$44)=DATE(2026,5,16),$A$10:$A$44,"")),"—") | H74: =IFERROR(TEXTJOIN(", ",TRUE,IF(INT($I$10:$I$44)=DATE(2026,5,17),$A$10:$A$44,"")),"—")
A75: W4 | B75: 18 | C75: 19 | D75: 20 | E75: 21 | F75: 22 | G75: 23 | H75: 24
B76: =IFERROR(TEXTJOIN(", ",TRUE,IF(INT($I$10:$I$44)=DATE(2026,5,18),$A$10:$A$44,"")),"—") | C76: =IFERROR(TEXTJOIN(", ",TRUE,IF(INT($I$10:$I$44)=DATE(2026,5,19),$A$10:$A$44,"")),"—") | D76: =IFERROR(TEXTJOIN(", ",TRUE,IF(INT($I$10:$I$44)=DATE(2026,5,20),$A$10:$A$44,"")),"—") | E76: =IFERROR(TEXTJOIN(", ",TRUE,IF(INT($I$10:$I$44)=DATE(2026,5,21),$A$10:$A$44,"")),"—") | F76: =IFERROR(TEXTJOIN(", ",TRUE,IF(INT($I$10:$I$44)=DATE(2026,5,22),$A$10:$A$44,"")),"—") | G76: =IFERROR(TEXTJOIN(", ",TRUE,IF(INT($I$10:$I$44)=DATE(2026,5,23),$A$10:$A$44,"")),"—") | H76: =IFERROR(TEXTJOIN(", ",TRUE,IF(INT($I$10:$I$44)=DATE(2026,5,24),$A$10:$A$44,"")),"—")
A77: W5 | B77: 25 | C77: 26 | D77: 27 | E77: 28 | F77: 29 | G77: 30 | H77: 31
B78: =IFERROR(TEXTJOIN(", ",TRUE,IF(INT($I$10:$I$44)=DATE(2026,5,25),$A$10:$A$44,"")),"—") | C78: =IFERROR(TEXTJOIN(", ",TRUE,IF(INT($I$10:$I$44)=DATE(2026,5,26),$A$10:$A$44,"")),"—") | D78: =IFERROR(TEXTJOIN(", ",TRUE,IF(INT($I$10:$I$44)=DATE(2026,5,27),$A$10:$A$44,"")),"—") | E78: =IFERROR(TEXTJOIN(", ",TRUE,IF(INT($I$10:$I$44)=DATE(2026,5,28),$A$10:$A$44,"")),"—") | F78: =IFERROR(TEXTJOIN(", ",TRUE,IF(INT($I$10:$I$44)=DATE(2026,5,29),$A$10:$A$44,"")),"—") | G78: =IFERROR(TEXTJOIN(", ",TRUE,IF(INT($I$10:$I$44)=DATE(2026,5,30),$A$10:$A$44,"")),"—") | H78: =IFERROR(TEXTJOIN(", ",TRUE,IF(INT($I$10:$I$44)=DATE(2026,5,31),$A$10:$A$44,"")),"—")
A81: UPCOMING PROCUREMENT ALERTS — SORTED BY URGENCY (uses Consolidated totals)
A82: Item | B82: Status | C82: Days Left | D82: Depletion Date | E82: Unit | F82: Daily Rate | G82: Est. Monthly Cost | H82: Category
A83: {=IFERROR(INDEX($A$49:$A$63,MATCH(SMALL(IF(ISNUMBER($G$49:$G$63),$G$49:$G$63),1),$G$49:$G$63,0)),"")} | B83: {=IFERROR(INDEX($I$49:$I$63,MATCH(SMALL(IF(ISNUMBER($G$49:$G$63),$G$49:$G$63),1),$G$49:$G$63,0)),"")} | C83: =IFERROR(SMALL(IF(ISNUMBER($G$49:$G$63),$G$49:$G$63),1),"") | D83: =IFERROR(TODAY()+SMALL(IF(ISNUMBER($G$49:$G$63),$G$49:$G$63),1),"") | E83: {=IFERROR(INDEX($C$49:$C$63,MATCH(SMALL(IF(ISNUMBER($G$49:$G$63),$G$49:$G$63),1),$G$49:$G$63,0)),"")} | F83: {=IFERROR(INDEX($E$49:$E$63,MATCH(SMALL(IF(ISNUMBER($G$49:$G$63),$G$49:$G$63),1),$G$49:$G$63,0)),"")} | G83: {=IFERROR(INDEX($K$49:$K$63,MATCH(SMALL(IF(ISNUMBER($G$49:$G$63),$G$49:$G$63),1),$G$49:$G$63,0)),"")} | H83: {=IFERROR(INDEX($B$10:$B$44,MATCH(INDEX($A$49:$A$63,MATCH(SMALL(IF(ISNUMBER($G$49:$G$63),$G$49:$G$63),1),$G$49:$G$63,0)),$A$10:$A$44,0)),"")}
A84: {=IFERROR(INDEX($A$49:$A$63,MATCH(SMALL(IF(ISNUMBER($G$49:$G$63),$G$49:$G$63),2),$G$49:$G$63,0)),"")} | B84: {=IFERROR(INDEX($I$49:$I$63,MATCH(SMALL(IF(ISNUMBER($G$49:$G$63),$G$49:$G$63),2),$G$49:$G$63,0)),"")} | C84: =IFERROR(SMALL(IF(ISNUMBER($G$49:$G$63),$G$49:$G$63),2),"") | D84: =IFERROR(TODAY()+SMALL(IF(ISNUMBER($G$49:$G$63),$G$49:$G$63),2),"") | E84: {=IFERROR(INDEX($C$49:$C$63,MATCH(SMALL(IF(ISNUMBER($G$49:$G$63),$G$49:$G$63),2),$G$49:$G$63,0)),"")} | F84: {=IFERROR(INDEX($E$49:$E$63,MATCH(SMALL(IF(ISNUMBER($G$49:$G$63),$G$49:$G$63),2),$G$49:$G$63,0)),"")} | G84: {=IFERROR(INDEX($K$49:$K$63,MATCH(SMALL(IF(ISNUMBER($G$49:$G$63),$G$49:$G$63),2),$G$49:$G$63,0)),"")} | H84: {=IFERROR(INDEX($B$10:$B$44,MATCH(INDEX($A$49:$A$63,MATCH(SMALL(IF(ISNUMBER($G$49:$G$63),$G$49:$G$63),2),$G$49:$G$63,0)),$A$10:$A$44,0)),"")}
A85: {=IFERROR(INDEX($A$49:$A$63,MATCH(SMALL(IF(ISNUMBER($G$49:$G$63),$G$49:$G$63),3),$G$49:$G$63,0)),"")} | B85: {=IFERROR(INDEX($I$49:$I$63,MATCH(SMALL(IF(ISNUMBER($G$49:$G$63),$G$49:$G$63),3),$G$49:$G$63,0)),"")} | C85: =IFERROR(SMALL(IF(ISNUMBER($G$49:$G$63),$G$49:$G$63),3),"") | D85: =IFERROR(TODAY()+SMALL(IF(ISNUMBER($G$49:$G$63),$G$49:$G$63),3),"") | E85: {=IFERROR(INDEX($C$49:$C$63,MATCH(SMALL(IF(ISNUMBER($G$49:$G$63),$G$49:$G$63),3),$G$49:$G$63,0)),"")} | F85: {=IFERROR(INDEX($E$49:$E$63,MATCH(SMALL(IF(ISNUMBER($G$49:$G$63),$G$49:$G$63),3),$G$49:$G$63,0)),"")} | G85: {=IFERROR(INDEX($K$49:$K$63,MATCH(SMALL(IF(ISNUMBER($G$49:$G$63),$G$49:$G$63),3),$G$49:$G$63,0)),"")} | H85: {=IFERROR(INDEX($B$10:$B$44,MATCH(INDEX($A$49:$A$63,MATCH(SMALL(IF(ISNUMBER($G$49:$G$63),$G$49:$G$63),3),$G$49:$G$63,0)),$A$10:$A$44,0)),"")}
A86: {=IFERROR(INDEX($A$49:$A$63,MATCH(SMALL(IF(ISNUMBER($G$49:$G$63),$G$49:$G$63),4),$G$49:$G$63,0)),"")} | B86: {=IFERROR(INDEX($I$49:$I$63,MATCH(SMALL(IF(ISNUMBER($G$49:$G$63),$G$49:$G$63),4),$G$49:$G$63,0)),"")} | C86: =IFERROR(SMALL(IF(ISNUMBER($G$49:$G$63),$G$49:$G$63),4),"") | D86: =IFERROR(TODAY()+SMALL(IF(ISNUMBER($G$49:$G$63),$G$49:$G$63),4),"") | E86: {=IFERROR(INDEX($C$49:$C$63,MATCH(SMALL(IF(ISNUMBER($G$49:$G$63),$G$49:$G$63),4),$G$49:$G$63,0)),"")} | F86: {=IFERROR(INDEX($E$49:$E$63,MATCH(SMALL(IF(ISNUMBER($G$49:$G$63),$G$49:$G$63),4),$G$49:$G$63,0)),"")} | G86: {=IFERROR(INDEX($K$49:$K$63,MATCH(SMALL(IF(ISNUMBER($G$49:$G$63),$G$49:$G$63),4),$G$49:$G$63,0)),"")} | H86: {=IFERROR(INDEX($B$10:$B$44,MATCH(INDEX($A$49:$A$63,MATCH(SMALL(IF(ISNUMBER($G$49:$G$63),$G$49:$G$63),4),$G$49:$G$63,0)),$A$10:$A$44,0)),"")}
A87: {=IFERROR(INDEX($A$49:$A$63,MATCH(SMALL(IF(ISNUMBER($G$49:$G$63),$G$49:$G$63),5),$G$49:$G$63,0)),"")} | B87: {=IFERROR(INDEX($I$49:$I$63,MATCH(SMALL(IF(ISNUMBER($G$49:$G$63),$G$49:$G$63),5),$G$49:$G$63,0)),"")} | C87: =IFERROR(SMALL(IF(ISNUMBER($G$49:$G$63),$G$49:$G$63),5),"") | D87: =IFERROR(TODAY()+SMALL(IF(ISNUMBER($G$49:$G$63),$G$49:$G$63),5),"") | E87: {=IFERROR(INDEX($C$49:$C$63,MATCH(SMALL(IF(ISNUMBER($G$49:$G$63),$G$49:$G$63),5),$G$49:$G$63,0)),"")} | F87: {=IFERROR(INDEX($E$49:$E$63,MATCH(SMALL(IF(ISNUMBER($G$49:$G$63),$G$49:$G$63),5),$G$49:$G$63,0)),"")} | G87: {=IFERROR(INDEX($K$49:$K$63,MATCH(SMALL(IF(ISNUMBER($G$49:$G$63),$G$49:$G$63),5),$G$49:$G$63,0)),"")} | H87: {=IFERROR(INDEX($B$10:$B$44,MATCH(INDEX($A$49:$A$63,MATCH(SMALL(IF(ISNUMBER($G$49:$G$63),$G$49:$G$63),5),$G$49:$G$63,0)),$A$10:$A$44,0)),"")}
A88: {=IFERROR(INDEX($A$49:$A$63,MATCH(SMALL(IF(ISNUMBER($G$49:$G$63),$G$49:$G$63),6),$G$49:$G$63,0)),"")} | B88: {=IFERROR(INDEX($I$49:$I$63,MATCH(SMALL(IF(ISNUMBER($G$49:$G$63),$G$49:$G$63),6),$G$49:$G$63,0)),"")} | C88: =IFERROR(SMALL(IF(ISNUMBER($G$49:$G$63),$G$49:$G$63),6),"") | D88: =IFERROR(TODAY()+SMALL(IF(ISNUMBER($G$49:$G$63),$G$49:$G$63),6),"") | E88: {=IFERROR(INDEX($C$49:$C$63,MATCH(SMALL(IF(ISNUMBER($G$49:$G$63),$G$49:$G$63),6),$G$49:$G$63,0)),"")} | F88: {=IFERROR(INDEX($E$49:$E$63,MATCH(SMALL(IF(ISNUMBER($G$49:$G$63),$G$49:$G$63),6),$G$49:$G$63,0)),"")} | G88: {=IFERROR(INDEX($K$49:$K$63,MATCH(SMALL(IF(ISNUMBER($G$49:$G$63),$G$49:$G$63),6),$G$49:$G$63,0)),"")} | H88: {=IFERROR(INDEX($B$10:$B$44,MATCH(INDEX($A$49:$A$63,MATCH(SMALL(IF(ISNUMBER($G$49:$G$63),$G$49:$G$63),6),$G$49:$G$63,0)),$A$10:$A$44,0)),"")}
A89: {=IFERROR(INDEX($A$49:$A$63,MATCH(SMALL(IF(ISNUMBER($G$49:$G$63),$G$49:$G$63),7),$G$49:$G$63,0)),"")} | B89: {=IFERROR(INDEX($I$49:$I$63,MATCH(SMALL(IF(ISNUMBER($G$49:$G$63),$G$49:$G$63),7),$G$49:$G$63,0)),"")} | C89: =IFERROR(SMALL(IF(ISNUMBER($G$49:$G$63),$G$49:$G$63),7),"") | D89: =IFERROR(TODAY()+SMALL(IF(ISNUMBER($G$49:$G$63),$G$49:$G$63),7),"") | E89: {=IFERROR(INDEX($C$49:$C$63,MATCH(SMALL(IF(ISNUMBER($G$49:$G$63),$G$49:$G$63),7),$G$49:$G$63,0)),"")} | F89: {=IFERROR(INDEX($E$49:$E$63,MATCH(SMALL(IF(ISNUMBER($G$49:$G$63),$G$49:$G$63),7),$G$49:$G$63,0)),"")} | G89: {=IFERROR(INDEX($K$49:$K$63,MATCH(SMALL(IF(ISNUMBER($G$49:$G$63),$G$49:$G$63),7),$G$49:$G$63,0)),"")} | H89: {=IFERROR(INDEX($B$10:$B$44,MATCH(INDEX($A$49:$A$63,MATCH(SMALL(IF(ISNUMBER($G$49:$G$63),$G$49:$G$63),7),$G$49:$G$63,0)),$A$10:$A$44,0)),"")}
A90: {=IFERROR(INDEX($A$49:$A$63,MATCH(SMALL(IF(ISNUMBER($G$49:$G$63),$G$49:$G$63),8),$G$49:$G$63,0)),"")} | B90: {=IFERROR(INDEX($I$49:$I$63,MATCH(SMALL(IF(ISNUMBER($G$49:$G$63),$G$49:$G$63),8),$G$49:$G$63,0)),"")} | C90: =IFERROR(SMALL(IF(ISNUMBER($G$49:$G$63),$G$49:$G$63),8),"") | D90: =IFERROR(TODAY()+SMALL(IF(ISNUMBER($G$49:$G$63),$G$49:$G$63),8),"") | E90: {=IFERROR(INDEX($C$49:$C$63,MATCH(SMALL(IF(ISNUMBER($G$49:$G$63),$G$49:$G$63),8),$G$49:$G$63,0)),"")} | F90: {=IFERROR(INDEX($E$49:$E$63,MATCH(SMALL(IF(ISNUMBER($G$49:$G$63),$G$49:$G$63),8),$G$49:$G$63,0)),"")} | G90: {=IFERROR(INDEX($K$49:$K$63,MATCH(SMALL(IF(ISNUMBER($G$49:$G$63),$G$49:$G$63),8),$G$49:$G$63,0)),"")} | H90: {=IFERROR(INDEX($B$10:$B$44,MATCH(INDEX($A$49:$A$63,MATCH(SMALL(IF(ISNUMBER($G$49:$G$63),$G$49:$G$63),8),$G$49:$G$63,0)),$A$10:$A$44,0)),"")}
A91: {=IFERROR(INDEX($A$49:$A$63,MATCH(SMALL(IF(ISNUMBER($G$49:$G$63),$G$49:$G$63),9),$G$49:$G$63,0)),"")} | B91: {=IFERROR(INDEX($I$49:$I$63,MATCH(SMALL(IF(ISNUMBER($G$49:$G$63),$G$49:$G$63),9),$G$49:$G$63,0)),"")} | C91: =IFERROR(SMALL(IF(ISNUMBER($G$49:$G$63),$G$49:$G$63),9),"") | D91: =IFERROR(TODAY()+SMALL(IF(ISNUMBER($G$49:$G$63),$G$49:$G$63),9),"") | E91: {=IFERROR(INDEX($C$49:$C$63,MATCH(SMALL(IF(ISNUMBER($G$49:$G$63),$G$49:$G$63),9),$G$49:$G$63,0)),"")} | F91: {=IFERROR(INDEX($E$49:$E$63,MATCH(SMALL(IF(ISNUMBER($G$49:$G$63),$G$49:$G$63),9),$G$49:$G$63,0)),"")} | G91: {=IFERROR(INDEX($K$49:$K$63,MATCH(SMALL(IF(ISNUMBER($G$49:$G$63),$G$49:$G$63),9),$G$49:$G$63,0)),"")} | H91: {=IFERROR(INDEX($B$10:$B$44,MATCH(INDEX($A$49:$A$63,MATCH(SMALL(IF(ISNUMBER($G$49:$G$63),$G$49:$G$63),9),$G$49:$G$63,0)),$A$10:$A$44,0)),"")}
A92: {=IFERROR(INDEX($A$49:$A$63,MATCH(SMALL(IF(ISNUMBER($G$49:$G$63),$G$49:$G$63),10),$G$49:$G$63,0)),"")} | B92: {=IFERROR(INDEX($I$49:$I$63,MATCH(SMALL(IF(ISNUMBER($G$49:$G$63),$G$49:$G$63),10),$G$49:$G$63,0)),"")} | C92: =IFERROR(SMALL(IF(ISNUMBER($G$49:$G$63),$G$49:$G$63),10),"") | D92: =IFERROR(TODAY()+SMALL(IF(ISNUMBER($G$49:$G$63),$G$49:$G$63),10),"") | E92: {=IFERROR(INDEX($C$49:$C$63,MATCH(SMALL(IF(ISNUMBER($G$49:$G$63),$G$49:$G$63),10),$G$49:$G$63,0)),"")} | F92: {=IFERROR(INDEX($E$49:$E$63,MATCH(SMALL(IF(ISNUMBER($G$49:$G$63),$G$49:$G$63),10),$G$49:$G$63,0)),"")} | G92: {=IFERROR(INDEX($K$49:$K$63,MATCH(SMALL(IF(ISNUMBER($G$49:$G$63),$G$49:$G$63),10),$G$49:$G$63,0)),"")} | H92: {=IFERROR(INDEX($B$10:$B$44,MATCH(INDEX($A$49:$A$63,MATCH(SMALL(IF(ISNUMBER($G$49:$G$63),$G$49:$G$63),10),$G$49:$G$63,0)),$A$10:$A$44,0)),"")}
A94: STATUS LEGEND
A95: DEPLETED | B95: Item has run out — procure immediately
A96: TODAY! | B96: Item runs out today
A97: URGENT | B97: 1–3 days remaining
A98: LOW | B98: 4–7 days remaining — plan your next shop
A99: OK | B99: Well stocked (7+ days remaining)

Sheet Settings
A1: SETTINGS & CONFIGURATION
A2: Parameter | B2: Value | C2: Description
A3: Tracker Year | B3: 2026 | C3: Year for all calculations
A4: GBP to INR Exchange Rate | B4: 123 | C4: Update manually as needed
A5: INR to GBP Exchange Rate | B5: =IF(B4=0,"",1/B4) | C5: Auto-calculated
A6: Default Currency | B6: GBP | C6: Your primary currency
A7: Date Format | B7: DD/MM/YYYY | C7: Used across all sheets
A8: Budget Alert Threshold | B8: 0.8 | C8: Warn at 80% of budget (0.0 to 1.0)
A11: Version | B11: 4.0
A12: Last Updated | B12: 46119

Sheet Accounts
A1: MASTER ACCOUNT LIST
A2: Account Name | B2: Account Type | C2: Currency | D2: Card Last 4 Digits | E2: Bank/Provider | F2: Opening Balance / Credit Limit | G2: Status | H2: Date Opened | I2: Notes
A3: Lloyds Bank (GBP) | B3: Bank Account | C3: GBP | E3: LLYODS Bank | F3: 79.91 | G3: Active
A4: HSBC Bank (GBP) | B4: Bank Account | C4: GBP | F4: 1754.79 | G4: Active
A5: Barclays Bank (GBP) | B5: Bank Account | C5: GBP | F5: 181.73 | G5: Active
A6: Halifax Bank (GBP) | B6: Bank Account | C6: GBP | F6: 362.67 | G6: Discontinued | I6: Discontinued 16/05/2026
A7: Klarna Pay (GBP) | B7: Bank Account | C7: GBP | F7: 27.62 | G7: Active
A8: Capitol One Credit Card (GBP) | B8: Credit Card | C8: GBP | F8: 550 | G8: Active
A9: HSBC Rewards Credit Card (GBP) | B9: Credit Card | C9: GBP | F9: 6000 | G9: Active
A10: Barclays Rewards Credit Card (GBP) | B10: Credit Card | C10: GBP | F10: 3500 | G10: Active
A11: Klarna Pay Later (GBP) | B11: Pay Later | C11: GBP | G11: Active
A12: Splitwise (GBP) | B12: Expense Sharing | C12: GBP | G12: Active
A13: Oyster Travel Card (GBP) | B13: Travel Card | C13: GBP | F13: 78.7 | G13: Active
A14: HDFC Bank (INR) | B14: Bank Account | C14: INR | F14: 75570.26 | G14: Active
A15: HDFC IOCL Credit Card (INR) | B15: Credit Card | C15: INR | F15: 25000 | G15: Active
A16: HDFC Swiggy Credit Card (INR) | B16: Credit Card | C16: INR | F16: 25000 | G16: Active
A17: Axis Airtel Credit Card (INR) | B17: Credit Card | C17: INR | F17: 110000 | G17: Active
A18: Chase Bank (GBP) | B18: Bank Account | C18: GBP | E18: Chase UK | F18: 0 | G18: Active | H18: 16/05/2026 | I18: New account
A19: Monzo (GBP) | B19: Bank Account | C19: GBP | E19: Monzo | F19: 0 | G19: Active | H19: 16/05/2026 | I19: New account

Sheet Expenses
A1: EXPENSE TRACKER
A2: Date | B2: Name/Description | C2: Category | D2: Price | E2: Currency | F2: Transaction Gateway | G2: Splitwise | H2: Your Share | I2: Recurring | J2: Notes
A3: 46119 | B3: Barclays Card Due | C3: Shopping | D3: 680.53 | E3: =IF(F3="","",IF(OR(F3="HDFC Bank (INR)",F3="HDFC IOCL Credit Card (INR)",F3="HDFC Swiggy Credit Card (INR)",F3="Axis Airtel Credit Card (INR)"),"INR","GBP")) | F3: Barclays Rewards Credit Card (GBP) | G3: No | H3: =IF(G3="Yes","",D3) | I3: No | J3: previous payments dated back at APR 7 1400PM
A4: 46119 | B4: HSBC Card Due | C4: Shopping | D4: =505.93-19-10 | E4: =IF(F4="","",IF(OR(F4="HDFC Bank (INR)",F4="HDFC IOCL Credit Card (INR)",F4="HDFC Swiggy Credit Card (INR)",F4="Axis Airtel Credit Card (INR)"),"INR","GBP")) | F4: HSBC Rewards Credit Card (GBP) | G4: No | H4: =IF(G4="Yes","",D4) | I4: No
A5: 46119 | B5: Capitol One Card Due | C5: Shopping | D5: 0 | E5: =IF(F5="","",IF(OR(F5="HDFC Bank (INR)",F5="HDFC IOCL Credit Card (INR)",F5="HDFC Swiggy Credit Card (INR)",F5="Axis Airtel Credit Card (INR)"),"INR","GBP")) | F5: Capitol One Credit Card (GBP) | G5: No | H5: =IF(G5="Yes","",D5) | I5: No
A6: 46119 | B6: Klarna Pay Later | C6: Shopping | D6: 181.34 | E6: =IF(F6="","",IF(OR(F6="HDFC Bank (INR)",F6="HDFC IOCL Credit Card (INR)",F6="HDFC Swiggy Credit Card (INR)",F6="Axis Airtel Credit Card (INR)"),"INR","GBP")) | F6: Klarna Pay Later (GBP) | G6: No | H6: =IF(G6="Yes","",D6) | I6: No
A7: 46119 | B7: HDFC Credit Due | C7: Shopping | D7: 335.4 | E7: =IF(F7="","",IF(OR(F7="HDFC Bank (INR)",F7="HDFC IOCL Credit Card (INR)",F7="HDFC Swiggy Credit Card (INR)",F7="Axis Airtel Credit Card (INR)"),"INR","GBP")) | F7: HDFC IOCL Credit Card (INR) | G7: No | H7: =IF(G7="Yes","",D7) | I7: No
A8: 46119 | B8: HDFC Credit Due | C8: Shopping | D8: 799 | E8: =IF(F8="","",IF(OR(F8="HDFC Bank (INR)",F8="HDFC IOCL Credit Card (INR)",F8="HDFC Swiggy Credit Card (INR)",F8="Axis Airtel Credit Card (INR)"),"INR","GBP")) | F8: HDFC Swiggy Credit Card (INR) | G8: No | H8: =IF(G8="Yes","",D8) | I8: No
A9: 46119 | B9: Axis Credit Due | C9: Shopping | D9: =110000-27121+21 | E9: =IF(F9="","",IF(OR(F9="HDFC Bank (INR)",F9="HDFC IOCL Credit Card (INR)",F9="HDFC Swiggy Credit Card (INR)",F9="Axis Airtel Credit Card (INR)"),"INR","GBP")) | F9: Axis Airtel Credit Card (INR) | G9: No | H9: =IF(G9="Yes","",D9) | I9: No
A10: 46119 | B10: East Ham to oxford Circus(U/D) | C10: Transport | D10: 4.3 | E10: =IF(F10="","",IF(OR(F10="HDFC Bank (INR)",F10="HDFC IOCL Credit Card (INR)",F10="HDFC Swiggy Credit Card (INR)",F10="Axis Airtel Credit Card (INR)"),"INR","GBP")) | F10: Oyster Travel Card (GBP) | G10: No | I10: No
A11: 46120 | B11: Ticket Machine | D11: 10 | E11: =IF(F11="","",IF(OR(F11="HDFC Bank (INR)",F11="HDFC IOCL Credit Card (INR)",F11="HDFC Swiggy Credit Card (INR)",F11="Axis Airtel Credit Card (INR)"),"INR","GBP")) | F11: HSBC Rewards Credit Card (GBP) | G11: Yes | H11: 0 | I11: No | J11: To tanisha
A12: 46120 | B12: Apple Polishing Cloth | C12: Shopping | D12: 19 | E12: =IF(F12="","",IF(OR(F12="HDFC Bank (INR)",F12="HDFC IOCL Credit Card (INR)",F12="HDFC Swiggy Credit Card (INR)",F12="Axis Airtel Credit Card (INR)"),"INR","GBP")) | F12: HSBC Rewards Credit Card (GBP) | G12: No | H12: =IF(G12="Yes","",D12) | I12: No
A13: 46120 | B13: Free Prints | C13: Shopping | D13: 5.11 | E13: =IF(F13="","",IF(OR(F13="HDFC Bank (INR)",F13="HDFC IOCL Credit Card (INR)",F13="HDFC Swiggy Credit Card (INR)",F13="Axis Airtel Credit Card (INR)"),"INR","GBP")) | F13: Lloyds Bank (GBP) | G13: No | H13: =IF(G13="Yes","",D13) | I13: No
A14: 46120 | B14: Amazon Album | C14: Shopping | D14: 6.99 | E14: =IF(F14="","",IF(OR(F14="HDFC Bank (INR)",F14="HDFC IOCL Credit Card (INR)",F14="HDFC Swiggy Credit Card (INR)",F14="Axis Airtel Credit Card (INR)"),"INR","GBP")) | F14: Capitol One Credit Card (GBP) | G14: No | H14: =IF(G14="Yes","",D14) | I14: No
A15: 46120 | B15: Amazon Watch klit | C15: Shopping | D15: 9.99 | E15: =IF(F15="","",IF(OR(F15="HDFC Bank (INR)",F15="HDFC IOCL Credit Card (INR)",F15="HDFC Swiggy Credit Card (INR)",F15="Axis Airtel Credit Card (INR)"),"INR","GBP")) | F15: Capitol One Credit Card (GBP) | G15: No | H15: =IF(G15="Yes","",D15) | I15: No
A16: 46120 | B16: Amazon Brita water catridfges | C16: Others | D16: 24.99 | E16: =IF(F16="","",IF(OR(F16="HDFC Bank (INR)",F16="HDFC IOCL Credit Card (INR)",F16="HDFC Swiggy Credit Card (INR)",F16="Axis Airtel Credit Card (INR)"),"INR","GBP")) | F16: Capitol One Credit Card (GBP) | G16: No | H16: =IF(G16="Yes","",D16) | I16: Yes
A17: 46120 | B17: East Ham to Shoreditch U/D | C17: Transport | D17: 4.3 | E17: =IF(F17="","",IF(OR(F17="HDFC Bank (INR)",F17="HDFC IOCL Credit Card (INR)",F17="HDFC Swiggy Credit Card (INR)",F17="Axis Airtel Credit Card (INR)"),"INR","GBP")) | F17: Oyster Travel Card (GBP) | G17: No | H17: =IF(G17="Yes","",D17) | I17: No
A18: 46121 | B18: East Ham to Shoreditch U/D | C18: Transport | D18: 6.05 | E18: =IF(F18="","",IF(OR(F18="HDFC Bank (INR)",F18="HDFC IOCL Credit Card (INR)",F18="HDFC Swiggy Credit Card (INR)",F18="Axis Airtel Credit Card (INR)"),"INR","GBP")) | F18: Oyster Travel Card (GBP) | G18: No | H18: =IF(G18="Yes","",D18) | I18: No | J18: in peak time travel
A19: 46124 | B19: Barber | C19: Others | D19: 20 | E19: =IF(F19="","",IF(OR(F19="HDFC Bank (INR)",F19="HDFC IOCL Credit Card (INR)",F19="HDFC Swiggy Credit Card (INR)",F19="Axis Airtel Credit Card (INR)"),"INR","GBP")) | F19: Barclays Rewards Credit Card (GBP) | G19: No | H19: =IF(G19="Yes","",D19) | I19: No
A20: 46124 | B20: KFC | C20: Food and Drinks | D20: 5.62 | E20: =IF(F20="","",IF(OR(F20="HDFC Bank (INR)",F20="HDFC IOCL Credit Card (INR)",F20="HDFC Swiggy Credit Card (INR)",F20="Axis Airtel Credit Card (INR)"),"INR","GBP")) | F20: Splitwise (GBP) | G20: No | H20: =IF(G20="Yes","",D20) | I20: No
A21: 46125 | B21: Post Cards | C21: Travel | D21: 2.8 | E21: =IF(F21="","",IF(OR(F21="HDFC Bank (INR)",F21="HDFC IOCL Credit Card (INR)",F21="HDFC Swiggy Credit Card (INR)",F21="Axis Airtel Credit Card (INR)"),"INR","GBP")) | F21: Barclays Rewards Credit Card (GBP) | G21: No | H21: =IF(G21="Yes","",D21) | I21: No
A22: 46125 | B22: Top Church View | C22: Travel | D22: 6 | E22: =IF(F22="","",IF(OR(F22="HDFC Bank (INR)",F22="HDFC IOCL Credit Card (INR)",F22="HDFC Swiggy Credit Card (INR)",F22="Axis Airtel Credit Card (INR)"),"INR","GBP")) | F22: Splitwise (GBP) | G22: No | H22: =IF(G22="Yes","",D22) | I22: No
A23: 46125 | B23: Ask Italian | C23: Food and Drinks | E23: =IF(F23="","",IF(OR(F23="HDFC Bank (INR)",F23="HDFC IOCL Credit Card (INR)",F23="HDFC Swiggy Credit Card (INR)",F23="Axis Airtel Credit Card (INR)"),"INR","GBP")) | F23: Splitwise (GBP) | G23: No | H23: =IF(G23="Yes","",D23) | I23: No
A24: 46125 | B24: Pret | C24: Food and Drinks | D24: 2.35 | E24: =IF(F24="","",IF(OR(F24="HDFC Bank (INR)",F24="HDFC IOCL Credit Card (INR)",F24="HDFC Swiggy Credit Card (INR)",F24="Axis Airtel Credit Card (INR)"),"INR","GBP")) | F24: Barclays Rewards Credit Card (GBP) | G24: No | H24: =IF(G24="Yes","",D24) | I24: No
A25: 46125 | B25: Gelato | C25: Food and Drinks | D25: 16 | E25: =IF(F25="","",IF(OR(F25="HDFC Bank (INR)",F25="HDFC IOCL Credit Card (INR)",F25="HDFC Swiggy Credit Card (INR)",F25="Axis Airtel Credit Card (INR)"),"INR","GBP")) | F25: Barclays Rewards Credit Card (GBP) | G25: Yes | H25: 4 | I25: No
A26: 46125 | B26: Donation Church | C26: Donations | D26: 2.09 | E26: =IF(F26="","",IF(OR(F26="HDFC Bank (INR)",F26="HDFC IOCL Credit Card (INR)",F26="HDFC Swiggy Credit Card (INR)",F26="Axis Airtel Credit Card (INR)"),"INR","GBP")) | F26: Lloyds Bank (GBP) | G26: No | H26: =IF(G26="Yes","",D26) | I26: No
A27: 46125 | B27: Now Sky Sports | C27: Subscriptions | D27: 27.99 | E27: =IF(F27="","",IF(OR(F27="HDFC Bank (INR)",F27="HDFC IOCL Credit Card (INR)",F27="HDFC Swiggy Credit Card (INR)",F27="Axis Airtel Credit Card (INR)"),"INR","GBP")) | F27: Barclays Rewards Credit Card (GBP) | G27: No | H27: =IF(G27="Yes","",D27) | I27: Yes
A28: 46125 | B28: Chai and hill | C28: Food and Drinks | D28: 1 | E28: =IF(F28="","",IF(OR(F28="HDFC Bank (INR)",F28="HDFC IOCL Credit Card (INR)",F28="HDFC Swiggy Credit Card (INR)",F28="Axis Airtel Credit Card (INR)"),"INR","GBP")) | F28: Lloyds Bank (GBP) | G28: No | H28: =IF(G28="Yes","",D28) | I28: No
A29: 46125 | B29: Chocolates | C29: Food and Drinks | D29: 3.19 | E29: =IF(F29="","",IF(OR(F29="HDFC Bank (INR)",F29="HDFC IOCL Credit Card (INR)",F29="HDFC Swiggy Credit Card (INR)",F29="Axis Airtel Credit Card (INR)"),"INR","GBP")) | F29: Lloyds Bank (GBP) | G29: No | H29: =IF(G29="Yes","",D29) | I29: No
A30: 46125 | B30: Lays | C30: Food and Drinks | D30: 0.89 | E30: =IF(F30="","",IF(OR(F30="HDFC Bank (INR)",F30="HDFC IOCL Credit Card (INR)",F30="HDFC Swiggy Credit Card (INR)",F30="Axis Airtel Credit Card (INR)"),"INR","GBP")) | F30: Lloyds Bank (GBP) | G30: No | H30: =IF(G30="Yes","",D30) | I30: No
A31: 46125 | B31: Redbull | C31: Food and Drinks | D31: 1.65 | E31: =IF(F31="","",IF(OR(F31="HDFC Bank (INR)",F31="HDFC IOCL Credit Card (INR)",F31="HDFC Swiggy Credit Card (INR)",F31="Axis Airtel Credit Card (INR)"),"INR","GBP")) | F31: Lloyds Bank (GBP) | G31: No | H31: =IF(G31="Yes","",D31) | I31: No
A32: 46125 | B32: Prime Sub | C32: Subscriptions | D32: 4.49 | E32: =IF(F32="","",IF(OR(F32="HDFC Bank (INR)",F32="HDFC IOCL Credit Card (INR)",F32="HDFC Swiggy Credit Card (INR)",F32="Axis Airtel Credit Card (INR)"),"INR","GBP")) | F32: Capitol One Credit Card (GBP) | G32: Yes | H32: 1.49 | I32: Yes
A33: 46125 | B33: Seeko | C33: Food and Drinks | D33: 5.51 | E33: =IF(F33="","",IF(OR(F33="HDFC Bank (INR)",F33="HDFC IOCL Credit Card (INR)",F33="HDFC Swiggy Credit Card (INR)",F33="Axis Airtel Credit Card (INR)"),"INR","GBP")) | F33: Splitwise (GBP) | G33: No | H33: =IF(G33="Yes","",D33) | I33: No
A34: 46125 | B34: Nike | C34: Shopping | D34: 99.98 | E34: =IF(F34="","",IF(OR(F34="HDFC Bank (INR)",F34="HDFC IOCL Credit Card (INR)",F34="HDFC Swiggy Credit Card (INR)",F34="Axis Airtel Credit Card (INR)"),"INR","GBP")) | F34: HSBC Rewards Credit Card (GBP) | G34: No | H34: =IF(G34="Yes","",D34) | I34: No
A35: 46125 | B35: Fusion | C35: Entertainment | D35: 328 | E35: =IF(F35="","",IF(OR(F35="HDFC Bank (INR)",F35="HDFC IOCL Credit Card (INR)",F35="HDFC Swiggy Credit Card (INR)",F35="Axis Airtel Credit Card (INR)"),"INR","GBP")) | F35: HDFC Bank (INR) | G35: No | H35: =IF(G35="Yes","",D35) | I35: No
A36: 46125 | B36: Now Sky Sports 2nd Screen | C36: Subscriptions | D36: 6 | E36: =IF(F36="","",IF(OR(F36="HDFC Bank (INR)",F36="HDFC IOCL Credit Card (INR)",F36="HDFC Swiggy Credit Card (INR)",F36="Axis Airtel Credit Card (INR)"),"INR","GBP")) | F36: Barclays Rewards Credit Card (GBP) | G36: No | H36: =IF(G36="Yes","",D36) | I36: Yes
A37: 46129 | B37: Lidl | C37: Groceries | D37: 4.24 | E37: =IF(F37="","",IF(OR(F37="HDFC Bank (INR)",F37="HDFC IOCL Credit Card (INR)",F37="HDFC Swiggy Credit Card (INR)",F37="Axis Airtel Credit Card (INR)"),"INR","GBP")) | F37: Splitwise (GBP) | G37: No | H37: =IF(G37="Yes","",D37)
A38: 46129 | B38: Onions | C38: Groceries | D38: 0.66 | E38: =IF(F38="","",IF(OR(F38="HDFC Bank (INR)",F38="HDFC IOCL Credit Card (INR)",F38="HDFC Swiggy Credit Card (INR)",F38="Axis Airtel Credit Card (INR)"),"INR","GBP")) | F38: Splitwise (GBP) | G38: No | H38: =IF(G38="Yes","",D38)
A39: 46129 | B39: Paradise | C39: Food and Drinks | D39: 6.5 | E39: =IF(F39="","",IF(OR(F39="HDFC Bank (INR)",F39="HDFC IOCL Credit Card (INR)",F39="HDFC Swiggy Credit Card (INR)",F39="Axis Airtel Credit Card (INR)"),"INR","GBP")) | F39: Lloyds Bank (GBP) | G39: No | H39: =IF(G39="Yes","",D39) | I39: No
A40: 46129 | B40: Lighter | C40: Electronics | D40: 1 | E40: =IF(F40="","",IF(OR(F40="HDFC Bank (INR)",F40="HDFC IOCL Credit Card (INR)",F40="HDFC Swiggy Credit Card (INR)",F40="Axis Airtel Credit Card (INR)"),"INR","GBP")) | F40: Lloyds Bank (GBP) | G40: No | H40: =IF(G40="Yes","",D40) | I40: No
A41: 46129 | B41: Mints | C41: Food and Drinks | D41: 2.5 | E41: =IF(F41="","",IF(OR(F41="HDFC Bank (INR)",F41="HDFC IOCL Credit Card (INR)",F41="HDFC Swiggy Credit Card (INR)",F41="Axis Airtel Credit Card (INR)"),"INR","GBP")) | F41: Lloyds Bank (GBP) | G41: No | H41: =IF(G41="Yes","",D41) | I41: No
A42: 46129 | B42: eggs | C42: Groceries | D42: 4.45 | E42: =IF(F42="","",IF(OR(F42="HDFC Bank (INR)",F42="HDFC IOCL Credit Card (INR)",F42="HDFC Swiggy Credit Card (INR)",F42="Axis Airtel Credit Card (INR)"),"INR","GBP")) | F42: Lloyds Bank (GBP) | G42: Yes | H42: 1.42 | I42: No
A43: 46129 | B43: Claude AI | C43: Subscriptions | D43: 18 | E43: =IF(F43="","",IF(OR(F43="HDFC Bank (INR)",F43="HDFC IOCL Credit Card (INR)",F43="HDFC Swiggy Credit Card (INR)",F43="Axis Airtel Credit Card (INR)"),"INR","GBP")) | F43: Barclays Rewards Credit Card (GBP) | G43: No | H43: =IF(G43="Yes","",D43) | I43: No
A44: 46129 | B44: EE | C44: Bills | D44: 26.92 | E44: =IF(F44="","",IF(OR(F44="HDFC Bank (INR)",F44="HDFC IOCL Credit Card (INR)",F44="HDFC Swiggy Credit Card (INR)",F44="Axis Airtel Credit Card (INR)"),"INR","GBP")) | F44: Barclays Bank (GBP) | G44: No | H44: =IF(G44="Yes","",D44) | I44: No
A45: 46129 | B45: GBP to Inr | D45: 200 | E45: =IF(F45="","",IF(OR(F45="HDFC Bank (INR)",F45="HDFC IOCL Credit Card (INR)",F45="HDFC Swiggy Credit Card (INR)",F45="Axis Airtel Credit Card (INR)"),"INR","GBP")) | F45: Halifax Bank (GBP) | G45: No | H45: =IF(G45="Yes","",D45) | I45: No
A46: 46129 | B46: Mad MAx | C46: Entertainment | D46: 399 | E46: =IF(F46="","",IF(OR(F46="HDFC Bank (INR)",F46="HDFC IOCL Credit Card (INR)",F46="HDFC Swiggy Credit Card (INR)",F46="Axis Airtel Credit Card (INR)"),"INR","GBP")) | F46: HDFC Bank (INR) | G46: No | H46: =IF(G46="Yes","",D46) | I46: No
A47: 46129 | B47: Apple Itunes OM | C47: Entertainment | D47: 15 | E47: =IF(F47="","",IF(OR(F47="HDFC Bank (INR)",F47="HDFC IOCL Credit Card (INR)",F47="HDFC Swiggy Credit Card (INR)",F47="Axis Airtel Credit Card (INR)"),"INR","GBP")) | F47: HDFC Bank (INR) | G47: No | H47: =IF(G47="Yes","",D47) | I47: No
A48: 46129 | B48: TJ Jones | C48: Gifts | D48: 13.24 | E48: =IF(F48="","",IF(OR(F48="HDFC Bank (INR)",F48="HDFC IOCL Credit Card (INR)",F48="HDFC Swiggy Credit Card (INR)",F48="Axis Airtel Credit Card (INR)"),"INR","GBP")) | F48: HSBC Rewards Credit Card (GBP) | G48: No | H48: =IF(G48="Yes","",D48) | I48: No
A49: 46129 | B49: JD Sports | C49: Shopping | D49: 117 | E49: =IF(F49="","",IF(OR(F49="HDFC Bank (INR)",F49="HDFC IOCL Credit Card (INR)",F49="HDFC Swiggy Credit Card (INR)",F49="Axis Airtel Credit Card (INR)"),"INR","GBP")) | F49: HSBC Rewards Credit Card (GBP) | G49: No | H49: =IF(G49="Yes","",D49) | I49: No
A50: 46133 | B50: Top Gun IMAX | C50: Entertainment | D50: 5 | E50: =IF(F50="","",IF(OR(F50="HDFC Bank (INR)",F50="HDFC IOCL Credit Card (INR)",F50="HDFC Swiggy Credit Card (INR)",F50="Axis Airtel Credit Card (INR)"),"INR","GBP")) | F50: Lloyds Bank (GBP) | G50: No | H50: =IF(G50="Yes","",D50) | I50: No
A51: 46133 | B51: Pizza | C51: Food and Drinks | D51: 6.33 | E51: =IF(F51="","",IF(OR(F51="HDFC Bank (INR)",F51="HDFC IOCL Credit Card (INR)",F51="HDFC Swiggy Credit Card (INR)",F51="Axis Airtel Credit Card (INR)"),"INR","GBP")) | F51: Splitwise (GBP) | G51: No | H51: =IF(G51="Yes","",D51) | I51: No
A52: 46133 | B52: Lidl | C52: Groceries | D52: =6.18+0.25 | E52: =IF(F52="","",IF(OR(F52="HDFC Bank (INR)",F52="HDFC IOCL Credit Card (INR)",F52="HDFC Swiggy Credit Card (INR)",F52="Axis Airtel Credit Card (INR)"),"INR","GBP")) | F52: Splitwise (GBP) | G52: No | H52: =IF(G52="Yes","",D52) | I52: No
A53: 46133 | B53: Akka Shop | C53: Groceries | D53: 1.02 | E53: =IF(F53="","",IF(OR(F53="HDFC Bank (INR)",F53="HDFC IOCL Credit Card (INR)",F53="HDFC Swiggy Credit Card (INR)",F53="Axis Airtel Credit Card (INR)"),"INR","GBP")) | F53: Splitwise (GBP) | G53: No | H53: =IF(G53="Yes","",D53) | I53: No
A54: 46133 | B54: Mushrooms | C54: Groceries | D54: 1.68 | E54: =IF(F54="","",IF(OR(F54="HDFC Bank (INR)",F54="HDFC IOCL Credit Card (INR)",F54="HDFC Swiggy Credit Card (INR)",F54="Axis Airtel Credit Card (INR)"),"INR","GBP")) | F54: Splitwise (GBP) | G54: No | H54: =IF(G54="Yes","",D54) | I54: No
A55: 46133 | B55: Seeko | C55: Groceries | D55: 1.46 | E55: =IF(F55="","",IF(OR(F55="HDFC Bank (INR)",F55="HDFC IOCL Credit Card (INR)",F55="HDFC Swiggy Credit Card (INR)",F55="Axis Airtel Credit Card (INR)"),"INR","GBP")) | F55: Splitwise (GBP) | G55: No | H55: =IF(G55="Yes","",D55) | I55: No
A56: 46133 | B56: Washing Liquid | C56: Groceries | D56: 0.46 | E56: =IF(F56="","",IF(OR(F56="HDFC Bank (INR)",F56="HDFC IOCL Credit Card (INR)",F56="HDFC Swiggy Credit Card (INR)",F56="Axis Airtel Credit Card (INR)"),"INR","GBP")) | F56: Splitwise (GBP) | G56: No | H56: =IF(G56="Yes","",D56) | I56: No
A57: 46133 | B57: Mars | C57: Food and Drinks | D57: 1 | E57: =IF(F57="","",IF(OR(F57="HDFC Bank (INR)",F57="HDFC IOCL Credit Card (INR)",F57="HDFC Swiggy Credit Card (INR)",F57="Axis Airtel Credit Card (INR)"),"INR","GBP")) | F57: Lloyds Bank (GBP) | G57: No | H57: =IF(G57="Yes","",D57) | I57: No
A58: 46133 | B58: Paradise | C58: Food and Drinks | D58: 8 | E58: =IF(F58="","",IF(OR(F58="HDFC Bank (INR)",F58="HDFC IOCL Credit Card (INR)",F58="HDFC Swiggy Credit Card (INR)",F58="Axis Airtel Credit Card (INR)"),"INR","GBP")) | F58: Lloyds Bank (GBP) | G58: No | H58: =IF(G58="Yes","",D58) | I58: No
A59: 46133 | B59: East Ham to North Greewich | C59: Transport | D59: 2.9 | E59: =IF(F59="","",IF(OR(F59="HDFC Bank (INR)",F59="HDFC IOCL Credit Card (INR)",F59="HDFC Swiggy Credit Card (INR)",F59="Axis Airtel Credit Card (INR)"),"INR","GBP")) | F59: Oyster Travel Card (GBP) | G59: No | H59: =IF(G59="Yes","",D59) | I59: No
A60: 46133 | B60: East Ham to Shoreditch U/D | C60: Transport | D60: 4.3 | E60: =IF(F60="","",IF(OR(F60="HDFC Bank (INR)",F60="HDFC IOCL Credit Card (INR)",F60="HDFC Swiggy Credit Card (INR)",F60="Axis Airtel Credit Card (INR)"),"INR","GBP")) | F60: Oyster Travel Card (GBP) | G60: No | H60: =IF(G60="Yes","",D60) | I60: No
A61: 46133 | B61: East Ham to Shoreditch U/D | C61: Transport | D61: 4.3 | E61: =IF(F61="","",IF(OR(F61="HDFC Bank (INR)",F61="HDFC IOCL Credit Card (INR)",F61="HDFC Swiggy Credit Card (INR)",F61="Axis Airtel Credit Card (INR)"),"INR","GBP")) | F61: Oyster Travel Card (GBP) | G61: No | H61: =IF(G61="Yes","",D61) | I61: No
A62: 46133 | B62: East Ham to Shoreditch U/D | C62: Transport | D62: 6.95 | E62: =IF(F62="","",IF(OR(F62="HDFC Bank (INR)",F62="HDFC IOCL Credit Card (INR)",F62="HDFC Swiggy Credit Card (INR)",F62="Axis Airtel Credit Card (INR)"),"INR","GBP")) | F62: Oyster Travel Card (GBP) | G62: No | H62: =IF(G62="Yes","",D62) | I62: No
A63: 46133 | B63: East Ham to Shoreditch U/D | C63: Transport | D63: 4.3 | E63: =IF(F63="","",IF(OR(F63="HDFC Bank (INR)",F63="HDFC IOCL Credit Card (INR)",F63="HDFC Swiggy Credit Card (INR)",F63="Axis Airtel Credit Card (INR)"),"INR","GBP")) | F63: Oyster Travel Card (GBP) | G63: No | H63: =IF(G63="Yes","",D63) | I63: No
A64: 46133 | B64: East Ham to Shoreditch U/D | C64: Transport | D64: 4.3 | E64: =IF(F64="","",IF(OR(F64="HDFC Bank (INR)",F64="HDFC IOCL Credit Card (INR)",F64="HDFC Swiggy Credit Card (INR)",F64="Axis Airtel Credit Card (INR)"),"INR","GBP")) | F64: Oyster Travel Card (GBP) | G64: No | H64: =IF(G64="Yes","",D64) | I64: No
A65: 46133 | B65: East Ham to Shoreditch U/D | C65: Transport | D65: 5.95 | E65: =IF(F65="","",IF(OR(F65="HDFC Bank (INR)",F65="HDFC IOCL Credit Card (INR)",F65="HDFC Swiggy Credit Card (INR)",F65="Axis Airtel Credit Card (INR)"),"INR","GBP")) | F65: Oyster Travel Card (GBP) | G65: No | H65: =IF(G65="Yes","",D65) | I65: No | J65: Night travel
A66: 46133 | B66: Claude Ai Sub | C66: Subscriptions | D66: 1999 | E66: =IF(F66="","",IF(OR(F66="HDFC Bank (INR)",F66="HDFC IOCL Credit Card (INR)",F66="HDFC Swiggy Credit Card (INR)",F66="Axis Airtel Credit Card (INR)"),"INR","GBP")) | F66: HDFC Bank (INR) | G66: No | H66: =IF(G66="Yes","",D66) | I66: No
A67: 46137 | B67: Paradise | C67: Food and Drinks | D67: 8 | E67: =IF(F67="","",IF(OR(F67="HDFC Bank (INR)",F67="HDFC IOCL Credit Card (INR)",F67="HDFC Swiggy Credit Card (INR)",F67="Axis Airtel Credit Card (INR)"),"INR","GBP")) | F67: Lloyds Bank (GBP) | G67: No | H67: =IF(G67="Yes","",D67) | I67: No
A68: 46137 | B68: TFL | C68: Transport | D68: 3.5 | E68: =IF(F68="","",IF(OR(F68="HDFC Bank (INR)",F68="HDFC IOCL Credit Card (INR)",F68="HDFC Swiggy Credit Card (INR)",F68="Axis Airtel Credit Card (INR)"),"INR","GBP")) | F68: Lloyds Bank (GBP) | G68: No | H68: =IF(G68="Yes","",D68) | I68: No
A69: 46137 | B69: Rumali roti | C69: Groceries | D69: 1.99 | E69: =IF(F69="","",IF(OR(F69="HDFC Bank (INR)",F69="HDFC IOCL Credit Card (INR)",F69="HDFC Swiggy Credit Card (INR)",F69="Axis Airtel Credit Card (INR)"),"INR","GBP")) | F69: Lloyds Bank (GBP) | G69: No | H69: =IF(G69="Yes","",D69) | I69: No
A70: 46137 | B70: Lidl | C70: Food and Drinks | D70: 1.5 | E70: =IF(F70="","",IF(OR(F70="HDFC Bank (INR)",F70="HDFC IOCL Credit Card (INR)",F70="HDFC Swiggy Credit Card (INR)",F70="Axis Airtel Credit Card (INR)"),"INR","GBP")) | F70: Lloyds Bank (GBP) | G70: No | H70: =IF(G70="Yes","",D70) | I70: No
A71: 46137 | B71: East to East | C71: Transport | D71: 5.95 | E71: =IF(F71="","",IF(OR(F71="HDFC Bank (INR)",F71="HDFC IOCL Credit Card (INR)",F71="HDFC Swiggy Credit Card (INR)",F71="Axis Airtel Credit Card (INR)"),"INR","GBP")) | F71: Oyster Travel Card (GBP) | G71: No | H71: =IF(G71="Yes","",D71) | I71: No | J71: Night travel
A72: 46137 | B72: Chocolates | C72: Food and Drinks | D72: 1.78 | E72: =IF(F72="","",IF(OR(F72="HDFC Bank (INR)",F72="HDFC IOCL Credit Card (INR)",F72="HDFC Swiggy Credit Card (INR)",F72="Axis Airtel Credit Card (INR)"),"INR","GBP")) | F72: Lloyds Bank (GBP) | G72: No | H72: =IF(G72="Yes","",D72) | I72: No
A73: 46137 | B73: East to East | C73: Transport | D73: 3.9 | E73: =IF(F73="","",IF(OR(F73="HDFC Bank (INR)",F73="HDFC IOCL Credit Card (INR)",F73="HDFC Swiggy Credit Card (INR)",F73="Axis Airtel Credit Card (INR)"),"INR","GBP")) | F73: Oyster Travel Card (GBP) | G73: No | H73: =IF(G73="Yes","",D73) | I73: No
A74: 46137 | B74: Easto East | C74: Transport | D74: 5.95 | E74: =IF(F74="","",IF(OR(F74="HDFC Bank (INR)",F74="HDFC IOCL Credit Card (INR)",F74="HDFC Swiggy Credit Card (INR)",F74="Axis Airtel Credit Card (INR)"),"INR","GBP")) | F74: Oyster Travel Card (GBP) | G74: No | H74: =IF(G74="Yes","",D74) | I74: No | J74: Night travel
A75: 46138 | B75: Eggs | C75: Groceries | D75: 2.55 | E75: =IF(F75="","",IF(OR(F75="HDFC Bank (INR)",F75="HDFC IOCL Credit Card (INR)",F75="HDFC Swiggy Credit Card (INR)",F75="Axis Airtel Credit Card (INR)"),"INR","GBP")) | F75: Splitwise (GBP) | G75: No | H75: =IF(G75="Yes","",D75) | I75: No
A76: 46138 | B76: Lemons | C76: Groceries | D76: 0.3 | E76: =IF(F76="","",IF(OR(F76="HDFC Bank (INR)",F76="HDFC IOCL Credit Card (INR)",F76="HDFC Swiggy Credit Card (INR)",F76="Axis Airtel Credit Card (INR)"),"INR","GBP")) | F76: Splitwise (GBP) | G76: No | H76: =IF(G76="Yes","",D76) | I76: No
A77: 46138 | B77: Week 1 Diest Grocery | C77: Groceries | D77: 17.81 | E77: =IF(F77="","",IF(OR(F77="HDFC Bank (INR)",F77="HDFC IOCL Credit Card (INR)",F77="HDFC Swiggy Credit Card (INR)",F77="Axis Airtel Credit Card (INR)"),"INR","GBP")) | F77: Lloyds Bank (GBP) | G77: Yes | H77: 12.65 | I77: No
A78: 46138 | B78: Week 1 Diest Grocery | C78: Groceries | D78: 6.59 | E78: =IF(F78="","",IF(OR(F78="HDFC Bank (INR)",F78="HDFC IOCL Credit Card (INR)",F78="HDFC Swiggy Credit Card (INR)",F78="Axis Airtel Credit Card (INR)"),"INR","GBP")) | F78: Splitwise (GBP) | G78: No | H78: =IF(G78="Yes","",D78) | I78: No
A79: 46138 | B79: Week 1 Diest Grocery | C79: Groceries | D79: 4.28 | E79: =IF(F79="","",IF(OR(F79="HDFC Bank (INR)",F79="HDFC IOCL Credit Card (INR)",F79="HDFC Swiggy Credit Card (INR)",F79="Axis Airtel Credit Card (INR)"),"INR","GBP")) | F79: Lloyds Bank (GBP) | G79: Yes | H79: =D79/2 | I79: No
A80: 46138 | B80: Chai and hill | C80: Food and Drinks | D80: 1 | E80: =IF(F80="","",IF(OR(F80="HDFC Bank (INR)",F80="HDFC IOCL Credit Card (INR)",F80="HDFC Swiggy Credit Card (INR)",F80="Axis Airtel Credit Card (INR)"),"INR","GBP")) | F80: Lloyds Bank (GBP) | G80: No | H80: =IF(G80="Yes","",D80) | I80: No
A81: 46138 | B81: Nike Shoe | C81: Shopping | D81: 63.99 | E81: =IF(F81="","",IF(OR(F81="HDFC Bank (INR)",F81="HDFC IOCL Credit Card (INR)",F81="HDFC Swiggy Credit Card (INR)",F81="Axis Airtel Credit Card (INR)"),"INR","GBP")) | F81: HSBC Rewards Credit Card (GBP) | G81: No | H81: =IF(G81="Yes","",D81) | I81: No
A82: 46138 | B82: Nike T shirt | C82: Shopping | D82: 30.39 | E82: =IF(F82="","",IF(OR(F82="HDFC Bank (INR)",F82="HDFC IOCL Credit Card (INR)",F82="HDFC Swiggy Credit Card (INR)",F82="Axis Airtel Credit Card (INR)"),"INR","GBP")) | F82: HSBC Rewards Credit Card (GBP) | G82: No | H82: =IF(G82="Yes","",D82) | I82: No
A83: 46138 | B83: New Balance Shoe | C83: Shopping | D83: 139.5 | E83: =IF(F83="","",IF(OR(F83="HDFC Bank (INR)",F83="HDFC IOCL Credit Card (INR)",F83="HDFC Swiggy Credit Card (INR)",F83="Axis Airtel Credit Card (INR)"),"INR","GBP")) | F83: Barclays Rewards Credit Card (GBP) | G83: No | H83: =IF(G83="Yes","",D83) | I83: No
A84: 46138 | B84: New Balance Shoe | C84: Shopping | D84: 139.5 | E84: =IF(F84="","",IF(OR(F84="HDFC Bank (INR)",F84="HDFC IOCL Credit Card (INR)",F84="HDFC Swiggy Credit Card (INR)",F84="Axis Airtel Credit Card (INR)"),"INR","GBP")) | F84: Lloyds Bank (GBP) | G84: No | H84: =IF(G84="Yes","",D84) | I84: No
A85: 46138 | B85: Temu | C85: Shopping | D85: 26.05 | E85: =IF(F85="","",IF(OR(F85="HDFC Bank (INR)",F85="HDFC IOCL Credit Card (INR)",F85="HDFC Swiggy Credit Card (INR)",F85="Axis Airtel Credit Card (INR)"),"INR","GBP")) | F85: HSBC Rewards Credit Card (GBP) | G85: No | H85: =IF(G85="Yes","",D85) | I85: No
A86: 46138 | B86: Amazon Weigh Scale | C86: Shopping | D86: 22.49 | E86: =IF(F86="","",IF(OR(F86="HDFC Bank (INR)",F86="HDFC IOCL Credit Card (INR)",F86="HDFC Swiggy Credit Card (INR)",F86="Axis Airtel Credit Card (INR)"),"INR","GBP")) | F86: Capitol One Credit Card (GBP) | G86: No | H86: =IF(G86="Yes","",D86) | I86: No
A87: 46150 | E87: =IF(F87="","",IF(OR(F87="HDFC Bank (INR)",F87="HDFC IOCL Credit Card (INR)",F87="HDFC Swiggy Credit Card (INR)",F87="Axis Airtel Credit Card (INR)"),"INR","GBP")) | H87: =IF(G87="Yes","",D87)
A88: 46150 | B88: Leto | C88: Food and Drinks | D88: 19.6 | E88: =IF(F88="","",IF(OR(F88="HDFC Bank (INR)",F88="HDFC IOCL Credit Card (INR)",F88="HDFC Swiggy Credit Card (INR)",F88="Axis Airtel Credit Card (INR)"),"INR","GBP")) | F88: Barclays Bank (GBP) | G88: Yes | H88: 9.8 | I88: No
A89: 46150 | B89: Off Licesnce | C89: Food and Drinks | D89: 5.78 | E89: =IF(F89="","",IF(OR(F89="HDFC Bank (INR)",F89="HDFC IOCL Credit Card (INR)",F89="HDFC Swiggy Credit Card (INR)",F89="Axis Airtel Credit Card (INR)"),"INR","GBP")) | F89: Lloyds Bank (GBP) | G89: Yes | H89: 2.89 | I89: No
A90: 46150 | B90: Five Guys | C90: Food and Drinks | D90: 12.2 | E90: =IF(F90="","",IF(OR(F90="HDFC Bank (INR)",F90="HDFC IOCL Credit Card (INR)",F90="HDFC Swiggy Credit Card (INR)",F90="Axis Airtel Credit Card (INR)"),"INR","GBP")) | F90: Barclays Bank (GBP) | G90: Yes | H90: 4.75 | I90: No
A91: 46150 | B91: Bhai Bday gift | C91: Gifts | D91: 175 | E91: =IF(F91="","",IF(OR(F91="HDFC Bank (INR)",F91="HDFC IOCL Credit Card (INR)",F91="HDFC Swiggy Credit Card (INR)",F91="Axis Airtel Credit Card (INR)"),"INR","GBP")) | F91: Splitwise (GBP) | G91: No | H91: =IF(G91="Yes","",D91) | I91: No
A92: 46150 | B92: EHH Carrots | C92: Groceries | D92: 0.27 | E92: =IF(F92="","",IF(OR(F92="HDFC Bank (INR)",F92="HDFC IOCL Credit Card (INR)",F92="HDFC Swiggy Credit Card (INR)",F92="Axis Airtel Credit Card (INR)"),"INR","GBP")) | F92: Splitwise (GBP) | G92: No | H92: =IF(G92="Yes","",D92) | I92: No
A93: 46150 | B93: EHH Tomatoes | C93: Groceries | D93: 0.7 | E93: =IF(F93="","",IF(OR(F93="HDFC Bank (INR)",F93="HDFC IOCL Credit Card (INR)",F93="HDFC Swiggy Credit Card (INR)",F93="Axis Airtel Credit Card (INR)"),"INR","GBP")) | F93: Splitwise (GBP) | G93: No | H93: =IF(G93="Yes","",D93) | I93: No
A94: 46150 | B94: EHH Pepper Brocli | C94: Groceries | D94: 2.85 | E94: =IF(F94="","",IF(OR(F94="HDFC Bank (INR)",F94="HDFC IOCL Credit Card (INR)",F94="HDFC Swiggy Credit Card (INR)",F94="Axis Airtel Credit Card (INR)"),"INR","GBP")) | F94: Splitwise (GBP) | G94: No | H94: =IF(G94="Yes","",D94) | I94: No
A95: 46150 | B95: EHH Lidl | C95: Groceries | D95: 1.15 | E95: =IF(F95="","",IF(OR(F95="HDFC Bank (INR)",F95="HDFC IOCL Credit Card (INR)",F95="HDFC Swiggy Credit Card (INR)",F95="Axis Airtel Credit Card (INR)"),"INR","GBP")) | F95: Splitwise (GBP) | G95: No | H95: =IF(G95="Yes","",D95) | I95: No
A96: 46150 | B96: EHH Fish | C96: Groceries | D96: 4.16 | E96: =IF(F96="","",IF(OR(F96="HDFC Bank (INR)",F96="HDFC IOCL Credit Card (INR)",F96="HDFC Swiggy Credit Card (INR)",F96="Axis Airtel Credit Card (INR)"),"INR","GBP")) | F96: Splitwise (GBP) | G96: No | H96: =IF(G96="Yes","",D96) | I96: No
A97: 46150 | B97: EHH Rent | C97: Rent | D97: 15 | E97: =IF(F97="","",IF(OR(F97="HDFC Bank (INR)",F97="HDFC IOCL Credit Card (INR)",F97="HDFC Swiggy Credit Card (INR)",F97="Axis Airtel Credit Card (INR)"),"INR","GBP")) | F97: Splitwise (GBP) | G97: No | H97: =IF(G97="Yes","",D97) | I97: No
A98: 46150 | B98: EHH Rice | C98: Groceries | D98: 4.33 | E98: =IF(F98="","",IF(OR(F98="HDFC Bank (INR)",F98="HDFC IOCL Credit Card (INR)",F98="HDFC Swiggy Credit Card (INR)",F98="Axis Airtel Credit Card (INR)"),"INR","GBP")) | F98: Splitwise (GBP) | G98: No | H98: =IF(G98="Yes","",D98) | I98: No
A99: 46150 | B99: EHH Lemons | C99: Groceries | D99: 0.3 | E99: =IF(F99="","",IF(OR(F99="HDFC Bank (INR)",F99="HDFC IOCL Credit Card (INR)",F99="HDFC Swiggy Credit Card (INR)",F99="Axis Airtel Credit Card (INR)"),"INR","GBP")) | F99: Splitwise (GBP) | G99: No | H99: =IF(G99="Yes","",D99) | I99: No
A100: 46150 | B100: Pan parak | C100: Others | D100: 9 | E100: =IF(F100="","",IF(OR(F100="HDFC Bank (INR)",F100="HDFC IOCL Credit Card (INR)",F100="HDFC Swiggy Credit Card (INR)",F100="Axis Airtel Credit Card (INR)"),"INR","GBP")) | F100: Lloyds Bank (GBP) | G100: No | H100: =IF(G100="Yes","",D100) | I100: No
...

Sheet Income
A1: INCOME TRACKER
A2: Date of Credit | B2: Company | C2: Amount | D2: Currency | E2: Bank Account Credited | F2: Pay Cycle Start | G2: Pay Cycle End
A3: 46122 | B3: Kolumba Carnaby | C3: 2277.44 | D3: =IF(E3="","",IF(E3="HDFC Bank (INR)","INR","GBP")) | E3: Barclays Bank (GBP) | F3: 46089 | G3: 46116
A4: 46129 | B4: Family and Friends | C4: 25012 | D4: =IF(E4="","",IF(E4="HDFC Bank (INR)","INR","GBP")) | E4: HDFC Bank (INR) | F4: 46129 | G4: 46129
A5: 46143 | B5: Gaia Pulses LTD | C5: 370 | D5: =IF(E5="","",IF(E5="HDFC Bank (INR)","INR","GBP")) | E5: HSBC Bank (GBP) | F5: 46051 | G5: 46081
A6: 46150 | B6: Kolumba Carnaby | C6: 1447.53 | D6: =IF(E6="","",IF(E6="HDFC Bank (INR)","INR","GBP")) | E6: Barclays Bank (GBP) | F6: 46118 | G6: 46145
D7: =IF(E7="","",IF(E7="HDFC Bank (INR)","INR","GBP"))
D8: =IF(E8="","",IF(E8="HDFC Bank (INR)","INR","GBP"))
D9: =IF(E9="","",IF(E9="HDFC Bank (INR)","INR","GBP"))
D10: =IF(E10="","",IF(E10="HDFC Bank (INR)","INR","GBP"))
D11: =IF(E11="","",IF(E11="HDFC Bank (INR)","INR","GBP"))
D12: =IF(E12="","",IF(E12="HDFC Bank (INR)","INR","GBP"))
D13: =IF(E13="","",IF(E13="HDFC Bank (INR)","INR","GBP"))
D14: =IF(E14="","",IF(E14="HDFC Bank (INR)","INR","GBP"))
D15: =IF(E15="","",IF(E15="HDFC Bank (INR)","INR","GBP"))
D16: =IF(E16="","",IF(E16="HDFC Bank (INR)","INR","GBP"))
D17: =IF(E17="","",IF(E17="HDFC Bank (INR)","INR","GBP"))
D18: =IF(E18="","",IF(E18="HDFC Bank (INR)","INR","GBP"))
... D502: =IF(E502="","",IF(E502="HDFC Bank (INR)","INR","GBP"))

Sheet Transfers
A1: TRANSFERS (Credit Card Payments & Top-ups)
A2: Date | B2: Description | C2: To Account | D2: From Account | E2: Amount | F2: Notes
A3: 46122 | B3: Barclays Card | C3: Barclays Rewards Credit Card (GBP) | D3: Barclays Bank (GBP) | E3: 680.53
A4: 46122 | B4: Tissot Last Payment | C4: Klarna Pay Later (GBP) | D4: Barclays Rewards Credit Card (GBP) | E4: 181.34
A5: 46122 | B5: Savings | C5: HSBC Bank (GBP) | D5: Barclays Bank (GBP) | E5: 1251.14
A6: 46122 | B6: Rent Savings | C6: Halifax Bank (GBP) | D6: Barclays Bank (GBP) | E6: 101.84
A7: 46122 | B7: Tanisha Split Clear | C7: Lloyds Bank (GBP) | D7: Splitwise (GBP) | E7: 50
A8: 46122 | B8: Ajith Split Clear | C8: Splitwise (GBP) | D8: Lloyds Bank (GBP) | E8: 5.22
A9: 46122 | B9: Bilques Split Clear | C9: Splitwise (GBP) | D9: Halifax Bank (GBP) | E9: 64.51
A10: 46126 | B10: Tanisha Split Clear | C10: Halifax Bank (GBP) | D10: Splitwise (GBP) | E10: 19.09
A11: 46126 | B11: Kuldeep Split Clear | C11: Splitwise (GBP) | D11: Halifax Bank (GBP) | E11: 18.57
A12: 46126 | B12: HSBC Payment | C12: HSBC Rewards Credit Card (GBP) | D12: HSBC Bank (GBP) | E12: 505.93
A13: 46126 | B13: Axis Bank Statememnt | C13: Axis Airtel Credit Card (INR) | D13: HDFC Bank (INR) | E13: 28550.9
A14: 46129 | B14: Capitol one | C14: Capitol One Credit Card (GBP) | D14: Barclays Bank (GBP) | E14: 41.97
A15: 46133 | B15: Nike retails | C15: HSBC Rewards Credit Card (GBP) | E15: 71.99
A16: 46133 | B16: Credit Card Payment Swiggy | C16: HDFC Swiggy Credit Card (INR) | D16: HDFC Bank (INR) | E16: 799
A17: 46133 | B17: Credit Card Payment IOCL | C17: HDFC IOCL Credit Card (INR) | D17: HDFC Bank (INR) | E17: 335
A18: 46133 | B18: Oyste recharge | C18: Oyster Travel Card (GBP) | D18: Klarna Pay (GBP) | E18: 25
A19: 46133 | B19: Adidas Return | C19: Lloyds Bank (GBP) | E19: 140
A20: 46138 | B20: New Balance Return
A21: 46138 | B21: JD Sport Return | C21: HSBC Rewards Credit Card (GBP) | E21: 117
A22: 46138 | B22: Photo Album return | C22: Capitol One Credit Card (GBP) | E22: 6.99
A23: 46150 | B23: Bilques Split Clear | C23: Splitwise (GBP) | D23: Halifax Bank (GBP) | E23: 46.53
A24: 46150 | B24: Bilques Split Clear | C24: Splitwise (GBP) | D24: Halifax Bank (GBP) | E24: 153
A25: 46150 | B25: Barclays Card | C25: Barclays Rewards Credit Card (GBP) | D25: Barclays Bank (GBP) | E25: 445.97
A26: 46150 | B26: Oyste recharge | C26: Oyster Travel Card (GBP) | D26: Barclays Bank (GBP) | E26: 80
A27: 46150 | B27: Capitol one | C27: Capitol One Credit Card (GBP) | D27: Barclays Bank (GBP) | E27: 61.57
A28: 46150 | B28: Axis Bank Statememnt | C28: Axis Airtel Credit Card (INR) | D28: HDFC Bank (INR) | E28: 28000
A29: 46150 | B29: Axis Bank Statememnt | C29: Axis Airtel Credit Card (INR) | D29: HDFC Bank (INR) | E29: =30454.71-E28

Sheet Balances
A1: ACCOUNT BALANCES
A2: Account | B2: Type | C2: Currency | D2: Opening Balance / Credit Limit | E2: Total Credits | F2: Total Debits | G2: Current Balance / Available Credit | H2: CC Dues | I2: Tally Satus
A3: Lloyds Bank (GBP) | B3: Bank Account | C3: GBP | D3: 79.61 | E3: =SUMIFS(Income!C$3:C$502,Income!E$3:E$502,A3)+SUMIFS(Transfers!E$3:E$501,Transfers!C$3:C$501,A3) | F3: =SUMIFS(Expenses!D$3:D$999,Expenses!F$3:F$999,A3)+SUMIFS(Transfers!E$3:E$501,Transfers!D$3:D$501,A3) | G3: =D3+E3-F3 | I3: TRUE
A4: HSBC Bank (GBP) | B4: Bank Account | C4: GBP | D4: =Accounts!F4 | E4: =SUMIFS(Income!C$3:C$502,Income!E$3:E$502,A4)+SUMIFS(Transfers!E$3:E$501,Transfers!C$3:C$501,A4) | F4: =SUMIFS(Expenses!D$3:D$999,Expenses!F$3:F$999,A4)+SUMIFS(Transfers!E$3:E$501,Transfers!D$3:D$501,A4) | G4: =D4+E4-F4 | I4: TRUE
A5: Barclays Bank (GBP) | B5: Bank Account | C5: GBP | D5: =Accounts!F5 | E5: =SUMIFS(Income!C$3:C$502,Income!E$3:E$502,A5)+SUMIFS(Transfers!E$3:E$501,Transfers!C$3:C$501,A5) | F5: =SUMIFS(Expenses!D$3:D$999,Expenses!F$3:F$999,A5)+SUMIFS(Transfers!E$3:E$501,Transfers!D$3:D$501,A5) | G5: =D5+E5-F5 | I5: TRUE
A6: Halifax Bank (GBP) | B6: Bank Account | C6: GBP | D6: =Accounts!F6 | E6: =SUMIFS(Income!C$3:C$502,Income!E$3:E$502,A6)+SUMIFS(Transfers!E$3:E$501,Transfers!C$3:C$501,A6) | F6: =SUMIFS(Expenses!D$3:D$999,Expenses!F$3:F$999,A6)+SUMIFS(Transfers!E$3:E$501,Transfers!D$3:D$501,A6) | G6: =D6+E6-F6 | I6: Discontinued
A7: Klarna Pay (GBP) | B7: Bank Account | C7: GBP | D7: =Accounts!F7 | E7: =SUMIFS(Income!C$3:C$502,Income!E$3:E$502,A7)+SUMIFS(Transfers!E$3:E$501,Transfers!C$3:C$501,A7) | F7: =SUMIFS(Expenses!D$3:D$999,Expenses!F$3:F$999,A7)+SUMIFS(Transfers!E$3:E$501,Transfers!D$3:D$501,A7) | G7: =D7+E7-F7 | I7: TRUE
A8: Capitol One Credit Card (GBP) | B8: Credit Card | C8: GBP | D8: =Accounts!F8 | E8: =SUMIFS(Income!C$3:C$502,Income!E$3:E$502,A8)+SUMIFS(Transfers!E$3:E$501,Transfers!C$3:C$501,A8) | F8: =SUMIFS(Expenses!D$3:D$999,Expenses!F$3:F$999,A8)+SUMIFS(Transfers!E$3:E$501,Transfers!D$3:D$501,A8) | G8: =D8+E8-F8 | H8: =550-G8 | I8: TRUE
A9: HSBC Rewards Credit Card (GBP) | B9: Credit Card | C9: GBP | D9: =Accounts!F9 | E9: =SUMIFS(Income!C$3:C$502,Income!E$3:E$502,A9)+SUMIFS(Transfers!E$3:E$501,Transfers!C$3:C$501,A9) | F9: =SUMIFS(Expenses!D$3:D$999,Expenses!F$3:F$999,A9)+SUMIFS(Transfers!E$3:E$501,Transfers!D$3:D$501,A9) | G9: =D9+E9-F9 | H9: =6000-G9 | I9: TRUE
A10: Barclays Rewards Credit Card (GBP) | B10: Credit Card | C10: GBP | D10: =Accounts!F10 | E10: =SUMIFS(Income!C$3:C$502,Income!E$3:E$502,A10)+SUMIFS(Transfers!E$3:E$501,Transfers!C$3:C$501,A10) | F10: =SUMIFS(Expenses!D$3:D$999,Expenses!F$3:F$999,A10)+SUMIFS(Transfers!E$3:E$501,Transfers!D$3:D$501,A10) | G10: =D10+E10-F10 | H10: =3500-G10 | I10: TRUE
A11: Klarna Pay Later (GBP) | B11: Pay Later | C11: GBP | D11: 0 | E11: =SUMIFS(Income!C$3:C$502,Income!E$3:E$502,A11)+SUMIFS(Transfers!E$3:E$501,Transfers!C$3:C$501,A11) | F11: =SUMIFS(Expenses!D$3:D$999,Expenses!F$3:F$999,A11)+SUMIFS(Transfers!E$3:E$501,Transfers!D$3:D$501,A11) | G11: =D11+E11-F11 | I11: TRUE
A12: Splitwise (GBP) | B12: Expense Sharing | C12: GBP | D12: =5.18-28.41-0.49-0.32+7.5 | E12: =SUMPRODUCT((Expenses!G$3:G$999="Yes")*(Expenses!D$3:D$999-Expenses!H$3:H$999))+SUMIFS(Transfers!E$3:E$501,Transfers!C$3:C$501,A12) | F12: =SUMIFS(Expenses!D$3:D$999,Expenses!F$3:F$999,A12)+SUMIFS(Transfers!E$3:E$501,Transfers!D$3:D$501,A12) | G12: =D12+E12-F12 | I12: TRUE
A13: Oyster Travel Card (GBP) | B13: Travel Card | C13: GBP | D13: =Accounts!F13 | E13: =SUMIFS(Income!C$3:C$502,Income!E$3:E$502,A13)+SUMIFS(Transfers!E$3:E$501,Transfers!C$3:C$501,A13) | F13: =SUMIFS(Expenses!D$3:D$999,Expenses!F$3:F$999,A13)+SUMIFS(Transfers!E$3:E$501,Transfers!D$3:D$501,A13) | G13: =D13+E13-F13 | I13: TRUE
A14: HDFC Bank (INR) | B14: Bank Account | C14: INR | D14: =Accounts!F14 | E14: =SUMIFS(Income!C$3:C$502,Income!E$3:E$502,A14)+SUMIFS(Transfers!E$3:E$501,Transfers!C$3:C$501,A14) | F14: =SUMIFS(Expenses!D$3:D$999,Expenses!F$3:F$999,A14)+SUMIFS(Transfers!E$3:E$501,Transfers!D$3:D$501,A14) | G14: =D14+E14-F14 | I14: FALSE
A15: HDFC IOCL Credit Card (INR) | B15: Credit Card | C15: INR | D15: =Accounts!F15 | E15: =SUMIFS(Income!C$3:C$502,Income!E$3:E$502,A15)+SUMIFS(Transfers!E$3:E$501,Transfers!C$3:C$501,A15) | F15: =SUMIFS(Expenses!D$3:D$999,Expenses!F$3:F$999,A15)+SUMIFS(Transfers!E$3:E$501,Transfers!D$3:D$501,A15) | G15: =D15+E15-F15 | I15: FALSE
A16: HDFC Swiggy Credit Card (INR) | B16: Credit Card | C16: INR | D16: =Accounts!F16 | E16: =SUMIFS(Income!C$3:C$502,Income!E$3:E$502,A16)+SUMIFS(Transfers!E$3:E$501,Transfers!C$3:C$501,A16) | F16: =SUMIFS(Expenses!D$3:D$999,Expenses!F$3:F$999,A16)+SUMIFS(Transfers!E$3:E$501,Transfers!D$3:D$501,A16) | G16: =D16+E16-F16 | I16: FALSE
A17: Axis Airtel Credit Card (INR) | B17: Credit Card | C17: INR | D17: =Accounts!F17 | E17: =SUMIFS(Income!C$3:C$502,Income!E$3:E$502,A17)+SUMIFS(Transfers!E$3:E$501,Transfers!C$3:C$501,A17) | F17: =SUMIFS(Expenses!D$3:D$999,Expenses!F$3:F$999,A17)+SUMIFS(Transfers!E$3:E$501,Transfers!D$3:D$501,A17) | G17: =D17+E17-F17 | I17: FALSE
A18: Chase Bank (GBP) | B18: Bank Account | C18: GBP | D18: 0 | E18: =SUMIFS(Income!C$3:C$502,Income!E$3:E$502,A18) | F18: =SUMIFS(Expenses!D$3:D$999,Expenses!F$3:F$999,A18) | G18: =D18+E18-F18 | I18: True
A19: Monzo (GBP) | B19: Bank Account | C19: GBP | D19: 0 | E19: =SUMIFS(Income!C$3:C$502,Income!E$3:E$502,A19) | F19: =SUMIFS(Expenses!D$3:D$999,Expenses!F$3:F$999,A19) | G19: =D19+E19-F19 | I19: True
A20: DASHBOARD SUMMARY
A21: Total GBP Bank Assets | B21: =SUMPRODUCT((C3:C19="GBP")*(B3:B19="Bank Account")*G3:G19) | G21: Balance Summary
A22: Total GBP Credit Card Debt | B22: =SUMIFS(F3:F19,C3:C19,"GBP",B3:B19,"Credit Card") | D22: =B21-B22 | G22: Bilquis | H22: -0.67
A23: Total INR Bank Assets | B23: =SUMPRODUCT((C3:C19="INR")*(B3:B19="Bank Account")*G3:G19) | G23: Tanisha | H23: 4.17
A24: Total INR Credit Card Debt | B24: =SUMIFS(F3:F19,C3:C19,"INR",B3:B19,"Credit Card") | G24: Bhanu | H24: 4
A25: Exchange Rate (GBP to INR) | B25: =Settings!B4
A26: Approx Combined GBP Equivalent | B26: =B21-B22+(B23-B24)/B25

Sheet Monthly Overview GBP
A1: MONTHLY OVERVIEW (GBP)
A2: Month | B2: Rent | C2: Transport | D2: Travel | E2: Shopping | F2: Electronics | G2: Subscriptions | H2: Bills | I2: Entertainment | J2: Food and Drinks | K2: Groceries | L2: Others | M2: Gifts | N2: Donations | O2: Investments | P2: Total Expenditure | Q2: Income | R2: Gross Savings
A3: January 2026 | B3: =SUMPRODUCT((Expenses!C$3:C$999="Rent")*(Expenses!E$3:E$999="GBP")*(MONTH(Expenses!A$3:A$999)=1)*(YEAR(Expenses!A$3:A$999)=2026)*(Expenses!A$3:A$999<>"")*(IF(Expenses!G$3:G$999="Yes",Expenses!H$3:H$999,Expenses!D$3:D$999))) | C3: =SUMPRODUCT((Expenses!C$3:C$999="Transport")*(Expenses!E$3:E$999="GBP")*(MONTH(Expenses!A$3:A$999)=1)*(YEAR(Expenses!A$3:A$999)=2026)*(Expenses!A$3:A$999<>"")*(IF(Expenses!G$3:G$999="Yes",Expenses!H$3:H$999,Expenses!D$3:D$999))) | D3: =SUMPRODUCT((Expenses!C$3:C$999="Travel")*(Expenses!E$3:E$999="GBP")*(MONTH(Expenses!A$3:A$999)=1)*(YEAR(Expenses!A$3:A$999)=2026)*(Expenses!A$3:A$999<>"")*(IF(Expenses!G$3:G$999="Yes",Expenses!H$3:H$999,Expenses!D$3:D$999))) | E3: =SUMPRODUCT((Expenses!C$3:C$999="Shopping")*(Expenses!E$3:E$999="GBP")*(MONTH(Expenses!A$3:A$999)=1)*(YEAR(Expenses!A$3:A$999)=2026)*(Expenses!A$3:A$999<>"")*(IF(Expenses!G$3:G$999="Yes",Expenses!H$3:H$999,Expenses!D$3:D$999))) | F3: =SUMPRODUCT((Expenses!C$3:C$999="Electronics")*(Expenses!E$3:E$999="GBP")*(MONTH(Expenses!A$3:A$999)=1)*(YEAR(Expenses!A$3:A$999)=2026)*(Expenses!A$3:A$999<>"")*(IF(Expenses!G$3:G$999="Yes",Expenses!H$3:H$999,Expenses!D$3:D$999))) | G3: =SUMPRODUCT((Expenses!C$3:C$999="Subscriptions")*(Expenses!E$3:E$999="GBP")*(MONTH(Expenses!A$3:A$999)=1)*(YEAR(Expenses!A$3:A$999)=2026)*(Expenses!A$3:A$999<>"")*(IF(Expenses!G$3:G$999="Yes",Expenses!H$3:H$999,Expenses!D$3:D$999))) | H3: =SUMPRODUCT((Expenses!C$3:C$999="Bills")*(Expenses!E$3:E$999="GBP")*(MONTH(Expenses!A$3:A$999)=1)*(YEAR(Expenses!A$3:A$999)=2026)*(Expenses!A$3:A$999<>"")*(IF(Expenses!G$3:G$999="Yes",Expenses!H$3:H$999,Expenses!D$3:D$999))) | I3: =SUMPRODUCT((Expenses!C$3:C$999="Entertainment")*(Expenses!E$3:E$999="GBP")*(MONTH(Expenses!A$3:A$999)=1)*(YEAR(Expenses!A$3:A$999)=2026)*(Expenses!A$3:A$999<>"")*(IF(Expenses!G$3:G$999="Yes",Expenses!H$3:H$999,Expenses!D$3:D$999))) | J3: =SUMPRODUCT((Expenses!C$3:C$999="Food and Drinks")*(Expenses!E$3:E$999="GBP")*(MONTH(Expenses!A$3:A$999)=1)*(YEAR(Expenses!A$3:A$999)=2026)*(Expenses!A$3:A$999<>"")*(IF(Expenses!G$3:G$999="Yes",Expenses!H$3:H$999,Expenses!D$3:D$999))) | K3: =SUMPRODUCT((Expenses!C$3:C$999="Groceries")*(Expenses!E$3:E$999="GBP")*(MONTH(Expenses!A$3:A$999)=1)*(YEAR(Expenses!A$3:A$999)=2026)*(Expenses!A$3:A$999<>"")*(IF(Expenses!G$3:G$999="Yes",Expenses!H$3:H$999,Expenses!D$3:D$999))) | L3: =SUMPRODUCT((Expenses!C$3:C$999="Others")*(Expenses!E$3:E$999="GBP")*(MONTH(Expenses!A$3:A$999)=1)*(YEAR(Expenses!A$3:A$999)=2026)*(Expenses!A$3:A$999<>"")*(IF(Expenses!G$3:G$999="Yes",Expenses!H$3:H$999,Expenses!D$3:D$999))) | M3: =SUMPRODUCT((Expenses!C$3:C$999="Gifts")*(Expenses!E$3:E$999="GBP")*(MONTH(Expenses!A$3:A$999)=1)*(YEAR(Expenses!A$3:A$999)=2026)*(Expenses!A$3:A$999<>"")*(IF(Expenses!G$3:G$999="Yes",Expenses!H$3:H$999,Expenses!D$3:D$999))) | N3: =SUMPRODUCT((Expenses!C$3:C$999="Donations")*(Expenses!E$3:E$999="GBP")*(MONTH(Expenses!A$3:A$999)=1)*(YEAR(Expenses!A$3:A$999)=2026)*(Expenses!A$3:A$999<>"")*(IF(Expenses!G$3:G$999="Yes",Expenses!H$3:H$999,Expenses!D$3:D$999))) | O3: =SUMPRODUCT((Expenses!C$3:C$999="Investments")*(Expenses!E$3:E$999="GBP")*(MONTH(Expenses!A$3:A$999)=1)*(YEAR(Expenses!A$3:A$999)=2026)*(Expenses!A$3:A$999<>"")*(IF(Expenses!G$3:G$999="Yes",Expenses!H$3:H$999,Expenses!D$3:D$999))) | P3: =SUM(B3:O3) | Q3: =SUMPRODUCT((Income!D$3:D$502="GBP")*(MONTH(Income!A$3:A$502)=1)*(YEAR(Income!A$3:A$502)=2026)*(Income!A$3:A$502<>"")*Income!C$3:C$502) | R3: =Q3-P3
A4: February 2026 | B4: =SUMPRODUCT((Expenses!C$3:C$999="Rent")*(Expenses!E$3:E$999="GBP")*(MONTH(Expenses!A$3:A$999)=2)*(YEAR(Expenses!A$3:A$999)=2026)*(Expenses!A$3:A$999<>"")*(IF(Expenses!G$3:G$999="Yes",Expenses!H$3:H$999,Expenses!D$3:D$999))) | C4: =SUMPRODUCT((Expenses!C$3:C$999="Transport")*(Expenses!E$3:E$999="GBP")*(MONTH(Expenses!A$3:A$999)=2)*(YEAR(Expenses!A$3:A$999)=2026)*(Expenses!A$3:A$999<>"")*(IF(Expenses!G$3:G$999="Yes",Expenses!H$3:H$999,Expenses!D$3:D$999))) | D4: =SUMPRODUCT((Expenses!C$3:C$999="Travel")*(Expenses!E$3:E$999="GBP")*(MONTH(Expenses!A$3:A$999)=2)*(YEAR(Expenses!A$3:A$999)=2026)*(Expenses!A$3:A$999<>"")*(IF(Expenses!G$3:G$999="Yes",Expenses!H$3:H$999,Expenses!D$3:D$999))) | E4: =SUMPRODUCT((Expenses!C$3:C$999="Shopping")*(Expenses!E$3:E$999="GBP")*(MONTH(Expenses!A$3:A$999)=2)*(YEAR(Expenses!A$3:A$999)=2026)*(Expenses!A$3:A$999<>"")*(IF(Expenses!G$3:G$999="Yes",Expenses!H$3:H$999,Expenses!D$3:D$999))) | F4: =SUMPRODUCT((Expenses!C$3:C$999="Electronics")*(Expenses!E$3:E$999="GBP")*(MONTH(Expenses!A$3:A$999)=2)*(YEAR(Expenses!A$3:A$999)=2026)*(Expenses!A$3:A$999<>"")*(IF(Expenses!G$3:G$999="Yes",Expenses!H$3:H$999,Expenses!D$3:D$999))) | G4: =SUMPRODUCT((Expenses!C$3:C$999="Subscriptions")*(Expenses!E$3:E$999="GBP")*(MONTH(Expenses!A$3:A$999)=2)*(YEAR(Expenses!A$3:A$999)=2026)*(Expenses!A$3:A$999<>"")*(IF(Expenses!G$3:G$999="Yes",Expenses!H$3:H$999,Expenses!D$3:D$999))) | H4: =SUMPRODUCT((Expenses!C$3:C$999="Bills")*(Expenses!E$3:E$999="GBP")*(MONTH(Expenses!A$3:A$999)=2)*(YEAR(Expenses!A$3:A$999)=2026)*(Expenses!A$3:A$999<>"")*(IF(Expenses!G$3:G$999="Yes",Expenses!H$3:H$999,Expenses!D$3:D$999))) | I4: =SUMPRODUCT((Expenses!C$3:C$999="Entertainment")*(Expenses!E$3:E$999="GBP")*(MONTH(Expenses!A$3:A$999)=2)*(YEAR(Expenses!A$3:A$999)=2026)*(Expenses!A$3:A$999<>"")*(IF(Expenses!G$3:G$999="Yes",Expenses!H$3:H$999,Expenses!D$3:D$999))) | J4: =SUMPRODUCT((Expenses!C$3:C$999="Food and Drinks")*(Expenses!E$3:E$999="GBP")*(MONTH(Expenses!A$3:A$999)=2)*(YEAR(Expenses!A$3:A$999)=2026)*(Expenses!A$3:A$999<>"")*(IF(Expenses!G$3:G$999="Yes",Expenses!H$3:H$999,Expenses!D$3:D$999))) | K4: =SUMPRODUCT((Expenses!C$3:C$999="Groceries")*(Expenses!E$3:E$999="GBP")*(MONTH(Expenses!A$3:A$999)=2)*(YEAR(Expenses!A$3:A$999)=2026)*(Expenses!A$3:A$999<>"")*(IF(Expenses!G$3:G$999="Yes",Expenses!H$3:H$999,Expenses!D$3:D$999))) | L4: =SUMPRODUCT((Expenses!C$3:C$999="Others")*(Expenses!E$3:E$999="GBP")*(MONTH(Expenses!A$3:A$999)=2)*(YEAR(Expenses!A$3:A$999)=2026)*(Expenses!A$3:A$999<>"")*(IF(Expenses!G$3:G$999="Yes",Expenses!H$3:H$999,Expenses!D$3:D$999))) | M4: =SUMPRODUCT((Expenses!C$3:C$999="Gifts")*(Expenses!E$3:E$999="GBP")*(MONTH(Expenses!A$3:A$999)=2)*(YEAR(Expenses!A$3:A$999)=2026)*(Expenses!A$3:A$999<>"")*(IF(Expenses!G$3:G$999="Yes",Expenses!H$3:H$999,Expenses!D$3:D$999))) | N4: =SUMPRODUCT((Expenses!C$3:C$999="Donations")*(Expenses!E$3:E$999="GBP")*(MONTH(Expenses!A$3:A$999)=2)*(YEAR(Expenses!A$3:A$999)=2026)*(Expenses!A$3:A$999<>"")*(IF(Expenses!G$3:G$999="Yes",Expenses!H$3:H$999,Expenses!D$3:D$999))) | O4: =SUMPRODUCT((Expenses!C$3:C$999="Investments")*(Expenses!E$3:E$999="GBP")*(MONTH(Expenses!A$3:A$999)=2)*(YEAR(Expenses!A$3:A$999)=2026)*(Expenses!A$3:A$999<>"")*(IF(Expenses!G$3:G$999="Yes",Expenses!H$3:H$999,Expenses!D$3:D$999))) | P4: =SUM(B4:O4) | Q4: =SUMPRODUCT((Income!D$3:D$502="GBP")*(MONTH(Income!A$3:A$502)=2)*(YEAR(Income!A$3:A$502)=2026)*(Income!A$3:A$502<>"")*Income!C$3:C$502) | R4: =Q4-P4
A5: March 2026 | B5: =SUMPRODUCT((Expenses!C$3:C$999="Rent")*(Expenses!E$3:E$999="GBP")*(MONTH(Expenses!A$3:A$999)=3)*(YEAR(Expenses!A$3:A$999)=2026)*(Expenses!A$3:A$999<>"")*(IF(Expenses!G$3:G$999="Yes",Expenses!H$3:H$999,Expenses!D$3:D$999))) | C5: =SUMPRODUCT((Expenses!C$3:C$999="Transport")*(Expenses!E$3:E$999="GBP")*(MONTH(Expenses!A$3:A$999)=3)*(YEAR(Expenses!A$3:A$999)=2026)*(Expenses!A$3:A$999<>"")*(IF(Expenses!G$3:G$999="Yes",Expenses!H$3:H$999,Expenses!D$3:D$999))) | D5: =SUMPRODUCT((Expenses!C$3:C$999="Travel")*(Expenses!E$3:E$999="GBP")*(MONTH(Expenses!A$3:A$999)=3)*(YEAR(Expenses!A$3:A$999)=2026)*(Expenses!A$3:A$999<>"")*(IF(Expenses!G$3:G$999="Yes",Expenses!H$3:H$999,Expenses!D$3:D$999))) | E5: =SUMPRODUCT((Expenses!C$3:C$999="Shopping")*(Expenses!E$3:E$999="GBP")*(MONTH(Expenses!A$3:A$999)=3)*(YEAR(Expenses!A$3:A$999)=2026)*(Expenses!A$3:A$999<>"")*(IF(Expenses!G$3:G$999="Yes",Expenses!H$3:H$999,Expenses!D$3:D$999))) | F5: =SUMPRODUCT((Expenses!C$3:C$999="Electronics")*(Expenses!E$3:E$999="GBP")*(MONTH(Expenses!A$3:A$999)=3)*(YEAR(Expenses!A$3:A$999)=2026)*(Expenses!A$3:A$999<>"")*(IF(Expenses!G$3:G$999="Yes",Expenses!H$3:H$999,Expenses!D$3:D$999))) | G5: =SUMPRODUCT((Expenses!C$3:C$999="Subscriptions")*(Expenses!E$3:E$999="GBP")*(MONTH(Expenses!A$3:A$999)=3)*(YEAR(Expenses!A$3:A$999)=2026)*(Expenses!A$3:A$999<>"")*(IF(Expenses!G$3:G$999="Yes",Expenses!H$3:H$999,Expenses!D$3:D$999))) | H5: =SUMPRODUCT((Expenses!C$3:C$999="Bills")*(Expenses!E$3:E$999="GBP")*(MONTH(Expenses!A$3:A$999)=3)*(YEAR(Expenses!A$3:A$999)=2026)*(Expenses!A$3:A$999<>"")*(IF(Expenses!G$3:G$999="Yes",Expenses!H$3:H$999,Expenses!D$3:D$999))) | I5: =SUMPRODUCT((Expenses!C$3:C$999="Entertainment")*(Expenses!E$3:E$999="GBP")*(MONTH(Expenses!A$3:A$999)=3)*(YEAR(Expenses!A$3:A$999)=2026)*(Expenses!A$3:A$999<>"")*(IF(Expenses!G$3:G$999="Yes",Expenses!H$3:H$999,Expenses!D$3:D$999))) | J5: =SUMPRODUCT((Expenses!C$3:C$999="Food and Drinks")*(Expenses!E$3:E$999="GBP")*(MONTH(Expenses!A$3:A$999)=3)*(YEAR(Expenses!A$3:A$999)=2026)*(Expenses!A$3:A$999<>"")*(IF(Expenses!G$3:G$999="Yes",Expenses!H$3:H$999,Expenses!D$3:D$999))) | K5: =SUMPRODUCT((Expenses!C$3:C$999="Groceries")*(Expenses!E$3:E$999="GBP")*(MONTH(Expenses!A$3:A$999)=3)*(YEAR(Expenses!A$3:A$999)=2026)*(Expenses!A$3:A$999<>"")*(IF(Expenses!G$3:G$999="Yes",Expenses!H$3:H$999,Expenses!D$3:D$999))) | L5: =SUMPRODUCT((Expenses!C$3:C$999="Others")*(Expenses!E$3:E$999="GBP")*(MONTH(Expenses!A$3:A$999)=3)*(YEAR(Expenses!A$3:A$999)=2026)*(Expenses!A$3:A$999<>"")*(IF(Expenses!G$3:G$999="Yes",Expenses!H$3:H$999,Expenses!D$3:D$999))) | M5: =SUMPRODUCT((Expenses!C$3:C$999="Gifts")*(Expenses!E$3:E$999="GBP")*(MONTH(Expenses!A$3:A$999)=3)*(YEAR(Expenses!A$3:A$999)=2026)*(Expenses!A$3:A$999<>"")*(IF(Expenses!G$3:G$999="Yes",Expenses!H$3:H$999,Expenses!D$3:D$999))) | N5: =SUMPRODUCT((Expenses!C$3:C$999="Donations")*(Expenses!E$3:E$999="GBP")*(MONTH(Expenses!A$3:A$999)=3)*(YEAR(Expenses!A$3:A$999)=2026)*(Expenses!A$3:A$999<>"")*(IF(Expenses!G$3:G$999="Yes",Expenses!H$3:H$999,Expenses!D$3:D$999))) | O5: =SUMPRODUCT((Expenses!C$3:C$999="Investments")*(Expenses!E$3:E$999="GBP")*(MONTH(Expenses!A$3:A$999)=3)*(YEAR(Expenses!A$3:A$999)=2026)*(Expenses!A$3:A$999<>"")*(IF(Expenses!G$3:G$999="Yes",Expenses!H$3:H$999,Expenses!D$3:D$999))) | P5: =SUM(B5:O5) | Q5: =SUMPRODUCT((Income!D$3:D$502="GBP")*(MONTH(Income!A$3:A$502)=3)*(YEAR(Income!A$3:A$502)=2026)*(Income!A$3:A$502<>"")*Income!C$3:C$502) | R5: =Q5-P5
A6: April 2026 | B6: =SUMPRODUCT((Expenses!C$3:C$999="Rent")*(Expenses!E$3:E$999="GBP")*(MONTH(Expenses!A$3:A$999)=4)*(YEAR(Expenses!A$3:A$999)=2026)*(Expenses!A$3:A$999<>"")*(IF(Expenses!G$3:G$999="Yes",Expenses!H$3:H$999,Expenses!D$3:D$999))) | C6: =SUMPRODUCT((Expenses!C$3:C$999="Transport")*(Expenses!E$3:E$999="GBP")*(MONTH(Expenses!A$3:A$999)=4)*(YEAR(Expenses!A$3:A$999)=2026)*(Expenses!A$3:A$999<>"")*(IF(Expenses!G$3:G$999="Yes",Expenses!H$3:H$999,Expenses!D$3:D$999))) | D6: =SUMPRODUCT((Expenses!C$3:C$999="Travel")*(Expenses!E$3:E$999="GBP")*(MONTH(Expenses!A$3:A$999)=4)*(YEAR(Expenses!A$3:A$999)=2026)*(Expenses!A$3:A$999<>"")*(IF(Expenses!G$3:G$999="Yes",Expenses!H$3:H$999,Expenses!D$3:D$999))) | E6: =SUMPRODUCT((Expenses!C$3:C$999="Shopping")*(Expenses!E$3:E$999="GBP")*(MONTH(Expenses!A$3:A$999)=4)*(YEAR(Expenses!A$3:A$999)=2026)*(Expenses!A$3:A$999<>"")*(IF(Expenses!G$3:G$999="Yes",Expenses!H$3:H$999,Expenses!D$3:D$999))) | F6: =SUMPRODUCT((Expenses!C$3:C$999="Electronics")*(Expenses!E$3:E$999="GBP")*(MONTH(Expenses!A$3:A$999)=4)*(YEAR(Expenses!A$3:A$999)=2026)*(Expenses!A$3:A$999<>"")*(IF(Expenses!G$3:G$999="Yes",Expenses!H$3:H$999,Expenses!D$3:D$999))) | G6: =SUMPRODUCT((Expenses!C$3:C$999="Subscriptions")*(Expenses!E$3:E$999="GBP")*(MONTH(Expenses!A$3:A$999)=4)*(YEAR(Expenses!A$3:A$999)=2026)*(Expenses!A$3:A$999<>"")*(IF(Expenses!G$3:G$999="Yes",Expenses!H$3:H$999,Expenses!D$3:D$999))) | H6: =SUMPRODUCT((Expenses!C$3:C$999="Bills")*(Expenses!E$3:E$999="GBP")*(MONTH(Expenses!A$3:A$999)=4)*(YEAR(Expenses!A$3:A$999)=2026)*(Expenses!A$3:A$999<>"")*(IF(Expenses!G$3:G$999="Yes",Expenses!H$3:H$999,Expenses!D$3:D$999))) | I6: =SUMPRODUCT((Expenses!C$3:C$999="Entertainment")*(Expenses!E$3:E$999="GBP")*(MONTH(Expenses!A$3:A$999)=4)*(YEAR(Expenses!A$3:A$999)=2026)*(Expenses!A$3:A$999<>"")*(IF(Expenses!G$3:G$999="Yes",Expenses!H$3:H$999,Expenses!D$3:D$999))) | J6: =SUMPRODUCT((Expenses!C$3:C$999="Food and Drinks")*(Expenses!E$3:E$999="GBP")*(MONTH(Expenses!A$3:A$999)=4)*(YEAR(Expenses!A$3:A$999)=2026)*(Expenses!A$3:A$999<>"")*(IF(Expenses!G$3:G$999="Yes",Expenses!H$3:H$999,Expenses!D$3:D$999))) | K6: =SUMPRODUCT((Expenses!C$3:C$999="Groceries")*(Expenses!E$3:E$999="GBP")*(MONTH(Expenses!A$3:A$999)=4)*(YEAR(Expenses!A$3:A$999)=2026)*(Expenses!A$3:A$999<>"")*(IF(Expenses!G$3:G$999="Yes",Expenses!H$3:H$999,Expenses!D$3:D$999))) | L6: =SUMPRODUCT((Expenses!C$3:C$999="Others")*(Expenses!E$3:E$999="GBP")*(MONTH(Expenses!A$3:A$999)=4)*(YEAR(Expenses!A$3:A$999)=2026)*(Expenses!A$3:A$999<>"")*(IF(Expenses!G$3:G$999="Yes",Expenses!H$3:H$999,Expenses!D$3:D$999))) | M6: =SUMPRODUCT((Expenses!C$3:C$999="Gifts")*(Expenses!E$3:E$999="GBP")*(MONTH(Expenses!A$3:A$999)=4)*(YEAR(Expenses!A$3:A$999)=2026)*(Expenses!A$3:A$999<>"")*(IF(Expenses!G$3:G$999="Yes",Expenses!H$3:H$999,Expenses!D$3:D$999))) | N6: =SUMPRODUCT((Expenses!C$3:C$999="Donations")*(Expenses!E$3:E$999="GBP")*(MONTH(Expenses!A$3:A$999)=4)*(YEAR(Expenses!A$3:A$999)=2026)*(Expenses!A$3:A$999<>"")*(IF(Expenses!G$3:G$999="Yes",Expenses!H$3:H$999,Expenses!D$3:D$999))) | O6: =SUMPRODUCT((Expenses!C$3:C$999="Investments")*(Expenses!E$3:E$999="GBP")*(MONTH(Expenses!A$3:A$999)=4)*(YEAR(Expenses!A$3:A$999)=2026)*(Expenses!A$3:A$999<>"")*(IF(Expenses!G$3:G$999="Yes",Expenses!H$3:H$999,Expenses!D$3:D$999))) | P6: =SUM(B6:O6) | Q6: =SUMPRODUCT((Income!D$3:D$502="GBP")*(MONTH(Income!A$3:A$502)=4)*(YEAR(Income!A$3:A$502)=2026)*(Income!A$3:A$502<>"")*Income!C$3:C$502) | R6: =Q6-P6
A7: May 2026 | B7: =SUMPRODUCT((Expenses!C$3:C$999="Rent")*(Expenses!E$3:E$999="GBP")*(MONTH(Expenses!A$3:A$999)=5)*(YEAR(Expenses!A$3:A$999)=2026)*(Expenses!A$3:A$999<>"")*(IF(Expenses!G$3:G$999="Yes",Expenses!H$3:H$999,Expenses!D$3:D$999))) | C7: =SUMPRODUCT((Expenses!C$3:C$999="Transport")*(Expenses!E$3:E$999="GBP")*(MONTH(Expenses!A$3:A$999)=5)*(YEAR(Expenses!A$3:A$999)=2026)*(Expenses!A$3:A$999<>"")*(IF(Expenses!G$3:G$999="Yes",Expenses!H$3:H$999,Expenses!D$3:D$999))) | D7: =SUMPRODUCT((Expenses!C$3:C$999="Travel")*(Expenses!E$3:E$999="GBP")*(MONTH(Expenses!A$3:A$999)=5)*(YEAR(Expenses!A$3:A$999)=2026)*(Expenses!A$3:A$999<>"")*(IF(Expenses!G$3:G$999="Yes",Expenses!H$3:H$999,Expenses!D$3:D$999))) | E7: =SUMPRODUCT((Expenses!C$3:C$999="Shopping")*(Expenses!E$3:E$999="GBP")*(MONTH(Expenses!A$3:A$999)=5)*(YEAR(Expenses!A$3:A$999)=2026)*(Expenses!A$3:A$999<>"")*(IF(Expenses!G$3:G$999="Yes",Expenses!H$3:H$999,Expenses!D$3:D$999))) | F7: =SUMPRODUCT((Expenses!C$3:C$999="Electronics")*(Expenses!E$3:E$999="GBP")*(MONTH(Expenses!A$3:A$999)=5)*(YEAR(Expenses!A$3:A$999)=2026)*(Expenses!A$3:A$999<>"")*(IF(Expenses!G$3:G$999="Yes",Expenses!H$3:H$999,Expenses!D$3:D$999))) | G7: =SUMPRODUCT((Expenses!C$3:C$999="Subscriptions")*(Expenses!E$3:E$999="GBP")*(MONTH(Expenses!A$3:A$999)=5)*(YEAR(Expenses!A$3:A$999)=2026)*(Expenses!A$3:A$999<>"")*(IF(Expenses!G$3:G$999="Yes",Expenses!H$3:H$999,Expenses!D$3:D$999))) | H7: =SUMPRODUCT((Expenses!C$3:C$999="Bills")*(Expenses!E$3:E$999="GBP")*(MONTH(Expenses!A$3:A$999)=5)*(YEAR(Expenses!A$3:A$999)=2026)*(Expenses!A$3:A$999<>"")*(IF(Expenses!G$3:G$999="Yes",Expenses!H$3:H$999,Expenses!D$3:D$999))) | I7: =SUMPRODUCT((Expenses!C$3:C$999="Entertainment")*(Expenses!E$3:E$999="GBP")*(MONTH(Expenses!A$3:A$999)=5)*(YEAR(Expenses!A$3:A$999)=2026)*(Expenses!A$3:A$999<>"")*(IF(Expenses!G$3:G$999="Yes",Expenses!H$3:H$999,Expenses!D$3:D$999))) | J7: =SUMPRODUCT((Expenses!C$3:C$999="Food and Drinks")*(Expenses!E$3:E$999="GBP")*(MONTH(Expenses!A$3:A$999)=5)*(YEAR(Expenses!A$3:A$999)=2026)*(Expenses!A$3:A$999<>"")*(IF(Expenses!G$3:G$999="Yes",Expenses!H$3:H$999,Expenses!D$3:D$999))) | K7: =SUMPRODUCT((Expenses!C$3:C$999="Groceries")*(Expenses!E$3:E$999="GBP")*(MONTH(Expenses!A$3:A$999)=5)*(YEAR(Expenses!A$3:A$999)=2026)*(Expenses!A$3:A$999<>"")*(IF(Expenses!G$3:G$999="Yes",Expenses!H$3:H$999,Expenses!D$3:D$999))) | L7: =SUMPRODUCT((Expenses!C$3:C$999="Others")*(Expenses!E$3:E$999="GBP")*(MONTH(Expenses!A$3:A$999)=5)*(YEAR(Expenses!A$3:A$999)=2026)*(Expenses!A$3:A$999<>"")*(IF(Expenses!G$3:G$999="Yes",Expenses!H$3:H$999,Expenses!D$3:D$999))) | M7: =SUMPRODUCT((Expenses!C$3:C$999="Gifts")*(Expenses!E$3:E$999="GBP")*(MONTH(Expenses!A$3:A$999)=5)*(YEAR(Expenses!A$3:A$999)=2026)*(Expenses!A$3:A$999<>"")*(IF(Expenses!G$3:G$999="Yes",Expenses!H$3:H$999,Expenses!D$3:D$999))) | N7: =SUMPRODUCT((Expenses!C$3:C$999="Donations")*(Expenses!E$3:E$999="GBP")*(MONTH(Expenses!A$3:A$999)=5)*(YEAR(Expenses!A$3:A$999)=2026)*(Expenses!A$3:A$999<>"")*(IF(Expenses!G$3:G$999="Yes",Expenses!H$3:H$999,Expenses!D$3:D$999))) | O7: =SUMPRODUCT((Expenses!C$3:C$999="Investments")*(Expenses!E$3:E$999="GBP")*(MONTH(Expenses!A$3:A$999)=5)*(YEAR(Expenses!A$3:A$999)=2026)*(Expenses!A$3:A$999<>"")*(IF(Expenses!G$3:G$999="Yes",Expenses!H$3:H$999,Expenses!D$3:D$999))) | P7: =SUM(B7:O7) | Q7: =SUMPRODUCT((Income!D$3:D$502="GBP")*(MONTH(Income!A$3:A$502)=5)*(YEAR(Income!A$3:A$502)=2026)*(Income!A$3:A$502<>"")*Income!C$3:C$502) | R7: =Q7-P7
A8: June 2026 | B8: =SUMPRODUCT((Expenses!C$3:C$999="Rent")*(Expenses!E$3:E$999="GBP")*(MONTH(Expenses!A$3:A$999)=6)*(YEAR(Expenses!A$3:A$999)=2026)*(Expenses!A$3:A$999<>"")*(IF(Expenses!G$3:G$999="Yes",Expenses!H$3:H$999,Expenses!D$3:D$999))) | C8: =SUMPRODUCT((Expenses!C$3:C$999="Transport")*(Expenses!E$3:E$999="GBP")*(MONTH(Expenses!A$3:A$999)=6)*(YEAR(Expenses!A$3:A$999)=2026)*(Expenses!A$3:A$999<>"")*(IF(Expenses!G$3:G$999="Yes",Expenses!H$3:H$999,Expenses!D$3:D$999))) | D8: =SUMPRODUCT((Expenses!C$3:C$999="Travel")*(Expenses!E$3:E$999="GBP")*(MONTH(Expenses!A$3:A$999)=6)*(YEAR(Expenses!A$3:A$999)=2026)*(Expenses!A$3:A$999<>"")*(IF(Expenses!G$3:G$999="Yes",Expenses!H$3:H$999,Expenses!D$3:D$999))) | E8: =SUMPRODUCT((Expenses!C$3:C$999="Shopping")*(Expenses!E$3:E$999="GBP")*(MONTH(Expenses!A$3:A$999)=6)*(YEAR(Expenses!A$3:A$999)=2026)*(Expenses!A$3:A$999<>"")*(IF(Expenses!G$3:G$999="Yes",Expenses!H$3:H$999,Expenses!D$3:D$999))) | F8: =SUMPRODUCT((Expenses!C$3:C$999="Electronics")*(Expenses!E$3:E$999="GBP")*(MONTH(Expenses!A$3:A$999)=6)*(YEAR(Expenses!A$3:A$999)=2026)*(Expenses!A$3:A$999<>"")*(IF(Expenses!G$3:G$999="Yes",Expenses!H$3:H$999,Expenses!D$3:D$999))) | G8: =SUMPRODUCT((Expenses!C$3:C$999="Subscriptions")*(Expenses!E$3:E$999="GBP")*(MONTH(Expenses!A$3:A$999)=6)*(YEAR(Expenses!A$3:A$999)=2026)*(Expenses!A$3:A$999<>"")*(IF(Expenses!G$3:G$999="Yes",Expenses!H$3:H$999,Expenses!D$3:D$999))) | H8: =SUMPRODUCT((Expenses!C$3:C$999="Bills")*(Expenses!E$3:E$999="GBP")*(MONTH(Expenses!A$3:A$999)=6)*(YEAR(Expenses!A$3:A$999)=2026)*(Expenses!A$3:A$999<>"")*(IF(Expenses!G$3:G$999="Yes",Expenses!H$3:H$999,Expenses!D$3:D$999))) | I8: =SUMPRODUCT((Expenses!C$3:C$999="Entertainment")*(Expenses!E$3:E$999="GBP")*(MONTH(Expenses!A$3:A$999)=6)*(YEAR(Expenses!A$3:A$999)=2026)*(Expenses!A$3:A$999<>"")*(IF(Expenses!G$3:G$999="Yes",Expenses!H$3:H$999,Expenses!D$3:D$999))) | J8: =SUMPRODUCT((Expenses!C$3:C$999="Food and Drinks")*(Expenses!E$3:E$999="GBP")*(MONTH(Expenses!A$3:A$999)=6)*(YEAR(Expenses!A$3:A$999)=2026)*(Expenses!A$3:A$999<>"")*(IF(Expenses!G$3:G$999="Yes",Expenses!H$3:H$999,Expenses!D$3:D$999))) | K8: =SUMPRODUCT((Expenses!C$3:C$999="Groceries")*(Expenses!E$3:E$999="GBP")*(MONTH(Expenses!A$3:A$999)=6)*(YEAR(Expenses!A$3:A$999)=2026)*(Expenses!A$3:A$999<>"")*(IF(Expenses!G$3:G$999="Yes",Expenses!H$3:H$999,Expenses!D$3:D$999))) | L8: =SUMPRODUCT((Expenses!C$3:C$999="Others")*(Expenses!E$3:E$999="GBP")*(MONTH(Expenses!A$3:A$999)=6)*(YEAR(Expenses!A$3:A$999)=2026)*(Expenses!A$3:A$999<>"")*(IF(Expenses!G$3:G$999="Yes",Expenses!H$3:H$999,Expenses!D$3:D$999))) | M8: =SUMPRODUCT((Expenses!C$3:C$999="Gifts")*(Expenses!E$3:E$999="GBP")*(MONTH(Expenses!A$3:A$999)=6)*(YEAR(Expenses!A$3:A$999)=2026)*(Expenses!A$3:A$999<>"")*(IF(Expenses!G$3:G$999="Yes",Expenses!H$3:H$999,Expenses!D$3:D$999))) | N8: =SUMPRODUCT((Expenses!C$3:C$999="Donations")*(Expenses!E$3:E$999="GBP")*(MONTH(Expenses!A$3:A$999)=6)*(YEAR(Expenses!A$3:A$999)=2026)*(Expenses!A$3:A$999<>"")*(IF(Expenses!G$3:G$999="Yes",Expenses!H$3:H$999,Expenses!D$3:D$999))) | O8: =SUMPRODUCT((Expenses!C$3:C$999="Investments")*(Expenses!E$3:E$999="GBP")*(MONTH(Expenses!A$3:A$999)=6)*(YEAR(Expenses!A$3:A$999)=2026)*(Expenses!A$3:A$999<>"")*(IF(Expenses!G$3:G$999="Yes",Expenses!H$3:H$999,Expenses!D$3:D$999))) | P8: =SUM(B8:O8) | Q8: =SUMPRODUCT((Income!D$3:D$502="GBP")*(MONTH(Income!A$3:A$502)=6)*(YEAR(Income!A$3:A$502)=2026)*(Income!A$3:A$502<>"")*Income!C$3:C$502) | R8: =Q8-P8
A9: July 2026 | B9: =SUMPRODUCT((Expenses!C$3:C$999="Rent")*(Expenses!E$3:E$999="GBP")*(MONTH(Expenses!A$3:A$999)=7)*(YEAR(Expenses!A$3:A$999)=2026)*(Expenses!A$3:A$999<>"")*(IF(Expenses!G$3:G$999="Yes",Expenses!H$3:H$999,Expenses!D$3:D$999))) | C9: =SUMPRODUCT((Expenses!C$3:C$999="Transport")*(Expenses!E$3:E$999="GBP")*(MONTH(Expenses!A$3:A$999)=7)*(YEAR(Expenses!A$3:A$999)=2026)*(Expenses!A$3:A$999<>"")*(IF(Expenses!G$3:G$999="Yes",Expenses!H$3:H$999,Expenses!D$3:D$999))) | D9: =SUMPRODUCT((Expenses!C$3:C$999="Travel")*(Expenses!E$3:E$999="GBP")*(MONTH(Expenses!A$3:A$999)=7)*(YEAR(Expenses!A$3:A$999)=2026)*(Expenses!A$3:A$999<>"")*(IF(Expenses!G$3:G$999="Yes",Expenses!H$3:H$999,Expenses!D$3:D$999))) | E9: =SUMPRODUCT((Expenses!C$3:C$999="Shopping")*(Expenses!E$3:E$999="GBP")*(MONTH(Expenses!A$3:A$999)=7)*(YEAR(Expenses!A$3:A$999)=2026)*(Expenses!A$3:A$999<>"")*(IF(Expenses!G$3:G$999="Yes",Expenses!H$3:H$999,Expenses!D$3:D$999))) | F9: =SUMPRODUCT((Expenses!C$3:C$999="Electronics")*(Expenses!E$3:E$999="GBP")*(MONTH(Expenses!A$3:A$999)=7)*(YEAR(Expenses!A$3:A$999)=2026)*(Expenses!A$3:A$999<>"")*(IF(Expenses!G$3:G$999="Yes",Expenses!H$3:H$999,Expenses!D$3:D$999))) | G9: =SUMPRODUCT((Expenses!C$3:C$999="Subscriptions")*(Expenses!E$3:E$999="GBP")*(MONTH(Expenses!A$3:A$999)=7)*(YEAR(Expenses!A$3:A$999)=2026)*(Expenses!A$3:A$999<>"")*(IF(Expenses!G$3:G$999="Yes",Expenses!H$3:H$999,Expenses!D$3:D$999))) | H9: =SUMPRODUCT((Expenses!C$3:C$999="Bills")*(Expenses!E$3:E$999="GBP")*(MONTH(Expenses!A$3:A$999)=7)*(YEAR(Expenses!A$3:A$999)=2026)*(Expenses!A$3:A$999<>"")*(IF(Expenses!G$3:G$999="Yes",Expenses!H$3:H$999,Expenses!D$3:D$999))) | I9: =SUMPRODUCT((Expenses!C$3:C$999="Entertainment")*(Expenses!E$3:E$999="GBP")*(MONTH(Expenses!A$3:A$999)=7)*(YEAR(Expenses!A$3:A$999)=2026)*(Expenses!A$3:A$999<>"")*(IF(Expenses!G$3:G$999="Yes",Expenses!H$3:H$999,Expenses!D$3:D$999))) | J9: =SUMPRODUCT((Expenses!C$3:C$999="Food and Drinks")*(Expenses!E$3:E$999="GBP")*(MONTH(Expenses!A$3:A$999)=7)*(YEAR(Expenses!A$3:A$999)=2026)*(Expenses!A$3:A$999<>"")*(IF(Expenses!G$3:G$999="Yes",Expenses!H$3:H$999,Expenses!D$3:D$999))) | K9: =SUMPRODUCT((Expenses!C$3:C$999="Groceries")*(Expenses!E$3:E$999="GBP")*(MONTH(Expenses!A$3:A$999)=7)*(YEAR(Expenses!A$3:A$999)=2026)*(Expenses!A$3:A$999<>"")*(IF(Expenses!G$3:G$999="Yes",Expenses!H$3:H$999,Expenses!D$3:D$999))) | L9: =SUMPRODUCT((Expenses!C$3:C$999="Others")*(Expenses!E$3:E$999="GBP")*(MONTH(Expenses!A$3:A$999)=7)*(YEAR(Expenses!A$3:A$999)=2026)*(Expenses!A$3:A$999<>"")*(IF(Expenses!G$3:G$999="Yes",Expenses!H$3:H$999,Expenses!D$3:D$999))) | M9: =SUMPRODUCT((Expenses!C$3:C$999="Gifts")*(Expenses!E$3:E$999="GBP")*(MONTH(Expenses!A$3:A$999)=7)*(YEAR(Expenses!A$3:A$999)=2026)*(Expenses!A$3:A$999<>"")*(IF(Expenses!G$3:G$999="Yes",Expenses!H$3:H$999,Expenses!D$3:D$999))) | N9: =SUMPRODUCT((Expenses!C$3:C$999="Donations")*(Expenses!E$3:E$999="GBP")*(MONTH(Expenses!A$3:A$999)=7)*(YEAR(Expenses!A$3:A$999)=2026)*(Expenses!A$3:A$999<>"")*(IF(Expenses!G$3:G$999="Yes",Expenses!H$3:H$999,Expenses!D$3:D$999))) | O9: =SUMPRODUCT((Expenses!C$3:C$999="Investments")*(Expenses!E$3:E$999="GBP")*(MONTH(Expenses!A$3:A$999)=7)*(YEAR(Expenses!A$3:A$999)=2026)*(Expenses!A$3:A$999<>"")*(IF(Expenses!G$3:G$999="Yes",Expenses!H$3:H$999,Expenses!D$3:D$999))) | P9: =SUM(B9:O9) | Q9: =SUMPRODUCT((Income!D$3:D$502="GBP")*(MONTH(Income!A$3:A$502)=7)*(YEAR(Income!A$3:A$502)=2026)*(Income!A$3:A$502<>"")*Income!C$3:C$502) | R9: =Q9-P9
A10: August 2026 | B10: =SUMPRODUCT((Expenses!C$3:C$999="Rent")*(Expenses!E$3:E$999="GBP")*(MONTH(Expenses!A$3:A$999)=8)*(YEAR(Expenses!A$3:A$999)=2026)*(Expenses!A$3:A$999<>"")*(IF(Expenses!G$3:G$999="Yes",Expenses!H$3:H$999,Expenses!D$3:D$999))) | C10: =SUMPRODUCT((Expenses!C$3:C$999="Transport")*(Expenses!E$3:E$999="GBP")*(MONTH(Expenses!A$3:A$999)=8)*(YEAR(Expenses!A$3:A$999)=2026)*(Expenses!A$3:A$999<>"")*(IF(Expenses!G$3:G$999="Yes",Expenses!H$3:H$999,Expenses!D$3:D$999))) | D10: =SUMPRODUCT((Expenses!C$3:C$999="Travel")*(Expenses!E$3:E$999="GBP")*(MONTH(Expenses!A$3:A$999)=8)*(YEAR(Expenses!A$3:A$999)=2026)*(Expenses!A$3:A$999<>"")*(IF(Expenses!G$3:G$999="Yes",Expenses!H$3:H$999,Expenses!D$3:D$999))) | E10: =SUMPRODUCT((Expenses!C$3:C$999="Shopping")*(Expenses!E$3:E$999="GBP")*(MONTH(Expenses!A$3:A$999)=8)*(YEAR(Expenses!A$3:A$999)=2026)*(Expenses!A$3:A$999<>"")*(IF(Expenses!G$3:G$999="Yes",Expenses!H$3:H$999,Expenses!D$3:D$999))) | F10: =SUMPRODUCT((Expenses!C$3:C$999="Electronics")*(Expenses!E$3:E$999="GBP")*(MONTH(Expenses!A$3:A$999)=8)*(YEAR(Expenses!A$3:A$999)=2026)*(Expenses!A$3:A$999<>"")*(IF(Expenses!G$3:G$999="Yes",Expenses!H$3:H$999,Expenses!D$3:D$999))) | G10: =SUMPRODUCT((Expenses!C$3:C$999="Subscriptions")*(Expenses!E$3:E$999="GBP")*(MONTH(Expenses!A$3:A$999)=8)*(YEAR(Expenses!A$3:A$999)=2026)*(Expenses!A$3:A$999<>"")*(IF(Expenses!G$3:G$999="Yes",Expenses!H$3:H$999,Expenses!D$3:D$999))) | H10: =SUMPRODUCT((Expenses!C$3:C$999="Bills")*(Expenses!E$3:E$999="GBP")*(MONTH(Expenses!A$3:A$999)=8)*(YEAR(Expenses!A$3:A$999)=2026)*(Expenses!A$3:A$999<>"")*(IF(Expenses!G$3:G$999="Yes",Expenses!H$3:H$999,Expenses!D$3:D$999))) | I10: =SUMPRODUCT((Expenses!C$3:C$999="Entertainment")*(Expenses!E$3:E$999="GBP")*(MONTH(Expenses!A$3:A$999)=8)*(YEAR(Expenses!A$3:A$999)=2026)*(Expenses!A$3:A$999<>"")*(IF(Expenses!G$3:G$999="Yes",Expenses!H$3:H$999,Expenses!D$3:D$999))) | J10: =SUMPRODUCT((Expenses!C$3:C$999="Food and Drinks")*(Expenses!E$3:E$999="GBP")*(MONTH(Expenses!A$3:A$999)=8)*(YEAR(Expenses!A$3:A$999)=2026)*(Expenses!A$3:A$999<>"")*(IF(Expenses!G$3:G$999="Yes",Expenses!H$3:H$999,Expenses!D$3:D$999))) | K10: =SUMPRODUCT((Expenses!C$3:C$999="Groceries")*(Expenses!E$3:E$999="GBP")*(MONTH(Expenses!A$3:A$999)=8)*(YEAR(Expenses!A$3:A$999)=2026)*(Expenses!A$3:A$999<>"")*(IF(Expenses!G$3:G$999="Yes",Expenses!H$3:H$999,Expenses!D$3:D$999))) | L10: =SUMPRODUCT((Expenses!C$3:C$999="Others")*(Expenses!E$3:E$999="GBP")*(MONTH(Expenses!A$3:A$999)=8)*(YEAR(Expenses!A$3:A$999)=2026)*(Expenses!A$3:A$999<>"")*(IF(Expenses!G$3:G$999="Yes",Expenses!H$3:H$999,Expenses!D$3:D$999))) | M10: =SUMPRODUCT((Expenses!C$3:C$999="Gifts")*(Expenses!E$3:E$999="GBP")*(MONTH(Expenses!A$3:A$999)=8)*(YEAR(Expenses!A$3:A$999)=2026)*(Expenses!A$3:A$999<>"")*(IF(Expenses!G$3:G$999="Yes",Expenses!H$3:H$999,Expenses!D$3:D$999))) | N10: =SUMPRODUCT((Expenses!C$3:C$999="Donations")*(Expenses!E$3:E$999="GBP")*(MONTH(Expenses!A$3:A$999)=8)*(YEAR(Expenses!A$3:A$999)=2026)*(Expenses!A$3:A$999<>"")*(IF(Expenses!G$3:G$999="Yes",Expenses!H$3:H$999,Expenses!D$3:D$999))) | O10: =SUMPRODUCT((Expenses!C$3:C$999="Investments")*(Expenses!E$3:E$999="GBP")*(MONTH(Expenses!A$3:A$999)=8)*(YEAR(Expenses!A$3:A$999)=2026)*(Expenses!A$3:A$999<>"")*(IF(Expenses!G$3:G$999="Yes",Expenses!H$3:H$999,Expenses!D$3:D$999))) | P10: =SUM(B10:O10) | Q10: =SUMPRODUCT((Income!D$3:D$502="GBP")*(MONTH(Income!A$3:A$502)=8)*(YEAR(Income!A$3:A$502)=2026)*(Income!A$3:A$502<>"")*Income!C$3:C$502) | R10: =Q10-P10
A11: September 2026 | B11: =SUMPRODUCT((Expenses!C$3:C$999="Rent")*(Expenses!E$3:E$999="GBP")*(MONTH(Expenses!A$3:A$999)=9)*(YEAR(Expenses!A$3:A$999)=2026)*(Expenses!A$3:A$999<>"")*(IF(Expenses!G$3:G$999="Yes",Expenses!H$3:H$999,Expenses!D$3:D$999))) | C11: =SUMPRODUCT((Expenses!C$3:C$999="Transport")*(Expenses!E$3:E$999="GBP")*(MONTH(Expenses!A$3:A$999)=9)*(YEAR(Expenses!A$3:A$999)=2026)*(Expenses!A$3:A$999<>"")*(IF(Expenses!G$3:G$999="Yes",Expenses!H$3:H$999,Expenses!D$3:D$999))) | D11: =SUMPRODUCT((Expenses!C$3:C$999="Travel")*(Expenses!E$3:E$999="GBP")*(MONTH(Expenses!A$3:A$999)=9)*(YEAR(Expenses!A$3:A$999)=2026)*(Expenses!A$3:A$999<>"")*(IF(Expenses!G$3:G$999="Yes",Expenses!H$3:H$999,Expenses!D$3:D$999))) | E11: =SUMPRODUCT((Expenses!C$3:C$999="Shopping")*(Expenses!E$3:E$999="GBP")*(MONTH(Expenses!A$3:A$999)=9)*(YEAR(Expenses!A$3:A$999)=2026)*(Expenses!A$3:A$999<>"")*(IF(Expenses!G$3:G$999="Yes",Expenses!H$3:H$999,Expenses!D$3:D$999))) | F11: =SUMPRODUCT((Expenses!C$3:C$999="Electronics")*(Expenses!E$3:E$999="GBP")*(MONTH(Expenses!A$3:A$999)=9)*(YEAR(Expenses!A$3:A$999)=2026)*(Expenses!A$3:A$999<>"")*(IF(Expenses!G$3:G$999="Yes",Expenses!H$3:H$999,Expenses!D$3:D$999))) | G11: =SUMPRODUCT((Expenses!C$3:C$999="Subscriptions")*(Expenses!E$3:E$999="GBP")*(MONTH(Expenses!A$3:A$999)=9)*(YEAR(Expenses!A$3:A$999)=2026)*(Expenses!A$3:A$999<>"")*(IF(Expenses!G$3:G$999="Yes",Expenses!H$3:H$999,Expenses!D$3:D$999))) | H11: =SUMPRODUCT((Expenses!C$3:C$999="Bills")*(Expenses!E$3:E$999="GBP")*(MONTH(Expenses!A$3:A$999)=9)*(YEAR(Expenses!A$3:A$999)=2026)*(Expenses!A$3:A$999<>"")*(IF(Expenses!G$3:G$999="Yes",Expenses!H$3:H$999,Expenses!D$3:D$999))) | I11: =SUMPRODUCT((Expenses!C$3:C$999="Entertainment")*(Expenses!E$3:E$999="GBP")*(MONTH(Expenses!A$3:A$999)=9)*(YEAR(Expenses!A$3:A$999)=2026)*(Expenses!A$3:A$999<>"")*(IF(Expenses!G$3:G$999="Yes",Expenses!H$3:H$999,Expenses!D$3:D$999))) | J11: =SUMPRODUCT((Expenses!C$3:C$999="Food and Drinks")*(Expenses!E$3:E$999="GBP")*(MONTH(Expenses!A$3:A$999)=9)*(YEAR(Expenses!A$3:A$999)=2026)*(Expenses!A$3:A$999<>"")*(IF(Expenses!G$3:G$999="Yes",Expenses!H$3:H$999,Expenses!D$3:D$999))) | K11: =SUMPRODUCT((Expenses!C$3:C$999="Groceries")*(Expenses!E$3:E$999="GBP")*(MONTH(Expenses!A$3:A$999)=9)*(YEAR(Expenses!A$3:A$999)=2026)*(Expenses!A$3:A$999<>"")*(IF(Expenses!G$3:G$999="Yes",Expenses!H$3:H$999,Expenses!D$3:D$999))) | L11: =SUMPRODUCT((Expenses!C$3:C$999="Others")*(Expenses!E$3:E$999="GBP")*(MONTH(Expenses!A$3:A$999)=9)*(YEAR(Expenses!A$3:A$999)=2026)*(Expenses!A$3:A$999<>"")*(IF(Expenses!G$3:G$999="Yes",Expenses!H$3:H$999,Expenses!D$3:D$999))) | M11: =SUMPRODUCT((Expenses!C$3:C$999="Gifts")*(Expenses!E$3:E$999="GBP")*(MONTH(Expenses!A$3:A$999)=9)*(YEAR(Expenses!A$3:A$999)=2026)*(Expenses!A$3:A$999<>"")*(IF(Expenses!G$3:G$999="Yes",Expenses!H$3:H$999,Expenses!D$3:D$999))) | N11: =SUMPRODUCT((Expenses!C$3:C$999="Donations")*(Expenses!E$3:E$999="GBP")*(MONTH(Expenses!A$3:A$999)=9)*(YEAR(Expenses!A$3:A$999)=2026)*(Expenses!A$3:A$999<>"")*(IF(Expenses!G$3:G$999="Yes",Expenses!H$3:H$999,Expenses!D$3:D$999))) | O11: =SUMPRODUCT((Expenses!C$3:C$999="Investments")*(Expenses!E$3:E$999="GBP")*(MONTH(Expenses!A$3:A$999)=9)*(YEAR(Expenses!A$3:A$999)=2026)*(Expenses!A$3:A$999<>"")*(IF(Expenses!G$3:G$999="Yes",Expenses!H$3:H$999,Expenses!D$3:D$999))) | P11: =SUM(B11:O11) | Q11: =SUMPRODUCT((Income!D$3:D$502="GBP")*(MONTH(Income!A$3:A$502)=9)*(YEAR(Income!A$3:A$502)=2026)*(Income!A$3:A$502<>"")*Income!C$3:C$502) | R11: =Q11-P11
A12: October 2026 | B12: =SUMPRODUCT((Expenses!C$3:C$999="Rent")*(Expenses!E$3:E$999="GBP")*(MONTH(Expenses!A$3:A$999)=10)*(YEAR(Expenses!A$3:A$999)=2026)*(Expenses!A$3:A$999<>"")*(IF(Expenses!G$3:G$999="Yes",Expenses!H$3:H$999,Expenses!D$3:D$999))) | C12: =SUMPRODUCT((Expenses!C$3:C$999="Transport")*(Expenses!E$3:E$999="GBP")*(MONTH(Expenses!A$3:A$999)=10)*(YEAR(Expenses!A$3:A$999)=2026)*(Expenses!A$3:A$999<>"")*(IF(Expenses!G$3:G$999="Yes",Expenses!H$3:H$999,Expenses!D$3:D$999))) | D12: =SUMPRODUCT((Expenses!C$3:C$999="Travel")*(Expenses!E$3:E$999="GBP")*(MONTH(Expenses!A$3:A$999)=10)*(YEAR(Expenses!A$3:A$999)=2026)*(Expenses!A$3:A$999<>"")*(IF(Expenses!G$3:G$999="Yes",Expenses!H$3:H$999,Expenses!D$3:D$999))) | E12: =SUMPRODUCT((Expenses!C$3:C$999="Shopping")*(Expenses!E$3:E$999="GBP")*(MONTH(Expenses!A$3:A$999)=10)*(YEAR(Expenses!A$3:A$999)=2026)*(Expenses!A$3:A$999<>"")*(IF(Expenses!G$3:G$999="Yes",Expenses!H$3:H$999,Expenses!D$3:D$999))) | F12: =SUMPRODUCT((Expenses!C$3:C$999="Electronics")*(Expenses!E$3:E$999="GBP")*(MONTH(Expenses!A$3:A$999)=10)*(YEAR(Expenses!A$3:A$999)=2026)*(Expenses!A$3:A$999<>"")*(IF(Expenses!G$3:G$999="Yes",Expenses!H$3:H$999,Expenses!D$3:D$999))) | G12: =SUMPRODUCT((Expenses!C$3:C$999="Subscriptions")*(Expenses!E$3:E$999="GBP")*(MONTH(Expenses!A$3:A$999)=10)*(YEAR(Expenses!A$3:A$999)=2026)*(Expenses!A$3:A$999<>"")*(IF(Expenses!G$3:G$999="Yes",Expenses!H$3:H$999,Expenses!D$3:D$999))) | H12: =SUMPRODUCT((Expenses!C$3:C$999="Bills")*(Expenses!E$3:E$999="GBP")*(MONTH(Expenses!A$3:A$999)=10)*(YEAR(Expenses!A$3:A$999)=2026)*(Expenses!A$3:A$999<>"")*(IF(Expenses!G$3:G$999="Yes",Expenses!H$3:H$999,Expenses!D$3:D$999))) | I12: =SUMPRODUCT((Expenses!C$3:C$999="Entertainment")*(Expenses!E$3:E$999="GBP")*(MONTH(Expenses!A$3:A$999)=10)*(YEAR(Expenses!A$3:A$999)=2026)*(Expenses!A$3:A$999<>"")*(IF(Expenses!G$3:G$999="Yes",Expenses!H$3:H$999,Expenses!D$3:D$999))) | J12: =SUMPRODUCT((Expenses!C$3:C$999="Food and Drinks")*(Expenses!E$3:E$999="GBP")*(MONTH(Expenses!A$3:A$999)=10)*(YEAR(Expenses!A$3:A$999)=2026)*(Expenses!A$3:A$999<>"")*(IF(Expenses!G$3:G$999="Yes",Expenses!H$3:H$999,Expenses!D$3:D$999))) | K12: =SUMPRODUCT((Expenses!C$3:C$999="Groceries")*(Expenses!E$3:E$999="GBP")*(MONTH(Expenses!A$3:A$999)=10)*(YEAR(Expenses!A$3:A$999)=2026)*(Expenses!A$3:A$999<>"")*(IF(Expenses!G$3:G$999="Yes",Expenses!H$3:H$999,Expenses!D$3:D$999))) | L12: =SUMPRODUCT((Expenses!C$3:C$999="Others")*(Expenses!E$3:E$999="GBP")*(MONTH(Expenses!A$3:A$999)=10)*(YEAR(Expenses!A$3:A$999)=2026)*(Expenses!A$3:A$999<>"")*(IF(Expenses!G$3:G$999="Yes",Expenses!H$3:H$999,Expenses!D$3:D$999))) | M12: =SUMPRODUCT((Expenses!C$3:C$999="Gifts")*(Expenses!E$3:E$999="GBP")*(MONTH(Expenses!A$3:A$999)=10)*(YEAR(Expenses!A$3:A$999)=2026)*(Expenses!A$3:A$999<>"")*(IF(Expenses!G$3:G$999="Yes",Expenses!H$3:H$999,Expenses!D$3:D$999))) | N12: =SUMPRODUCT((Expenses!C$3:C$999="Donations")*(Expenses!E$3:E$999="GBP")*(MONTH(Expenses!A$3:A$999)=10)*(YEAR(Expenses!A$3:A$999)=2026)*(Expenses!A$3:A$999<>"")*(IF(Expenses!G$3:G$999="Yes",Expenses!H$3:H$999,Expenses!D$3:D$999))) | O12: =SUMPRODUCT((Expenses!C$3:C$999="Investments")*(Expenses!E$3:E$999="GBP")*(MONTH(Expenses!A$3:A$999)=10)*(YEAR(Expenses!A$3:A$999)=2026)*(Expenses!A$3:A$999<>"")*(IF(Expenses!G$3:G$999="Yes",Expenses!H$3:H$999,Expenses!D$3:D$999))) | P12: =SUM(B12:O12) | Q12: =SUMPRODUCT((Income!D$3:D$502="GBP")*(MONTH(Income!A$3:A$502)=10)*(YEAR(Income!A$3:A$502)=2026)*(Income!A$3:A$502<>"")*Income!C$3:C$502) | R12: =Q12-P12
A13: November 2026 | B13: =SUMPRODUCT((Expenses!C$3:C$999="Rent")*(Expenses!E$3:E$999="GBP")*(MONTH(Expenses!A$3:A$999)=11)*(YEAR(Expenses!A$3:A$999)=2026)*(Expenses!A$3:A$999<>"")*(IF(Expenses!G$3:G$999="Yes",Expenses!H$3:H$999,Expenses!D$3:D$999))) | C13: =SUMPRODUCT((Expenses!C$3:C$999="Transport")*(Expenses!E$3:E$999="GBP")*(MONTH(Expenses!A$3:A$999)=11)*(YEAR(Expenses!A$3:A$999)=2026)*(Expenses!A$3:A$999<>"")*(IF(Expenses!G$3:G$999="Yes",Expenses!H$3:H$999,Expenses!D$3:D$999))) | D13: =SUMPRODUCT((Expenses!C$3:C$999="Travel")*(Expenses!E$3:E$999="GBP")*(MONTH(Expenses!A$3:A$999)=11)*(YEAR(Expenses!A$3:A$999)=2026)*(Expenses!A$3:A$999<>"")*(IF(Expenses!G$3:G$999="Yes",Expenses!H$3:H$999,Expenses!D$3:D$999))) | E13: =SUMPRODUCT((Expenses!C$3:C$999="Shopping")*(Expenses!E$3:E$999="GBP")*(MONTH(Expenses!A$3:A$999)=11)*(YEAR(Expenses!A$3:A$999)=2026)*(Expenses!A$3:A$999<>"")*(IF(Expenses!G$3:G$999="Yes",Expenses!H$3:H$999,Expenses!D$3:D$999))) | F13: =SUMPRODUCT((Expenses!C$3:C$999="Electronics")*(Expenses!E$3:E$999="GBP")*(MONTH(Expenses!A$3:A$999)=11)*(YEAR(Expenses!A$3:A$999)=2026)*(Expenses!A$3:A$999<>"")*(IF(Expenses!G$3:G$999="Yes",Expenses!H$3:H$999,Expenses!D$3:D$999))) | G13: =SUMPRODUCT((Expenses!C$3:C$999="Subscriptions")*(Expenses!E$3:E$999="GBP")*(MONTH(Expenses!A$3:A$999)=11)*(YEAR(Expenses!A$3:A$999)=2026)*(Expenses!A$3:A$999<>"")*(IF(Expenses!G$3:G$999="Yes",Expenses!H$3:H$999,Expenses!D$3:D$999))) | H13: =SUMPRODUCT((Expenses!C$3:C$999="Bills")*(Expenses!E$3:E$999="GBP")*(MONTH(Expenses!A$3:A$999)=11)*(YEAR(Expenses!A$3:A$999)=2026)*(Expenses!A$3:A$999<>"")*(IF(Expenses!G$3:G$999="Yes",Expenses!H$3:H$999,Expenses!D$3:D$999))) | I13: =SUMPRODUCT((Expenses!C$3:C$999="Entertainment")*(Expenses!E$3:E$999="GBP")*(MONTH(Expenses!A$3:A$999)=11)*(YEAR(Expenses!A$3:A$999)=2026)*(Expenses!A$3:A$999<>"")*(IF(Expenses!G$3:G$999="Yes",Expenses!H$3:H$999,Expenses!D$3:D$999))) | J13: =SUMPRODUCT((Expenses!C$3:C$999="Food and Drinks")*(Expenses!E$3:E$999="GBP")*(MONTH(Expenses!A$3:A$999)=11)*(YEAR(Expenses!A$3:A$999)=2026)*(Expenses!A$3:A$999<>"")*(IF(Expenses!G$3:G$999="Yes",Expenses!H$3:H$999,Expenses!D$3:D$999))) | K13: =SUMPRODUCT((Expenses!C$3:C$999="Groceries")*(Expenses!E$3:E$999="GBP")*(MONTH(Expenses!A$3:A$999)=11)*(YEAR(Expenses!A$3:A$999)=2026)*(Expenses!A$3:A$999<>"")*(IF(Expenses!G$3:G$999="Yes",Expenses!H$3:H$999,Expenses!D$3:D$999))) | L13: =SUMPRODUCT((Expenses!C$3:C$999="Others")*(Expenses!E$3:E$999="GBP")*(MONTH(Expenses!A$3:A$999)=11)*(YEAR(Expenses!A$3:A$999)=2026)*(Expenses!A$3:A$999<>"")*(IF(Expenses!G$3:G$999="Yes",Expenses!H$3:H$999,Expenses!D$3:D$999))) | M13: =SUMPRODUCT((Expenses!C$3:C$999="Gifts")*(Expenses!E$3:E$999="GBP")*(MONTH(Expenses!A$3:A$999)=11)*(YEAR(Expenses!A$3:A$999)=2026)*(Expenses!A$3:A$999<>"")*(IF(Expenses!G$3:G$999="Yes",Expenses!H$3:H$999,Expenses!D$3:D$999))) | N13: =SUMPRODUCT((Expenses!C$3:C$999="Donations")*(Expenses!E$3:E$999="GBP")*(MONTH(Expenses!A$3:A$999)=11)*(YEAR(Expenses!A$3:A$999)=2026)*(Expenses!A$3:A$999<>"")*(IF(Expenses!G$3:G$999="Yes",Expenses!H$3:H$999,Expenses!D$3:D$999))) | O13: =SUMPRODUCT((Expenses!C$3:C$999="Investments")*(Expenses!E$3:E$999="GBP")*(MONTH(Expenses!A$3:A$999)=11)*(YEAR(Expenses!A$3:A$999)=2026)*(Expenses!A$3:A$999<>"")*(IF(Expenses!G$3:G$999="Yes",Expenses!H$3:H$999,Expenses!D$3:D$999))) | P13: =SUM(B13:O13) | Q13: =SUMPRODUCT((Income!D$3:D$502="GBP")*(MONTH(Income!A$3:A$502)=11)*(YEAR(Income!A$3:A$502)=2026)*(Income!A$3:A$502<>"")*Income!C$3:C$502) | R13: =Q13-P13
A14: December 2026 | B14: =SUMPRODUCT((Expenses!C$3:C$999="Rent")*(Expenses!E$3:E$999="GBP")*(MONTH(Expenses!A$3:A$999)=12)*(YEAR(Expenses!A$3:A$999)=2026)*(Expenses!A$3:A$999<>"")*(IF(Expenses!G$3:G$999="Yes",Expenses!H$3:H$999,Expenses!D$3:D$999))) | C14: =SUMPRODUCT((Expenses!C$3:C$999="Transport")*(Expenses!E$3:E$999="GBP")*(MONTH(Expenses!A$3:A$999)=12)*(YEAR(Expenses!A$3:A$999)=2026)*(Expenses!A$3:A$999<>"")*(IF(Expenses!G$3:G$999="Yes",Expenses!H$3:H$999,Expenses!D$3:D$999))) | D14: =SUMPRODUCT((Expenses!C$3:C$999="Travel")*(Expenses!E$3:E$999="GBP")*(MONTH(Expenses!A$3:A$999)=12)*(YEAR(Expenses!A$3:A$999)=2026)*(Expenses!A$3:A$999<>"")*(IF(Expenses!G$3:G$999="Yes",Expenses!H$3:H$999,Expenses!D$3:D$999))) | E14: =SUMPRODUCT((Expenses!C$3:C$999="Shopping")*(Expenses!E$3:E$999="GBP")*(MONTH(Expenses!A$3:A$999)=12)*(YEAR(Expenses!A$3:A$999)=2026)*(Expenses!A$3:A$999<>"")*(IF(Expenses!G$3:G$999="Yes",Expenses!H$3:H$999,Expenses!D$3:D$999))) | F14: =SUMPRODUCT((Expenses!C$3:C$999="Electronics")*(Expenses!E$3:E$999="GBP")*(MONTH(Expenses!A$3:A$999)=12)*(YEAR(Expenses!A$3:A$999)=2026)*(Expenses!A$3:A$999<>"")*(IF(Expenses!G$3:G$999="Yes",Expenses!H$3:H$999,Expenses!D$3:D$999))) | G14: =SUMPRODUCT((Expenses!C$3:C$999="Subscriptions")*(Expenses!E$3:E$999="GBP")*(MONTH(Expenses!A$3:A$999)=12)*(YEAR(Expenses!A$3:A$999)=2026)*(Expenses!A$3:A$999<>"")*(IF(Expenses!G$3:G$999="Yes",Expenses!H$3:H$999,Expenses!D$3:D$999))) | H14: =SUMPRODUCT((Expenses!C$3:C$999="Bills")*(Expenses!E$3:E$999="GBP")*(MONTH(Expenses!A$3:A$999)=12)*(YEAR(Expenses!A$3:A$999)=2026)*(Expenses!A$3:A$999<>"")*(IF(Expenses!G$3:G$999="Yes",Expenses!H$3:H$999,Expenses!D$3:D$999))) | I14: =SUMPRODUCT((Expenses!C$3:C$999="Entertainment")*(Expenses!E$3:E$999="GBP")*(MONTH(Expenses!A$3:A$999)=12)*(YEAR(Expenses!A$3:A$999)=2026)*(Expenses!A$3:A$999<>"")*(IF(Expenses!G$3:G$999="Yes",Expenses!H$3:H$999,Expenses!D$3:D$999))) | J14: =SUMPRODUCT((Expenses!C$3:C$999="Food and Drinks")*(Expenses!E$3:E$999="GBP")*(MONTH(Expenses!A$3:A$999)=12)*(YEAR(Expenses!A$3:A$999)=2026)*(Expenses!A$3:A$999<>"")*(IF(Expenses!G$3:G$999="Yes",Expenses!H$3:H$999,Expenses!D$3:D$999))) | K14: =SUMPRODUCT((Expenses!C$3:C$999="Groceries")*(Expenses!E$3:E$999="GBP")*(MONTH(Expenses!A$3:A$999)=12)*(YEAR(Expenses!A$3:A$999)=2026)*(Expenses!A$3:A$999<>"")*(IF(Expenses!G$3:G$999="Yes",Expenses!H$3:H$999,Expenses!D$3:D$999))) | L14: =SUMPRODUCT((Expenses!C$3:C$999="Others")*(Expenses!E$3:E$999="GBP")*(MONTH(Expenses!A$3:A$999)=12)*(YEAR(Expenses!A$3:A$999)=2026)*(Expenses!A$3:A$999<>"")*(IF(Expenses!G$3:G$999="Yes",Expenses!H$3:H$999,Expenses!D$3:D$999))) | M14: =SUMPRODUCT((Expenses!C$3:C$999="Gifts")*(Expenses!E$3:E$999="GBP")*(MONTH(Expenses!A$3:A$999)=12)*(YEAR(Expenses!A$3:A$999)=2026)*(Expenses!A$3:A$999<>"")*(IF(Expenses!G$3:G$999="Yes",Expenses!H$3:H$999,Expenses!D$3:D$999))) | N14: =SUMPRODUCT((Expenses!C$3:C$999="Donations")*(Expenses!E$3:E$999="GBP")*(MONTH(Expenses!A$3:A$999)=12)*(YEAR(Expenses!A$3:A$999)=2026)*(Expenses!A$3:A$999<>"")*(IF(Expenses!G$3:G$999="Yes",Expenses!H$3:H$999,Expenses!D$3:D$999))) | O14: =SUMPRODUCT((Expenses!C$3:C$999="Investments")*(Expenses!E$3:E$999="GBP")*(MONTH(Expenses!A$3:A$999)=12)*(YEAR(Expenses!A$3:A$999)=2026)*(Expenses!A$3:A$999<>"")*(IF(Expenses!G$3:G$999="Yes",Expenses!H$3:H$999,Expenses!D$3:D$999))) | P14: =SUM(B14:O14) | Q14: =SUMPRODUCT((Income!D$3:D$502="GBP")*(MONTH(Income!A$3:A$502)=12)*(YEAR(Income!A$3:A$502)=2026)*(Income!A$3:A$502<>"")*Income!C$3:C$502) | R14: =Q14-P14
A16: Total | B16: =SUM(B3:B14) | C16: =SUM(C3:C14) | D16: =SUM(D3:D14) | E16: =SUM(E3:E14) | F16: =SUM(F3:F14) | G16: =SUM(G3:G14) | H16: =SUM(H3:H14) | I16: =SUM(I3:I14) | ... R16: =SUM(R3:R14)
A18: Monthly Budget | B18: 385 | C18: 125 | D18: 100 | E18: 200 | F18: 100 | G18: 100 | H18: 100 | I18: 100 | J18: 150 | K18: 100 | M18: 10 | N18: 10 | O18: 5 | P18: =SUM(B18:O18)
A21: Yearly Breakdown

Sheet Monthly Overview INR
A1: MONTHLY OVERVIEW (INR)
A2: Month | B2: Rent | C2: Transport | D2: Travel | E2: Shopping | F2: Electronics | G2: Subscriptions | H2: Bills | I2: Entertainment | J2: Food and Drinks | K2: Groceries | L2: Others | M2: Gifts | N2: Donations | O2: Investments | P2: Total Expenditure | Q2: Income | R2: Gross Savings
A3: January 2026 | B3: =SUMPRODUCT((Expenses!C$3:C$999="Rent")*(Expenses!E$3:E$999="INR")*(MONTH(Expenses!A$3:A$999)=1)*(YEAR(Expenses!A$3:A$999)=2026)*(Expenses!A$3:A$999<>"")*(IF(Expenses!G$3:G$999="Yes",Expenses!H$3:H$999,Expenses!D$3:D$999))) | C3: =SUMPRODUCT((Expenses!C$3:C$999="Transport")*(Expenses!E$3:E$999="INR")*(MONTH(Expenses!A$3:A$999)=1)*(YEAR(Expenses!A$3:A$999)=2026)*(Expenses!A$3:A$999<>"")*(IF(Expenses!G$3:G$999="Yes",Expenses!H$3:H$999,Expenses!D$3:D$999))) | D3: =SUMPRODUCT((Expenses!C$3:C$999="Travel")*(Expenses!E$3:E$999="INR")*(MONTH(Expenses!A$3:A$999)=1)*(YEAR(Expenses!A$3:A$999)=2026)*(Expenses!A$3:A$999<>"")*(IF(Expenses!G$3:G$999="Yes",Expenses!H$3:H$999,Expenses!D$3:D$999))) | E3: =SUMPRODUCT((Expenses!C$3:C$999="Shopping")*(Expenses!E$3:E$999="INR")*(MONTH(Expenses!A$3:A$999)=1)*(YEAR(Expenses!A$3:A$999)=2026)*(Expenses!A$3:A$999<>"")*(IF(Expenses!G$3:G$999="Yes",Expenses!H$3:H$999,Expenses!D$3:D$999))) | F3: =SUMPRODUCT((Expenses!C$3:C$999="Electronics")*(Expenses!E$3:E$999="INR")*(MONTH(Expenses!A$3:A$999)=1)*(YEAR(Expenses!A$3:A$999)=2026)*(Expenses!A$3:A$999<>"")*(IF(Expenses!G$3:G$999="Yes",Expenses!H$3:H$999,Expenses!D$3:D$999))) | G3: =SUMPRODUCT((Expenses!C$3:C$999="Subscriptions")*(Expenses!E$3:E$999="INR")*(MONTH(Expenses!A$3:A$999)=1)*(YEAR(Expenses!A$3:A$999)=2026)*(Expenses!A$3:A$999<>"")*(IF(Expenses!G$3:G$999="Yes",Expenses!H$3:H$999,Expenses!D$3:D$999))) | H3: =SUMPRODUCT((Expenses!C$3:C$999="Bills")*(Expenses!E$3:E$999="INR")*(MONTH(Expenses!A$3:A$999)=1)*(YEAR(Expenses!A$3:A$999)=2026)*(Expenses!A$3:A$999<>"")*(IF(Expenses!G$3:G$999="Yes",Expenses!H$3:H$999,Expenses!D$3:D$999))) | I3: =SUMPRODUCT((Expenses!C$3:C$999="Entertainment")*(Expenses!E$3:E$999="INR")*(MONTH(Expenses!A$3:A$999)=1)*(YEAR(Expenses!A$3:A$999)=2026)*(Expenses!A$3:A$999<>"")*(IF(Expenses!G$3:G$999="Yes",Expenses!H$3:H$999,Expenses!D$3:D$999))) | J3: =SUMPRODUCT((Expenses!C$3:C$999="Food and Drinks")*(Expenses!E$3:E$999="INR")*(MONTH(Expenses!A$3:A$999)=1)*(YEAR(Expenses!A$3:A$999)=2026)*(Expenses!A$3:A$999<>"")*(IF(Expenses!G$3:G$999="Yes",Expenses!H$3:H$999,Expenses!D$3:D$999))) | K3: =SUMPRODUCT((Expenses!C$3:C$999="Groceries")*(Expenses!E$3:E$999="INR")*(MONTH(Expenses!A$3:A$999)=1)*(YEAR(Expenses!A$3:A$999)=2026)*(Expenses!A$3:A$999<>"")*(IF(Expenses!G$3:G$999="Yes",Expenses!H$3:H$999,Expenses!D$3:D$999))) | L3: =SUMPRODUCT((Expenses!C$3:C$999="Others")*(Expenses!E$3:E$999="INR")*(MONTH(Expenses!A$3:A$999)=1)*(YEAR(Expenses!A$3:A$999)=2026)*(Expenses!A$3:A$999<>"")*(IF(Expenses!G$3:G$999="Yes",Expenses!H$3:H$999,Expenses!D$3:D$999))) | M3: =SUMPRODUCT((Expenses!C$3:C$999="Gifts")*(Expenses!E$3:E$999="INR")*(MONTH(Expenses!A$3:A$999)=1)*(YEAR(Expenses!A$3:A$999)=2026)*(Expenses!A$3:A$999<>"")*(IF(Expenses!G$3:G$999="Yes",Expenses!H$3:H$999,Expenses!D$3:D$999))) | N3: =SUMPRODUCT((Expenses!C$3:C$999="Donations")*(Expenses!E$3:E$999="INR")*(MONTH(Expenses!A$3:A$999)=1)*(YEAR(Expenses!A$3:A$999)=2026)*(Expenses!A$3:A$999<>"")*(IF(Expenses!G$3:G$999="Yes",Expenses!H$3:H$999,Expenses!D$3:D$999))) | O3: =SUMPRODUCT((Expenses!C$3:C$999="Investments")*(Expenses!E$3:E$999="INR")*(MONTH(Expenses!A$3:A$999)=1)*(YEAR(Expenses!A$3:A$999)=2026)*(Expenses!A$3:A$999<>"")*(IF(Expenses!G$3:G$999="Yes",Expenses!H$3:H$999,Expenses!D$3:D$999))) | P3: =SUM(B3:O3) | Q3: =SUMPRODUCT((Income!D$3:D$502="INR")*(MONTH(Income!A$3:A$502)=1)*(YEAR(Income!A$3:A$502)=2026)*(Income!A$3:A$502<>"")*Income!C$3:C$502) | R3: =Q3-P3
A4: February 2026 | B4: =SUMPRODUCT((Expenses!C$3:C$999="Rent")*(Expenses!E$3:E$999="INR")*(MONTH(Expenses!A$3:A$999)=2)*(YEAR(Expenses!A$3:A$999)=2026)*(Expenses!A$3:A$999<>"")*(IF(Expenses!G$3:G$999="Yes",Expenses!H$3:H$999,Expenses!D$3:D$999))) | C4: =SUMPRODUCT((Expenses!C$3:C$999="Transport")*(Expenses!E$3:E$999="INR")*(MONTH(Expenses!A$3:A$999)=2)*(YEAR(Expenses!A$3:A$999)=2026)*(Expenses!A$3:A$999<>"")*(IF(Expenses!G$3:G$999="Yes",Expenses!H$3:H$999,Expenses!D$3:D$999))) | D4: =SUMPRODUCT((Expenses!C$3:C$999="Travel")*(Expenses!E$3:E$999="INR")*(MONTH(Expenses!A$3:A$999)=2)*(YEAR(Expenses!A$3:A$999)=2026)*(Expenses!A$3:A$999<>"")*(IF(Expenses!G$3:G$999="Yes",Expenses!H$3:H$999,Expenses!D$3:D$999))) | E4: =SUMPRODUCT((Expenses!C$3:C$999="Shopping")*(Expenses!E$3:E$999="INR")*(MONTH(Expenses!A$3:A$999)=2)*(YEAR(Expenses!A$3:A$999)=2026)*(Expenses!A$3:A$999<>"")*(IF(Expenses!G$3:G$999="Yes",Expenses!H$3:H$999,Expenses!D$3:D$999))) | F4: =SUMPRODUCT((Expenses!C$3:C$999="Electronics")*(Expenses!E$3:E$999="INR")*(MONTH(Expenses!A$3:A$999)=2)*(YEAR(Expenses!A$3:A$999)=2026)*(Expenses!A$3:A$999<>"")*(IF(Expenses!G$3:G$999="Yes",Expenses!H$3:H$999,Expenses!D$3:D$999))) | G4: =SUMPRODUCT((Expenses!C$3:C$999="Subscriptions")*(Expenses!E$3:E$999="INR")*(MONTH(Expenses!A$3:A$999)=2)*(YEAR(Expenses!A$3:A$999)=2026)*(Expenses!A$3:A$999<>"")*(IF(Expenses!G$3:G$999="Yes",Expenses!H$3:H$999,Expenses!D$3:D$999))) | H4: =SUMPRODUCT((Expenses!C$3:C$999="Bills")*(Expenses!E$3:E$999="INR")*(MONTH(Expenses!A$3:A$999)=2)*(YEAR(Expenses!A$3:A$999)=2026)*(Expenses!A$3:A$999<>"")*(IF(Expenses!G$3:G$999="Yes",Expenses!H$3:H$999,Expenses!D$3:D$999))) | I4: =SUMPRODUCT((Expenses!C$3:C$999="Entertainment")*(Expenses!E$3:E$999="INR")*(MONTH(Expenses!A$3:A$999)=2)*(YEAR(Expenses!A$3:A$999)=2026)*(Expenses!A$3:A$999<>"")*(IF(Expenses!G$3:G$999="Yes",Expenses!H$3:H$999,Expenses!D$3:D$999))) | J4: =SUMPRODUCT((Expenses!C$3:C$999="Food and Drinks")*(Expenses!E$3:E$999="INR")*(MONTH(Expenses!A$3:A$999)=2)*(YEAR(Expenses!A$3:A$999)=2026)*(Expenses!A$3:A$999<>"")*(IF(Expenses!G$3:G$999="Yes",Expenses!H$3:H$999,Expenses!D$3:D$999))) | K4: =SUMPRODUCT((Expenses!C$3:C$999="Groceries")*(Expenses!E$3:E$999="INR")*(MONTH(Expenses!A$3:A$999)=2)*(YEAR(Expenses!A$3:A$999)=2026)*(Expenses!A$3:A$999<>"")*(IF(Expenses!G$3:G$999="Yes",Expenses!H$3:H$999,Expenses!D$3:D$999))) | L4: =SUMPRODUCT((Expenses!C$3:C$999="Others")*(Expenses!E$3:E$999="INR")*(MONTH(Expenses!A$3:A$999)=2)*(YEAR(Expenses!A$3:A$999)=2026)*(Expenses!A$3:A$999<>"")*(IF(Expenses!G$3:G$999="Yes",Expenses!H$3:H$999,Expenses!D$3:D$999))) | M4: =SUMPRODUCT((Expenses!C$3:C$999="Gifts")*(Expenses!E$3:E$999="INR")*(MONTH(Expenses!A$3:A$999)=2)*(YEAR(Expenses!A$3:A$999)=2026)*(Expenses!A$3:A$999<>"")*(IF(Expenses!G$3:G$999="Yes",Expenses!H$3:H$999,Expenses!D$3:D$999))) | N4: =SUMPRODUCT((Expenses!C$3:C$999="Donations")*(Expenses!E$3:E$999="INR")*(MONTH(Expenses!A$3:A$999)=2)*(YEAR(Expenses!A$3:A$999)=2026)*(Expenses!A$3:A$999<>"")*(IF(Expenses!G$3:G$999="Yes",Expenses!H$3:H$999,Expenses!D$3:D$999))) | O4: =SUMPRODUCT((Expenses!C$3:C$999="Investments")*(Expenses!E$3:E$999="INR")*(MONTH(Expenses!A$3:A$999)=2)*(YEAR(Expenses!A$3:A$999)=2026)*(Expenses!A$3:A$999<>"")*(IF(Expenses!G$3:G$999="Yes",Expenses!H$3:H$999,Expenses!D$3:D$999))) | P4: =SUM(B4:O4) | Q4: =SUMPRODUCT((Income!D$3:D$502="INR")*(MONTH(Income!A$3:A$502)=2)*(YEAR(Income!A$3:A$502)=2026)*(Income!A$3:A$502<>"")*Income!C$3:C$502) | R4: =Q4-P4
A5: March 2026 | B5: =SUMPRODUCT((Expenses!C$3:C$999="Rent")*(Expenses!E$3:E$999="INR")*(MONTH(Expenses!A$3:A$999)=3)*(YEAR(Expenses!A$3:A$999)=2026)*(Expenses!A$3:A$999<>"")*(IF(Expenses!G$3:G$999="Yes",Expenses!H$3:H$999,Expenses!D$3:D$999))) | C5: =SUMPRODUCT((Expenses!C$3:C$999="Transport")*(Expenses!E$3:E$999="INR")*(MONTH(Expenses!A$3:A$999)=3)*(YEAR(Expenses!A$3:A$999)=2026)*(Expenses!A$3:A$999<>"")*(IF(Expenses!G$3:G$999="Yes",Expenses!H$3:H$999,Expenses!D$3:D$999))) | D5: =SUMPRODUCT((Expenses!C$3:C$999="Travel")*(Expenses!E$3:E$999="INR")*(MONTH(Expenses!A$3:A$999)=3)*(YEAR(Expenses!A$3:A$999)=2026)*(Expenses!A$3:A$999<>"")*(IF(Expenses!G$3:G$999="Yes",Expenses!H$3:H$999,Expenses!D$3:D$999))) | E5: =SUMPRODUCT((Expenses!C$3:C$999="Shopping")*(Expenses!E$3:E$999="INR")*(MONTH(Expenses!A$3:A$999)=3)*(YEAR(Expenses!A$3:A$999)=2026)*(Expenses!A$3:A$999<>"")*(IF(Expenses!G$3:G$999="Yes",Expenses!H$3:H$999,Expenses!D$3:D$999))) | F5: =SUMPRODUCT((Expenses!C$3:C$999="Electronics")*(Expenses!E$3:E$999="INR")*(MONTH(Expenses!A$3:A$999)=3)*(YEAR(Expenses!A$3:A$999)=2026)*(Expenses!A$3:A$999<>"")*(IF(Expenses!G$3:G$999="Yes",Expenses!H$3:H$999,Expenses!D$3:D$999))) | G5: =SUMPRODUCT((Expenses!C$3:C$999="Subscriptions")*(Expenses!E$3:E$999="INR")*(MONTH(Expenses!A$3:A$999)=3)*(YEAR(Expenses!A$3:A$999)=2026)*(Expenses!A$3:A$999<>"")*(IF(Expenses!G$3:G$999="Yes",Expenses!H$3:H$999,Expenses!D$3:D$999))) | H5: =SUMPRODUCT((Expenses!C$3:C$999="Bills")*(Expenses!E$3:E$999="INR")*(MONTH(Expenses!A$3:A$999)=3)*(YEAR(Expenses!A$3:A$999)=2026)*(Expenses!A$3:A$999<>"")*(IF(Expenses!G$3:G$999="Yes",Expenses!H$3:H$999,Expenses!D$3:D$999))) | I5: =SUMPRODUCT((Expenses!C$3:C$999="Entertainment")*(Expenses!E$3:E$999="INR")*(MONTH(Expenses!A$3:A$999)=3)*(YEAR(Expenses!A$3:A$999)=2026)*(Expenses!A$3:A$999<>"")*(IF(Expenses!G$3:G$999="Yes",Expenses!H$3:H$999,Expenses!D$3:D$999))) | J5: =SUMPRODUCT((Expenses!C$3:C$999="Food and Drinks")*(Expenses!E$3:E$999="INR")*(MONTH(Expenses!A$3:A$999)=3)*(YEAR(Expenses!A$3:A$999)=2026)*(Expenses!A$3:A$999<>"")*(IF(Expenses!G$3:G$999="Yes",Expenses!H$3:H$999,Expenses!D$3:D$999))) | K5: =SUMPRODUCT((Expenses!C$3:C$999="Groceries")*(Expenses!E$3:E$999="INR")*(MONTH(Expenses!A$3:A$999)=3)*(YEAR(Expenses!A$3:A$999)=2026)*(Expenses!A$3:A$999<>"")*(IF(Expenses!G$3:G$999="Yes",Expenses!H$3:H$999,Expenses!D$3:D$999))) | L5: =SUMPRODUCT((Expenses!C$3:C$999="Others")*(Expenses!E$3:E$999="INR")*(MONTH(Expenses!A$3:A$999)=3)*(YEAR(Expenses!A$3:A$999)=2026)*(Expenses!A$3:A$999<>"")*(IF(Expenses!G$3:G$999="Yes",Expenses!H$3:H$999,Expenses!D$3:D$999))) | M5: =SUMPRODUCT((Expenses!C$3:C$999="Gifts")*(Expenses!E$3:E$999="INR")*(MONTH(Expenses!A$3:A$999)=3)*(YEAR(Expenses!A$3:A$999)=2026)*(Expenses!A$3:A$999<>"")*(IF(Expenses!G$3:G$999="Yes",Expenses!H$3:H$999,Expenses!D$3:D$999))) | N5: =SUMPRODUCT((Expenses!C$3:C$999="Donations")*(Expenses!E$3:E$999="INR")*(MONTH(Expenses!A$3:A$999)=3)*(YEAR(Expenses!A$3:A$999)=2026)*(Expenses!A$3:A$999<>"")*(IF(Expenses!G$3:G$999="Yes",Expenses!H$3:H$999,Expenses!D$3:D$999))) | O5: =SUMPRODUCT((Expenses!C$3:C$999="Investments")*(Expenses!E$3:E$999="INR")*(MONTH(Expenses!A$3:A$999)=3)*(YEAR(Expenses!A$3:A$999)=2026)*(Expenses!A$3:A$999<>"")*(IF(Expenses!G$3:G$999="Yes",Expenses!H$3:H$999,Expenses!D$3:D$999))) | P5: =SUM(B5:O5) | Q5: =SUMPRODUCT((Income!D$3:D$502="INR")*(MONTH(Income!A$3:A$502)=3)*(YEAR(Income!A$3:A$502)=2026)*(Income!A$3:A$502<>"")*Income!C$3:C$502) | R5: =Q5-P5
A6: April 2026 | B6: =SUMPRODUCT((Expenses!C$3:C$999="Rent")*(Expenses!E$3:E$999="INR")*(MONTH(Expenses!A$3:A$999)=4)*(YEAR(Expenses!A$3:A$999)=2026)*(Expenses!A$3:A$999<>"")*(IF(Expenses!G$3:G$999="Yes",Expenses!H$3:H$999,Expenses!D$3:D$999))) | C6: =SUMPRODUCT((Expenses!C$3:C$999="Transport")*(Expenses!E$3:E$999="INR")*(MONTH(Expenses!A$3:A$999)=4)*(YEAR(Expenses!A$3:A$999)=2026)*(Expenses!A$3:A$999<>"")*(IF(Expenses!G$3:G$999="Yes",Expenses!H$3:H$999,Expenses!D$3:D$999))) | D6: =SUMPRODUCT((Expenses!C$3:C$999="Travel")*(Expenses!E$3:E$999="INR")*(MONTH(Expenses!A$3:A$999)=4)*(YEAR(Expenses!A$3:A$999)=2026)*(Expenses!A$3:A$999<>"")*(IF(Expenses!G$3:G$999="Yes",Expenses!H$3:H$999,Expenses!D$3:D$999))) | E6: =SUMPRODUCT((Expenses!C$3:C$999="Shopping")*(Expenses!E$3:E$999="INR")*(MONTH(Expenses!A$3:A$999)=4)*(YEAR(Expenses!A$3:A$999)=2026)*(Expenses!A$3:A$999<>"")*(IF(Expenses!G$3:G$999="Yes",Expenses!H$3:H$999,Expenses!D$3:D$999))) | F6: =SUMPRODUCT((Expenses!C$3:C$999="Electronics")*(Expenses!E$3:E$999="INR")*(MONTH(Expenses!A$3:A$999)=4)*(YEAR(Expenses!A$3:A$999)=2026)*(Expenses!A$3:A$999<>"")*(IF(Expenses!G$3:G$999="Yes",Expenses!H$3:H$999,Expenses!D$3:D$999))) | G6: =SUMPRODUCT((Expenses!C$3:C$999="Subscriptions")*(Expenses!E$3:E$999="INR")*(MONTH(Expenses!A$3:A$999)=4)*(YEAR(Expenses!A$3:A$999)=2026)*(Expenses!A$3:A$999<>"")*(IF(Expenses!G$3:G$999="Yes",Expenses!H$3:H$999,Expenses!D$3:D$999))) | H6: =SUMPRODUCT((Expenses!C$3:C$999="Bills")*(Expenses!E$3:E$999="INR")*(MONTH(Expenses!A$3:A$999)=4)*(YEAR(Expenses!A$3:A$999)=2026)*(Expenses!A$3:A$999<>"")*(IF(Expenses!G$3:G$999="Yes",Expenses!H$3:H$999,Expenses!D$3:D$999))) | I6: =SUMPRODUCT((Expenses!C$3:C$999="Entertainment")*(Expenses!E$3:E$999="INR")*(MONTH(Expenses!A$3:A$999)=4)*(YEAR(Expenses!A$3:A$999)=2026)*(Expenses!A$3:A$999<>"")*(IF(Expenses!G$3:G$999="Yes",Expenses!H$3:H$999,Expenses!D$3:D$999))) | J6: =SUMPRODUCT((Expenses!C$3:C$999="Food and Drinks")*(Expenses!E$3:E$999="INR")*(MONTH(Expenses!A$3:A$999)=4)*(YEAR(Expenses!A$3:A$999)=2026)*(Expenses!A$3:A$999<>"")*(IF(Expenses!G$3:G$999="Yes",Expenses!H$3:H$999,Expenses!D$3:D$999))) | K6: =SUMPRODUCT((Expenses!C$3:C$999="Groceries")*(Expenses!E$3:E$999="INR")*(MONTH(Expenses!A$3:A$999)=4)*(YEAR(Expenses!A$3:A$999)=2026)*(Expenses!A$3:A$999<>"")*(IF(Expenses!G$3:G$999="Yes",Expenses!H$3:H$999,Expenses!D$3:D$999))) | L6: =SUMPRODUCT((Expenses!C$3:C$999="Others")*(Expenses!E$3:E$999="INR")*(MONTH(Expenses!A$3:A$999)=4)*(YEAR(Expenses!A$3:A$999)=2026)*(Expenses!A$3:A$999<>"")*(IF(Expenses!G$3:G$999="Yes",Expenses!H$3:H$999,Expenses!D$3:D$999))) | M6: =SUMPRODUCT((Expenses!C$3:C$999="Gifts")*(Expenses!E$3:E$999="INR")*(MONTH(Expenses!A$3:A$999)=4)*(YEAR(Expenses!A$3:A$999)=2026)*(Expenses!A$3:A$999<>"")*(IF(Expenses!G$3:G$999="Yes",Expenses!H$3:H$999,Expenses!D$3:D$999))) | N6: =SUMPRODUCT((Expenses!C$3:C$999="Donations")*(Expenses!E$3:E$999="INR")*(MONTH(Expenses!A$3:A$999)=4)*(YEAR(Expenses!A$3:A$999)=2026)*(Expenses!A$3:A$999<>"")*(IF(Expenses!G$3:G$999="Yes",Expenses!H$3:H$999,Expenses!D$3:D$999))) | O6: =SUMPRODUCT((Expenses!C$3:C$999="Investments")*(Expenses!E$3:E$999="INR")*(MONTH(Expenses!A$3:A$999)=4)*(YEAR(Expenses!A$3:A$999)=2026)*(Expenses!A$3:A$999<>"")*(IF(Expenses!G$3:G$999="Yes",Expenses!H$3:H$999,Expenses!D$3:D$999))) | P6: =SUM(B6:O6) | Q6: =SUMPRODUCT((Income!D$3:D$502="INR")*(MONTH(Income!A$3:A$502)=4)*(YEAR(Income!A$3:A$502)=2026)*(Income!A$3:A$502<>"")*Income!C$3:C$502) | R6: =Q6-P6
A7: May 2026 | B7: =SUMPRODUCT((Expenses!C$3:C$999="Rent")*(Expenses!E$3:E$999="INR")*(MONTH(Expenses!A$3:A$999)=5)*(YEAR(Expenses!A$3:A$999)=2026)*(Expenses!A$3:A$999<>"")*(IF(Expenses!G$3:G$999="Yes",Expenses!H$3:H$999,Expenses!D$3:D$999))) | C7: =SUMPRODUCT((Expenses!C$3:C$999="Transport")*(Expenses!E$3:E$999="INR")*(MONTH(Expenses!A$3:A$999)=5)*(YEAR(Expenses!A$3:A$999)=2026)*(Expenses!A$3:A$999<>"")*(IF(Expenses!G$3:G$999="Yes",Expenses!H$3:H$999,Expenses!D$3:D$999))) | D7: =SUMPRODUCT((Expenses!C$3:C$999="Travel")*(Expenses!E$3:E$999="INR")*(MONTH(Expenses!A$3:A$999)=5)*(YEAR(Expenses!A$3:A$999)=2026)*(Expenses!A$3:A$999<>"")*(IF(Expenses!G$3:G$999="Yes",Expenses!H$3:H$999,Expenses!D$3:D$999))) | E7: =SUMPRODUCT((Expenses!C$3:C$999="Shopping")*(Expenses!E$3:E$999="INR")*(MONTH(Expenses!A$3:A$999)=5)*(YEAR(Expenses!A$3:A$999)=2026)*(Expenses!A$3:A$999<>"")*(IF(Expenses!G$3:G$999="Yes",Expenses!H$3:H$999,Expenses!D$3:D$999))) | F7: =SUMPRODUCT((Expenses!C$3:C$999="Electronics")*(Expenses!E$3:E$999="INR")*(MONTH(Expenses!A$3:A$999)=5)*(YEAR(Expenses!A$3:A$999)=2026)*(Expenses!A$3:A$999<>"")*(IF(Expenses!G$3:G$999="Yes",Expenses!H$3:H$999,Expenses!D$3:D$999))) | G7: =SUMPRODUCT((Expenses!C$3:C$999="Subscriptions")*(Expenses!E$3:E$999="INR")*(MONTH(Expenses!A$3:A$999)=5)*(YEAR(Expenses!A$3:A$999)=2026)*(Expenses!A$3:A$999<>"")*(IF(Expenses!G$3:G$999="Yes",Expenses!H$3:H$999,Expenses!D$3:D$999))) | H7: =SUMPRODUCT((Expenses!C$3:C$999="Bills")*(Expenses!E$3:E$999="INR")*(MONTH(Expenses!A$3:A$999)=5)*(YEAR(Expenses!A$3:A$999)=2026)*(Expenses!A$3:A$999<>"")*(IF(Expenses!G$3:G$999="Yes",Expenses!H$3:H$999,Expenses!D$3:D$999))) | I7: =SUMPRODUCT((Expenses!C$3:C$999="Entertainment")*(Expenses!E$3:E$999="INR")*(MONTH(Expenses!A$3:A$999)=5)*(YEAR(Expenses!A$3:A$999)=2026)*(Expenses!A$3:A$999<>"")*(IF(Expenses!G$3:G$999="Yes",Expenses!H$3:H$999,Expenses!D$3:D$999))) | J7: =SUMPRODUCT((Expenses!C$3:C$999="Food and Drinks")*(Expenses!E$3:E$999="INR")*(MONTH(Expenses!A$3:A$999)=5)*(YEAR(Expenses!A$3:A$999)=2026)*(Expenses!A$3:A$999<>"")*(IF(Expenses!G$3:G$999="Yes",Expenses!H$3:H$999,Expenses!D$3:D$999))) | K7: =SUMPRODUCT((Expenses!C$3:C$999="Groceries")*(Expenses!E$3:E$999="INR")*(MONTH(Expenses!A$3:A$999)=5)*(YEAR(Expenses!A$3:A$999)=2026)*(Expenses!A$3:A$999<>"")*(IF(Expenses!G$3:G$999="Yes",Expenses!H$3:H$999,Expenses!D$3:D$999))) | L7: =SUMPRODUCT((Expenses!C$3:C$999="Others")*(Expenses!E$3:E$999="INR")*(MONTH(Expenses!A$3:A$999)=5)*(YEAR(Expenses!A$3:A$999)=2026)*(Expenses!A$3:A$999<>"")*(IF(Expenses!G$3:G$999="Yes",Expenses!H$3:H$999,Expenses!D$3:D$999))) | M7: =SUMPRODUCT((Expenses!C$3:C$999="Gifts")*(Expenses!E$3:E$999="INR")*(MONTH(Expenses!A$3:A$999)=5)*(YEAR(Expenses!A$3:A$999)=2026)*(Expenses!A$3:A$999<>"")*(IF(Expenses!G$3:G$999="Yes",Expenses!H$3:H$999,Expenses!D$3:D$999))) | N7: =SUMPRODUCT((Expenses!C$3:C$999="Donations")*(Expenses!E$3:E$999="INR")*(MONTH(Expenses!A$3:A$999)=5)*(YEAR(Expenses!A$3:A$999)=2026)*(Expenses!A$3:A$999<>"")*(IF(Expenses!G$3:G$999="Yes",Expenses!H$3:H$999,Expenses!D$3:D$999))) | O7: =SUMPRODUCT((Expenses!C$3:C$999="Investments")*(Expenses!E$3:E$999="INR")*(MONTH(Expenses!A$3:A$999)=5)*(YEAR(Expenses!A$3:A$999)=2026)*(Expenses!A$3:A$999<>"")*(IF(Expenses!G$3:G$999="Yes",Expenses!H$3:H$999,Expenses!D$3:D$999))) | P7: =SUM(B7:O7) | Q7: =SUMPRODUCT((Income!D$3:D$502="INR")*(MONTH(Income!A$3:A$502)=5)*(YEAR(Income!A$3:A$502)=2026)*(Income!A$3:A$502<>"")*Income!C$3:C$502) | R7: =Q7-P7
A8: June 2026 | B8: =SUMPRODUCT((Expenses!C$3:C$999="Rent")*(Expenses!E$3:E$999="INR")*(MONTH(Expenses!A$3:A$999)=6)*(YEAR(Expenses!A$3:A$999)=2026)*(Expenses!A$3:A$999<>"")*(IF(Expenses!G$3:G$999="Yes",Expenses!H$3:H$999,Expenses!D$3:D$999))) | C8: =SUMPRODUCT((Expenses!C$3:C$999="Transport")*(Expenses!E$3:E$999="INR")*(MONTH(Expenses!A$3:A$999)=6)*(YEAR(Expenses!A$3:A$999)=2026)*(Expenses!A$3:A$999<>"")*(IF(Expenses!G$3:G$999="Yes",Expenses!H$3:H$999,Expenses!D$3:D$999))) | D8: =SUMPRODUCT((Expenses!C$3:C$999="Travel")*(Expenses!E$3:E$999="INR")*(MONTH(Expenses!A$3:A$999)=6)*(YEAR(Expenses!A$3:A$999)=2026)*(Expenses!A$3:A$999<>"")*(IF(Expenses!G$3:G$999="Yes",Expenses!H$3:H$999,Expenses!D$3:D$999))) | E8: =SUMPRODUCT((Expenses!C$3:C$999="Shopping")*(Expenses!E$3:E$999="INR")*(MONTH(Expenses!A$3:A$999)=6)*(YEAR(Expenses!A$3:A$999)=2026)*(Expenses!A$3:A$999<>"")*(IF(Expenses!G$3:G$999="Yes",Expenses!H$3:H$999,Expenses!D$3:D$999))) | F8: =SUMPRODUCT((Expenses!C$3:C$999="Electronics")*(Expenses!E$3:E$999="INR")*(MONTH(Expenses!A$3:A$999)=6)*(YEAR(Expenses!A$3:A$999)=2026)*(Expenses!A$3:A$999<>"")*(IF(Expenses!G$3:G$999="Yes",Expenses!H$3:H$999,Expenses!D$3:D$999))) | G8: =SUMPRODUCT((Expenses!C$3:C$999="Subscriptions")*(Expenses!E$3:E$999="INR")*(MONTH(Expenses!A$3:A$999)=6)*(YEAR(Expenses!A$3:A$999)=2026)*(Expenses!A$3:A$999<>"")*(IF(Expenses!G$3:G$999="Yes",Expenses!H$3:H$999,Expenses!D$3:D$999))) | H8: =SUMPRODUCT((Expenses!C$3:C$999="Bills")*(Expenses!E$3:E$999="INR")*(MONTH(Expenses!A$3:A$999)=6)*(YEAR(Expenses!A$3:A$999)=2026)*(Expenses!A$3:A$999<>"")*(IF(Expenses!G$3:G$999="Yes",Expenses!H$3:H$999,Expenses!D$3:D$999))) | I8: =SUMPRODUCT((Expenses!C$3:C$999="Entertainment")*(Expenses!E$3:E$999="INR")*(MONTH(Expenses!A$3:A$999)=6)*(YEAR(Expenses!A$3:A$999)=2026)*(Expenses!A$3:A$999<>"")*(IF(Expenses!G$3:G$999="Yes",Expenses!H$3:H$999,Expenses!D$3:D$999))) | J8: =SUMPRODUCT((Expenses!C$3:C$999="Food and Drinks")*(Expenses!E$3:E$999="INR")*(MONTH(Expenses!A$3:A$999)=6)*(YEAR(Expenses!A$3:A$999)=2026)*(Expenses!A$3:A$999<>"")*(IF(Expenses!G$3:G$999="Yes",Expenses!H$3:H$999,Expenses!D$3:D$999))) | K8: =SUMPRODUCT((Expenses!C$3:C$999="Groceries")*(Expenses!E$3:E$999="INR")*(MONTH(Expenses!A$3:A$999)=6)*(YEAR(Expenses!A$3:A$999)=2026)*(Expenses!A$3:A$999<>"")*(IF(Expenses!G$3:G$999="Yes",Expenses!H$3:H$999,Expenses!D$3:D$999))) | L8: =SUMPRODUCT((Expenses!C$3:C$999="Others")*(Expenses!E$3:E$999="INR")*(MONTH(Expenses!A$3:A$999)=6)*(YEAR(Expenses!A$3:A$999)=2026)*(Expenses!A$3:A$999<>"")*(IF(Expenses!G$3:G$999="Yes",Expenses!H$3:H$999,Expenses!D$3:D$999))) | M8: =SUMPRODUCT((Expenses!C$3:C$999="Gifts")*(Expenses!E$3:E$999="INR")*(MONTH(Expenses!A$3:A$999)=6)*(YEAR(Expenses!A$3:A$999)=2026)*(Expenses!A$3:A$999<>"")*(IF(Expenses!G$3:G$999="Yes",Expenses!H$3:H$999,Expenses!D$3:D$999))) | N8: =SUMPRODUCT((Expenses!C$3:C$999="Donations")*(Expenses!E$3:E$999="INR")*(MONTH(Expenses!A$3:A$999)=6)*(YEAR(Expenses!A$3:A$999)=2026)*(Expenses!A$3:A$999<>"")*(IF(Expenses!G$3:G$999="Yes",Expenses!H$3:H$999,Expenses!D$3:D$999))) | O8: =SUMPRODUCT((Expenses!C$3:C$999="Investments")*(Expenses!E$3:E$999="INR")*(MONTH(Expenses!A$3:A$999)=6)*(YEAR(Expenses!A$3:A$999)=2026)*(Expenses!A$3:A$999<>"")*(IF(Expenses!G$3:G$999="Yes",Expenses!H$3:H$999,Expenses!D$3:D$999))) | P8: =SUM(B8:O8) | Q8: =SUMPRODUCT((Income!D$3:D$502="INR")*(MONTH(Income!A$3:A$502)=6)*(YEAR(Income!A$3:A$502)=2026)*(Income!A$3:A$502<>"")*Income!C$3:C$502) | R8: =Q8-P8
A9: July 2026 | B9: =SUMPRODUCT((Expenses!C$3:C$999="Rent")*(Expenses!E$3:E$999="INR")*(MONTH(Expenses!A$3:A$999)=7)*(YEAR(Expenses!A$3:A$999)=2026)*(Expenses!A$3:A$999<>"")*(IF(Expenses!G$3:G$999="Yes",Expenses!H$3:H$999,Expenses!D$3:D$999))) | C9: =SUMPRODUCT((Expenses!C$3:C$999="Transport")*(Expenses!E$3:E$999="INR")*(MONTH(Expenses!A$3:A$999)=7)*(YEAR(Expenses!A$3:A$999)=2026)*(Expenses!A$3:A$999<>"")*(IF(Expenses!G$3:G$999="Yes",Expenses!H$3:H$999,Expenses!D$3:D$999))) | D9: =SUMPRODUCT((Expenses!C$3:C$999="Travel")*(Expenses!E$3:E$999="INR")*(MONTH(Expenses!A$3:A$999)=7)*(YEAR(Expenses!A$3:A$999)=2026)*(Expenses!A$3:A$999<>"")*(IF(Expenses!G$3:G$999="Yes",Expenses!H$3:H$999,Expenses!D$3:D$999))) | E9: =SUMPRODUCT((Expenses!C$3:C$999="Shopping")*(Expenses!E$3:E$999="INR")*(MONTH(Expenses!A$3:A$999)=7)*(YEAR(Expenses!A$3:A$999)=2026)*(Expenses!A$3:A$999<>"")*(IF(Expenses!G$3:G$999="Yes",Expenses!H$3:H$999,Expenses!D$3:D$999))) | F9: =SUMPRODUCT((Expenses!C$3:C$999="Electronics")*(Expenses!E$3:E$999="INR")*(MONTH(Expenses!A$3:A$999)=7)*(YEAR(Expenses!A$3:A$999)=2026)*(Expenses!A$3:A$999<>"")*(IF(Expenses!G$3:G$999="Yes",Expenses!H$3:H$999,Expenses!D$3:D$999))) | G9: =SUMPRODUCT((Expenses!C$3:C$999="Subscriptions")*(Expenses!E$3:E$999="INR")*(MONTH(Expenses!A$3:A$999)=7)*(YEAR(Expenses!A$3:A$999)=2026)*(Expenses!A$3:A$999<>"")*(IF(Expenses!G$3:G$999="Yes",Expenses!H$3:H$999,Expenses!D$3:D$999))) | H9: =SUMPRODUCT((Expenses!C$3:C$999="Bills")*(Expenses!E$3:E$999="INR")*(MONTH(Expenses!A$3:A$999)=7)*(YEAR(Expenses!A$3:A$999)=2026)*(Expenses!A$3:A$999<>"")*(IF(Expenses!G$3:G$999="Yes",Expenses!H$3:H$999,Expenses!D$3:D$999))) | I9: =SUMPRODUCT((Expenses!C$3:C$999="Entertainment")*(Expenses!E$3:E$999="INR")*(MONTH(Expenses!A$3:A$999)=7)*(YEAR(Expenses!A$3:A$999)=2026)*(Expenses!A$3:A$999<>"")*(IF(Expenses!G$3:G$999="Yes",Expenses!H$3:H$999,Expenses!D$3:D$999))) | J9: =SUMPRODUCT((Expenses!C$3:C$999="Food and Drinks")*(Expenses!E$3:E$999="INR")*(MONTH(Expenses!A$3:A$999)=7)*(YEAR(Expenses!A$3:A$999)=2026)*(Expenses!A$3:A$999<>"")*(IF(Expenses!G$3:G$999="Yes",Expenses!H$3:H$999,Expenses!D$3:D$999))) | K9: =SUMPRODUCT((Expenses!C$3:C$999="Groceries")*(Expenses!E$3:E$999="INR")*(MONTH(Expenses!A$3:A$999)=7)*(YEAR(Expenses!A$3:A$999)=2026)*(Expenses!A$3:A$999<>"")*(IF(Expenses!G$3:G$999="Yes",Expenses!H$3:H$999,Expenses!D$3:D$999))) | L9: =SUMPRODUCT((Expenses!C$3:C$999="Others")*(Expenses!E$3:E$999="INR")*(MONTH(Expenses!A$3:A$999)=7)*(YEAR(Expenses!A$3:A$999)=2026)*(Expenses!A$3:A$999<>"")*(IF(Expenses!G$3:G$999="Yes",Expenses!H$3:H$999,Expenses!D$3:D$999))) | M9: =SUMPRODUCT((Expenses!C$3:C$999="Gifts")*(Expenses!E$3:E$999="INR")*(MONTH(Expenses!A$3:A$999)=7)*(YEAR(Expenses!A$3:A$999)=2026)*(Expenses!A$3:A$999<>"")*(IF(Expenses!G$3:G$999="Yes",Expenses!H$3:H$999,Expenses!D$3:D$999))) | N9: =SUMPRODUCT((Expenses!C$3:C$999="Donations")*(Expenses!E$3:E$999="INR")*(MONTH(Expenses!A$3:A$999)=7)*(YEAR(Expenses!A$3:A$999)=2026)*(Expenses!A$3:A$999<>"")*(IF(Expenses!G$3:G$999="Yes",Expenses!H$3:H$999,Expenses!D$3:D$999))) | O9: =SUMPRODUCT((Expenses!C$3:C$999="Investments")*(Expenses!E$3:E$999="INR")*(MONTH(Expenses!A$3:A$999)=7)*(YEAR(Expenses!A$3:A$999)=2026)*(Expenses!A$3:A$999<>"")*(IF(Expenses!G$3:G$999="Yes",Expenses!H$3:H$999,Expenses!D$3:D$999))) | P9: =SUM(B9:O9) | Q9: =SUMPRODUCT((Income!D$3:D$502="INR")*(MONTH(Income!A$3:A$502)=7)*(YEAR(Income!A$3:A$502)=2026)*(Income!A$3:A$502<>"")*Income!C$3:C$502) | R9: =Q9-P9
A10: August 2026 | B10: =SUMPRODUCT((Expenses!C$3:C$999="Rent")*(Expenses!E$3:E$999="INR")*(MONTH(Expenses!A$3:A$999)=8)*(YEAR(Expenses!A$3:A$999)=2026)*(Expenses!A$3:A$999<>"")*(IF(Expenses!G$3:G$999="Yes",Expenses!H$3:H$999,Expenses!D$3:D$999))) | C10: =SUMPRODUCT((Expenses!C$3:C$999="Transport")*(Expenses!E$3:E$999="INR")*(MONTH(Expenses!A$3:A$999)=8)*(YEAR(Expenses!A$3:A$999)=2026)*(Expenses!A$3:A$999<>"")*(IF(Expenses!G$3:G$999="Yes",Expenses!H$3:H$999,Expenses!D$3:D$999))) | D10: =SUMPRODUCT((Expenses!C$3:C$999="Travel")*(Expenses!E$3:E$999="INR")*(MONTH(Expenses!A$3:A$999)=8)*(YEAR(Expenses!A$3:A$999)=2026)*(Expenses!A$3:A$999<>"")*(IF(Expenses!G$3:G$999="Yes",Expenses!H$3:H$999,Expenses!D$3:D$999))) | E10: =SUMPRODUCT((Expenses!C$3:C$999="Shopping")*(Expenses!E$3:E$999="INR")*(MONTH(Expenses!A$3:A$999)=8)*(YEAR(Expenses!A$3:A$999)=2026)*(Expenses!A$3:A$999<>"")*(IF(Expenses!G$3:G$999="Yes",Expenses!H$3:H$999,Expenses!D$3:D$999))) | F10: =SUMPRODUCT((Expenses!C$3:C$999="Electronics")*(Expenses!E$3:E$999="INR")*(MONTH(Expenses!A$3:A$999)=8)*(YEAR(Expenses!A$3:A$999)=2026)*(Expenses!A$3:A$999<>"")*(IF(Expenses!G$3:G$999="Yes",Expenses!H$3:H$999,Expenses!D$3:D$999))) | G10: =SUMPRODUCT((Expenses!C$3:C$999="Subscriptions")*(Expenses!E$3:E$999="INR")*(MONTH(Expenses!A$3:A$999)=8)*(YEAR(Expenses!A$3:A$999)=2026)*(Expenses!A$3:A$999<>"")*(IF(Expenses!G$3:G$999="Yes",Expenses!H$3:H$999,Expenses!D$3:D$999))) | H10: =SUMPRODUCT((Expenses!C$3:C$999="Bills")*(Expenses!E$3:E$999="INR")*(MONTH(Expenses!A$3:A$999)=8)*(YEAR(Expenses!A$3:A$999)=2026)*(Expenses!A$3:A$999<>"")*(IF(Expenses!G$3:G$999="Yes",Expenses!H$3:H$999,Expenses!D$3:D$999))) | I10: =SUMPRODUCT((Expenses!C$3:C$999="Entertainment")*(Expenses!E$3:E$999="INR")*(MONTH(Expenses!A$3:A$999)=8)*(YEAR(Expenses!A$3:A$999)=2026)*(Expenses!A$3:A$999<>"")*(IF(Expenses!G$3:G$999="Yes",Expenses!H$3:H$999,Expenses!D$3:D$999))) | J10: =SUMPRODUCT((Expenses!C$3:C$999="Food and Drinks")*(Expenses!E$3:E$999="INR")*(MONTH(Expenses!A$3:A$999)=8)*(YEAR(Expenses!A$3:A$999)=2026)*(Expenses!A$3:A$999<>"")*(IF(Expenses!G$3:G$999="Yes",Expenses!H$3:H$999,Expenses!D$3:D$999))) | K10: =SUMPRODUCT((Expenses!C$3:C$999="Groceries")*(Expenses!E$3:E$999="INR")*(MONTH(Expenses!A$3:A$999)=8)*(YEAR(Expenses!A$3:A$999)=2026)*(Expenses!A$3:A$999<>"")*(IF(Expenses!G$3:G$999="Yes",Expenses!H$3:H$999,Expenses!D$3:D$999))) | L10: =SUMPRODUCT((Expenses!C$3:C$999="Others")*(Expenses!E$3:E$999="INR")*(MONTH(Expenses!A$3:A$999)=8)*(YEAR(Expenses!A$3:A$999)=2026)*(Expenses!A$3:A$999<>"")*(IF(Expenses!G$3:G$999="Yes",Expenses!H$3:H$999,Expenses!D$3:D$999))) | M10: =SUMPRODUCT((Expenses!C$3:C$999="Gifts")*(Expenses!E$3:E$999="INR")*(MONTH(Expenses!A$3:A$999)=8)*(YEAR(Expenses!A$3:A$999)=2026)*(Expenses!A$3:A$999<>"")*(IF(Expenses!G$3:G$999="Yes",Expenses!H$3:H$999,Expenses!D$3:D$999))) | N10: =SUMPRODUCT((Expenses!C$3:C$999="Donations")*(Expenses!E$3:E$999="INR")*(MONTH(Expenses!A$3:A$999)=8)*(YEAR(Expenses!A$3:A$999)=2026)*(Expenses!A$3:A$999<>"")*(IF(Expenses!G$3:G$999="Yes",Expenses!H$3:H$999,Expenses!D$3:D$999))) | O10: =SUMPRODUCT((Expenses!C$3:C$999="Investments")*(Expenses!E$3:E$999="INR")*(MONTH(Expenses!A$3:A$999)=8)*(YEAR(Expenses!A$3:A$999)=2026)*(Expenses!A$3:A$999<>"")*(IF(Expenses!G$3:G$999="Yes",Expenses!H$3:H$999,Expenses!D$3:D$999))) | P10: =SUM(B10:O10) | Q10: =SUMPRODUCT((Income!D$3:D$502="INR")*(MONTH(Income!A$3:A$502)=8)*(YEAR(Income!A$3:A$502)=2026)*(Income!A$3:A$502<>"")*Income!C$3:C$502) | R10: =Q10-P10
A11: September 2026 | B11: =SUMPRODUCT((Expenses!C$3:C$999="Rent")*(Expenses!E$3:E$999="INR")*(MONTH(Expenses!A$3:A$999)=9)*(YEAR(Expenses!A$3:A$999)=2026)*(Expenses!A$3:A$999<>"")*(IF(Expenses!G$3:G$999="Yes",Expenses!H$3:H$999,Expenses!D$3:D$999))) | C11: =SUMPRODUCT((Expenses!C$3:C$999="Transport")*(Expenses!E$3:E$999="INR")*(MONTH(Expenses!A$3:A$999)=9)*(YEAR(Expenses!A$3:A$999)=2026)*(Expenses!A$3:A$999<>"")*(IF(Expenses!G$3:G$999="Yes",Expenses!H$3:H$999,Expenses!D$3:D$999))) | D11: =SUMPRODUCT((Expenses!C$3:C$999="Travel")*(Expenses!E$3:E$999="INR")*(MONTH(Expenses!A$3:A$999)=9)*(YEAR(Expenses!A$3:A$999)=2026)*(Expenses!A$3:A$999<>"")*(IF(Expenses!G$3:G$999="Yes",Expenses!H$3:H$999,Expenses!D$3:D$999))) | E11: =SUMPRODUCT((Expenses!C$3:C$999="Shopping")*(Expenses!E$3:E$999="INR")*(MONTH(Expenses!A$3:A$999)=9)*(YEAR(Expenses!A$3:A$999)=2026)*(Expenses!A$3:A$999<>"")*(IF(Expenses!G$3:G$999="Yes",Expenses!H$3:H$999,Expenses!D$3:D$999))) | F11: =SUMPRODUCT((Expenses!C$3:C$999="Electronics")*(Expenses!E$3:E$999="INR")*(MONTH(Expenses!A$3:A$999)=9)*(YEAR(Expenses!A$3:A$999)=2026)*(Expenses!A$3:A$999<>"")*(IF(Expenses!G$3:G$999="Yes",Expenses!H$3:H$999,Expenses!D$3:D$999))) | G11: =SUMPRODUCT((Expenses!C$3:C$999="Subscriptions")*(Expenses!E$3:E$999="INR")*(MONTH(Expenses!A$3:A$999)=9)*(YEAR(Expenses!A$3:A$999)=2026)*(Expenses!A$3:A$999<>"")*(IF(Expenses!G$3:G$999="Yes",Expenses!H$3:H$999,Expenses!D$3:D$999))) | H11: =SUMPRODUCT((Expenses!C$3:C$999="Bills")*(Expenses!E$3:E$999="INR")*(MONTH(Expenses!A$3:A$999)=9)*(YEAR(Expenses!A$3:A$999)=2026)*(Expenses!A$3:A$999<>"")*(IF(Expenses!G$3:G$999="Yes",Expenses!H$3:H$999,Expenses!D$3:D$999))) | I11: =SUMPRODUCT((Expenses!C$3:C$999="Entertainment")*(Expenses!E$3:E$999="INR")*(MONTH(Expenses!A$3:A$999)=9)*(YEAR(Expenses!A$3:A$999)=2026)*(Expenses!A$3:A$999<>"")*(IF(Expenses!G$3:G$999="Yes",Expenses!H$3:H$999,Expenses!D$3:D$999))) | J11: =SUMPRODUCT((Expenses!C$3:C$999="Food and Drinks")*(Expenses!E$3:E$999="INR")*(MONTH(Expenses!A$3:A$999)=9)*(YEAR(Expenses!A$3:A$999)=2026)*(Expenses!A$3:A$999<>"")*(IF(Expenses!G$3:G$999="Yes",Expenses!H$3:H$999,Expenses!D$3:D$999))) | K11: =SUMPRODUCT((Expenses!C$3:C$999="Groceries")*(Expenses!E$3:E$999="INR")*(MONTH(Expenses!A$3:A$999)=9)*(YEAR(Expenses!A$3:A$999)=2026)*(Expenses!A$3:A$999<>"")*(IF(Expenses!G$3:G$999="Yes",Expenses!H$3:H$999,Expenses!D$3:D$999))) | L11: =SUMPRODUCT((Expenses!C$3:C$999="Others")*(Expenses!E$3:E$999="INR")*(MONTH(Expenses!A$3:A$999)=9)*(YEAR(Expenses!A$3:A$999)=2026)*(Expenses!A$3:A$999<>"")*(IF(Expenses!G$3:G$999="Yes",Expenses!H$3:H$999,Expenses!D$3:D$999))) | M11: =SUMPRODUCT((Expenses!C$3:C$999="Gifts")*(Expenses!E$3:E$999="INR")*(MONTH(Expenses!A$3:A$999)=9)*(YEAR(Expenses!A$3:A$999)=2026)*(Expenses!A$3:A$999<>"")*(IF(Expenses!G$3:G$999="Yes",Expenses!H$3:H$999,Expenses!D$3:D$999))) | N11: =SUMPRODUCT((Expenses!C$3:C$999="Donations")*(Expenses!E$3:E$999="INR")*(MONTH(Expenses!A$3:A$999)=9)*(YEAR(Expenses!A$3:A$999)=2026)*(Expenses!A$3:A$999<>"")*(IF(Expenses!G$3:G$999="Yes",Expenses!H$3:H$999,Expenses!D$3:D$999))) | O11: =SUMPRODUCT((Expenses!C$3:C$999="Investments")*(Expenses!E$3:E$999="INR")*(MONTH(Expenses!A$3:A$999)=9)*(YEAR(Expenses!A$3:A$999)=2026)*(Expenses!A$3:A$999<>"")*(IF(Expenses!G$3:G$999="Yes",Expenses!H$3:H$999,Expenses!D$3:D$999))) | P11: =SUM(B11:O11) | Q11: =SUMPRODUCT((Income!D$3:D$502="INR")*(MONTH(Income!A$3:A$502)=9)*(YEAR(Income!A$3:A$502)=2026)*(Income!A$3:A$502<>"")*Income!C$3:C$502) | R11: =Q11-P11
A12: October 2026 | B12: =SUMPRODUCT((Expenses!C$3:C$999="Rent")*(Expenses!E$3:E$999="INR")*(MONTH(Expenses!A$3:A$999)=10)*(YEAR(Expenses!A$3:A$999)=2026)*(Expenses!A$3:A$999<>"")*(IF(Expenses!G$3:G$999="Yes",Expenses!H$3:H$999,Expenses!D$3:D$999))) | C12: =SUMPRODUCT((Expenses!C$3:C$999="Transport")*(Expenses!E$3:E$999="INR")*(MONTH(Expenses!A$3:A$999)=10)*(YEAR(Expenses!A$3:A$999)=2026)*(Expenses!A$3:A$999<>"")*(IF(Expenses!G$3:G$999="Yes",Expenses!H$3:H$999,Expenses!D$3:D$999))) | D12: =SUMPRODUCT((Expenses!C$3:C$999="Travel")*(Expenses!E$3:E$999="INR")*(MONTH(Expenses!A$3:A$999)=10)*(YEAR(Expenses!A$3:A$999)=2026)*(Expenses!A$3:A$999<>"")*(IF(Expenses!G$3:G$999="Yes",Expenses!H$3:H$999,Expenses!D$3:D$999))) | E12: =SUMPRODUCT((Expenses!C$3:C$999="Shopping")*(Expenses!E$3:E$999="INR")*(MONTH(Expenses!A$3:A$999)=10)*(YEAR(Expenses!A$3:A$999)=2026)*(Expenses!A$3:A$999<>"")*(IF(Expenses!G$3:G$999="Yes",Expenses!H$3:H$999,Expenses!D$3:D$999))) | F12: =SUMPRODUCT((Expenses!C$3:C$999="Electronics")*(Expenses!E$3:E$999="INR")*(MONTH(Expenses!A$3:A$999)=10)*(YEAR(Expenses!A$3:A$999)=2026)*(Expenses!A$3:A$999<>"")*(IF(Expenses!G$3:G$999="Yes",Expenses!H$3:H$999,Expenses!D$3:D$999))) | G12: =SUMPRODUCT((Expenses!C$3:C$999="Subscriptions")*(Expenses!E$3:E$999="INR")*(MONTH(Expenses!A$3:A$999)=10)*(YEAR(Expenses!A$3:A$999)=2026)*(Expenses!A$3:A$999<>"")*(IF(Expenses!G$3:G$999="Yes",Expenses!H$3:H$999,Expenses!D$3:D$999))) | H12: =SUMPRODUCT((Expenses!C$3:C$999="Bills")*(Expenses!E$3:E$999="INR")*(MONTH(Expenses!A$3:A$999)=10)*(YEAR(Expenses!A$3:A$999)=2026)*(Expenses!A$3:A$999<>"")*(IF(Expenses!G$3:G$999="Yes",Expenses!H$3:H$999,Expenses!D$3:D$999))) | I12: =SUMPRODUCT((Expenses!C$3:C$999="Entertainment")*(Expenses!E$3:E$999="INR")*(MONTH(Expenses!A$3:A$999)=10)*(YEAR(Expenses!A$3:A$999)=2026)*(Expenses!A$3:A$999<>"")*(IF(Expenses!G$3:G$999="Yes",Expenses!H$3:H$999,Expenses!D$3:D$999))) | J12: =SUMPRODUCT((Expenses!C$3:C$999="Food and Drinks")*(Expenses!E$3:E$999="INR")*(MONTH(Expenses!A$3:A$999)=10)*(YEAR(Expenses!A$3:A$999)=2026)*(Expenses!A$3:A$999<>"")*(IF(Expenses!G$3:G$999="Yes",Expenses!H$3:H$999,Expenses!D$3:D$999))) | K12: =SUMPRODUCT((Expenses!C$3:C$999="Groceries")*(Expenses!E$3:E$999="INR")*(MONTH(Expenses!A$3:A$999)=10)*(YEAR(Expenses!A$3:A$999)=2026)*(Expenses!A$3:A$999<>"")*(IF(Expenses!G$3:G$999="Yes",Expenses!H$3:H$999,Expenses!D$3:D$999))) | L12: =SUMPRODUCT((Expenses!C$3:C$999="Others")*(Expenses!E$3:E$999="INR")*(MONTH(Expenses!A$3:A$999)=10)*(YEAR(Expenses!A$3:A$999)=2026)*(Expenses!A$3:A$999<>"")*(IF(Expenses!G$3:G$999="Yes",Expenses!H$3:H$999,Expenses!D$3:D$999))) | M12: =SUMPRODUCT((Expenses!C$3:C$999="Gifts")*(Expenses!E$3:E$999="INR")*(MONTH(Expenses!A$3:A$999)=10)*(YEAR(Expenses!A$3:A$999)=2026)*(Expenses!A$3:A$999<>"")*(IF(Expenses!G$3:G$999="Yes",Expenses!H$3:H$999,Expenses!D$3:D$999))) | N12: =SUMPRODUCT((Expenses!C$3:C$999="Donations")*(Expenses!E$3:E$999="INR")*(MONTH(Expenses!A$3:A$999)=10)*(YEAR(Expenses!A$3:A$999)=2026)*(Expenses!A$3:A$999<>"")*(IF(Expenses!G$3:G$999="Yes",Expenses!H$3:H$999,Expenses!D$3:D$999))) | O12: =SUMPRODUCT((Expenses!C$3:C$999="Investments")*(Expenses!E$3:E$999="INR")*(MONTH(Expenses!A$3:A$999)=10)*(YEAR(Expenses!A$3:A$999)=2026)*(Expenses!A$3:A$999<>"")*(IF(Expenses!G$3:G$999="Yes",Expenses!H$3:H$999,Expenses!D$3:D$999))) | P12: =SUM(B12:O12) | Q12: =SUMPRODUCT((Income!D$3:D$502="INR")*(MONTH(Income!A$3:A$502)=10)*(YEAR(Income!A$3:A$502)=2026)*(Income!A$3:A$502<>"")*Income!C$3:C$502) | R12: =Q12-P12
A13: November 2026 | B13: =SUMPRODUCT((Expenses!C$3:C$999="Rent")*(Expenses!E$3:E$999="INR")*(MONTH(Expenses!A$3:A$999)=11)*(YEAR(Expenses!A$3:A$999)=2026)*(Expenses!A$3:A$999<>"")*(IF(Expenses!G$3:G$999="Yes",Expenses!H$3:H$999,Expenses!D$3:D$999))) | C13: =SUMPRODUCT((Expenses!C$3:C$999="Transport")*(Expenses!E$3:E$999="INR")*(MONTH(Expenses!A$3:A$999)=11)*(YEAR(Expenses!A$3:A$999)=2026)*(Expenses!A$3:A$999<>"")*(IF(Expenses!G$3:G$999="Yes",Expenses!H$3:H$999,Expenses!D$3:D$999))) | D13: =SUMPRODUCT((Expenses!C$3:C$999="Travel")*(Expenses!E$3:E$999="INR")*(MONTH(Expenses!A$3:A$999)=11)*(YEAR(Expenses!A$3:A$999)=2026)*(Expenses!A$3:A$999<>"")*(IF(Expenses!G$3:G$999="Yes",Expenses!H$3:H$999,Expenses!D$3:D$999))) | E13: =SUMPRODUCT((Expenses!C$3:C$999="Shopping")*(Expenses!E$3:E$999="INR")*(MONTH(Expenses!A$3:A$999)=11)*(YEAR(Expenses!A$3:A$999)=2026)*(Expenses!A$3:A$999<>"")*(IF(Expenses!G$3:G$999="Yes",Expenses!H$3:H$999,Expenses!D$3:D$999))) | F13: =SUMPRODUCT((Expenses!C$3:C$999="Electronics")*(Expenses!E$3:E$999="INR")*(MONTH(Expenses!A$3:A$999)=11)*(YEAR(Expenses!A$3:A$999)=2026)*(Expenses!A$3:A$999<>"")*(IF(Expenses!G$3:G$999="Yes",Expenses!H$3:H$999,Expenses!D$3:D$999))) | G13: =SUMPRODUCT((Expenses!C$3:C$999="Subscriptions")*(Expenses!E$3:E$999="INR")*(MONTH(Expenses!A$3:A$999)=11)*(YEAR(Expenses!A$3:A$999)=2026)*(Expenses!A$3:A$999<>"")*(IF(Expenses!G$3:G$999="Yes",Expenses!H$3:H$999,Expenses!D$3:D$999))) | H13: =SUMPRODUCT((Expenses!C$3:C$999="Bills")*(Expenses!E$3:E$999="INR")*(MONTH(Expenses!A$3:A$999)=11)*(YEAR(Expenses!A$3:A$999)=2026)*(Expenses!A$3:A$999<>"")*(IF(Expenses!G$3:G$999="Yes",Expenses!H$3:H$999,Expenses!D$3:D$999))) | I13: =SUMPRODUCT((Expenses!C$3:C$999="Entertainment")*(Expenses!E$3:E$999="INR")*(MONTH(Expenses!A$3:A$999)=11)*(YEAR(Expenses!A$3:A$999)=2026)*(Expenses!A$3:A$999<>"")*(IF(Expenses!G$3:G$999="Yes",Expenses!H$3:H$999,Expenses!D$3:D$999))) | J13: =SUMPRODUCT((Expenses!C$3:C$999="Food and Drinks")*(Expenses!E$3:E$999="INR")*(MONTH(Expenses!A$3:A$999)=11)*(YEAR(Expenses!A$3:A$999)=2026)*(Expenses!A$3:A$999<>"")*(IF(Expenses!G$3:G$999="Yes",Expenses!H$3:H$999,Expenses!D$3:D$999))) | K13: =SUMPRODUCT((Expenses!C$3:C$999="Groceries")*(Expenses!E$3:E$999="INR")*(MONTH(Expenses!A$3:A$999)=11)*(YEAR(Expenses!A$3:A$999)=2026)*(Expenses!A$3:A$999<>"")*(IF(Expenses!G$3:G$999="Yes",Expenses!H$3:H$999,Expenses!D$3:D$999))) | L13: =SUMPRODUCT((Expenses!C$3:C$999="Others")*(Expenses!E$3:E$999="INR")*(MONTH(Expenses!A$3:A$999)=11)*(YEAR(Expenses!A$3:A$999)=2026)*(Expenses!A$3:A$999<>"")*(IF(Expenses!G$3:G$999="Yes",Expenses!H$3:H$999,Expenses!D$3:D$999))) | M13: =SUMPRODUCT((Expenses!C$3:C$999="Gifts")*(Expenses!E$3:E$999="INR")*(MONTH(Expenses!A$3:A$999)=11)*(YEAR(Expenses!A$3:A$999)=2026)*(Expenses!A$3:A$999<>"")*(IF(Expenses!G$3:G$999="Yes",Expenses!H$3:H$999,Expenses!D$3:D$999))) | N13: =SUMPRODUCT((Expenses!C$3:C$999="Donations")*(Expenses!E$3:E$999="INR")*(MONTH(Expenses!A$3:A$999)=11)*(YEAR(Expenses!A$3:A$999)=2026)*(Expenses!A$3:A$999<>"")*(IF(Expenses!G$3:G$999="Yes",Expenses!H$3:H$999,Expenses!D$3:D$999))) | O13: =SUMPRODUCT((Expenses!C$3:C$999="Investments")*(Expenses!E$3:E$999="INR")*(MONTH(Expenses!A$3:A$999)=11)*(YEAR(Expenses!A$3:A$999)=2026)*(Expenses!A$3:A$999<>"")*(IF(Expenses!G$3:G$999="Yes",Expenses!H$3:H$999,Expenses!D$3:D$999))) | P13: =SUM(B13:O13) | Q13: =SUMPRODUCT((Income!D$3:D$502="INR")*(MONTH(Income!A$3:A$502)=11)*(YEAR(Income!A$3:A$502)=2026)*(Income!A$3:A$502<>"")*Income!C$3:C$502) | R13: =Q13-P13
A14: December 2026 | B14: =SUMPRODUCT((Expenses!C$3:C$999="Rent")*(Expenses!E$3:E$999="INR")*(MONTH(Expenses!A$3:A$999)=12)*(YEAR(Expenses!A$3:A$999)=2026)*(Expenses!A$3:A$999<>"")*(IF(Expenses!G$3:G$999="Yes",Expenses!H$3:H$999,Expenses!D$3:D$999))) | C14: =SUMPRODUCT((Expenses!C$3:C$999="Transport")*(Expenses!E$3:E$999="INR")*(MONTH(Expenses!A$3:A$999)=12)*(YEAR(Expenses!A$3:A$999)=2026)*(Expenses!A$3:A$999<>"")*(IF(Expenses!G$3:G$999="Yes",Expenses!H$3:H$999,Expenses!D$3:D$999))) | D14: =SUMPRODUCT((Expenses!C$3:C$999="Travel")*(Expenses!E$3:E$999="INR")*(MONTH(Expenses!A$3:A$999)=12)*(YEAR(Expenses!A$3:A$999)=2026)*(Expenses!A$3:A$999<>"")*(IF(Expenses!G$3:G$999="Yes",Expenses!H$3:H$999,Expenses!D$3:D$999))) | E14: =SUMPRODUCT((Expenses!C$3:C$999="Shopping")*(Expenses!E$3:E$999="INR")*(MONTH(Expenses!A$3:A$999)=12)*(YEAR(Expenses!A$3:A$999)=2026)*(Expenses!A$3:A$999<>"")*(IF(Expenses!G$3:G$999="Yes",Expenses!H$3:H$999,Expenses!D$3:D$999))) | F14: =SUMPRODUCT((Expenses!C$3:C$999="Electronics")*(Expenses!E$3:E$999="INR")*(MONTH(Expenses!A$3:A$999)=12)*(YEAR(Expenses!A$3:A$999)=2026)*(Expenses!A$3:A$999<>"")*(IF(Expenses!G$3:G$999="Yes",Expenses!H$3:H$999,Expenses!D$3:D$999))) | G14: =SUMPRODUCT((Expenses!C$3:C$999="Subscriptions")*(Expenses!E$3:E$999="INR")*(MONTH(Expenses!A$3:A$999)=12)*(YEAR(Expenses!A$3:A$999)=2026)*(Expenses!A$3:A$999<>"")*(IF(Expenses!G$3:G$999="Yes",Expenses!H$3:H$999,Expenses!D$3:D$999))) | H14: =SUMPRODUCT((Expenses!C$3:C$999="Bills")*(Expenses!E$3:E$999="INR")*(MONTH(Expenses!A$3:A$999)=12)*(YEAR(Expenses!A$3:A$999)=2026)*(Expenses!A$3:A$999<>"")*(IF(Expenses!G$3:G$999="Yes",Expenses!H$3:H$999,Expenses!D$3:D$999))) | I14: =SUMPRODUCT((Expenses!C$3:C$999="Entertainment")*(Expenses!E$3:E$999="INR")*(MONTH(Expenses!A$3:A$999)=12)*(YEAR(Expenses!A$3:A$999)=2026)*(Expenses!A$3:A$999<>"")*(IF(Expenses!G$3:G$999="Yes",Expenses!H$3:H$999,Expenses!D$3:D$999))) | J14: =SUMPRODUCT((Expenses!C$3:C$999="Food and Drinks")*(Expenses!E$3:E$999="INR")*(MONTH(Expenses!A$3:A$999)=12)*(YEAR(Expenses!A$3:A$999)=2026)*(Expenses!A$3:A$999<>"")*(IF(Expenses!G$3:G$999="Yes",Expenses!H$3:H$999,Expenses!D$3:D$999))) | K14: =SUMPRODUCT((Expenses!C$3:C$999="Groceries")*(Expenses!E$3:E$999="INR")*(MONTH(Expenses!A$3:A$999)=12)*(YEAR(Expenses!A$3:A$999)=2026)*(Expenses!A$3:A$999<>"")*(IF(Expenses!G$3:G$999="Yes",Expenses!H$3:H$999,Expenses!D$3:D$999))) | L14: =SUMPRODUCT((Expenses!C$3:C$999="Others")*(Expenses!E$3:E$999="INR")*(MONTH(Expenses!A$3:A$999)=12)*(YEAR(Expenses!A$3:A$999)=2026)*(Expenses!A$3:A$999<>"")*(IF(Expenses!G$3:G$999="Yes",Expenses!H$3:H$999,Expenses!D$3:D$999))) | M14: =SUMPRODUCT((Expenses!C$3:C$999="Gifts")*(Expenses!E$3:E$999="INR")*(MONTH(Expenses!A$3:A$999)=12)*(YEAR(Expenses!A$3:A$999)=2026)*(Expenses!A$3:A$999<>"")*(IF(Expenses!G$3:G$999="Yes",Expenses!H$3:H$999,Expenses!D$3:D$999))) | N14: =SUMPRODUCT((Expenses!C$3:C$999="Donations")*(Expenses!E$3:E$999="INR")*(MONTH(Expenses!A$3:A$999)=12)*(YEAR(Expenses!A$3:A$999)=2026)*(Expenses!A$3:A$999<>"")*(IF(Expenses!G$3:G$999="Yes",Expenses!H$3:H$999,Expenses!D$3:D$999))) | O14: =SUMPRODUCT((Expenses!C$3:C$999="Investments")*(Expenses!E$3:E$999="INR")*(MONTH(Expenses!A$3:A$999)=12)*(YEAR(Expenses!A$3:A$999)=2026)*(Expenses!A$3:A$999<>"")*(IF(Expenses!G$3:G$999="Yes",Expenses!H$3:H$999,Expenses!D$3:D$999))) | P14: =SUM(B14:O14) | Q14: =SUMPRODUCT((Income!D$3:D$502="INR")*(MONTH(Income!A$3:A$502)=12)*(YEAR(Income!A$3:A$502)=2026)*(Income!A$3:A$502<>"")*Income!C$3:C$502) | R14: =Q14-P14
A16: Total | B16: =SUM(B3:B14) | C16: =SUM(C3:C14) | D16: =SUM(D3:D14) | E16: =SUM(E3:E14) | F16: =SUM(F3:F14) | G16: =SUM(G3:G14) | H16: =SUM(H3:H14) | I16: =SUM(I3:I14) | ... R16: =SUM(R3:R14)
A18: Monthly Budget | P18: =SUM(B18:O18)
A21: Yearly Breakdown

Sheet Cashflow GBP
A1: CASHFLOW (GBP) - Daily Running Balance
A2: Week | B2: Date | C2: Starting Balance | D2: Day Total +/- | E2: Income (+) | F2: Expenses (-) | G2: Ending Balance | H2: Notes
A3: 1 | B3: 46023 | C3: 2474.47 | D3: =E3-F3 | E3: =SUMPRODUCT((Income!D$3:D$502="GBP")*(Income!A$3:A$502=B3)*(Income!A$3:A$502<>"")*Income!C$3:C$502) | F3: =SUMPRODUCT((Expenses!E$3:E$999="GBP")*(Expenses!A$3:A$999=B3)*(Expenses!A$3:A$999<>"")*Expenses!D$3:D$999) | G3: =C3+D3
A4: 1 | B4: 46024 | C4: =G3 | D4: =E4-F4 | E4: =SUMPRODUCT((Income!D$3:D$502="GBP")*(Income!A$3:A$502=B4)*(Income!A$3:A$502<>"")*Income!C$3:C$502) | F4: =SUMPRODUCT((Expenses!E$3:E$999="GBP")*(Expenses!A$3:A$999=B4)*(Expenses!A$3:A$999<>"")*Expenses!D$3:D$999) | G4: =C4+D4
A5: 1 | B5: 46025 | C5: =G4 | D5: =E5-F5 | E5: =SUMPRODUCT((Income!D$3:D$502="GBP")*(Income!A$3:A$502=B5)*(Income!A$3:A$502<>"")*Income!C$3:C$502) | F5: =SUMPRODUCT((Expenses!E$3:E$999="GBP")*(Expenses!A$3:A$999=B5)*(Expenses!A$3:A$999<>"")*Expenses!D$3:D$999) | G5: =C5+D5
A6: 1 | B6: 46026 | C6: =G5 | D6: =E6-F6 | E6: =SUMPRODUCT((Income!D$3:D$502="GBP")*(Income!A$3:A$502=B6)*(Income!A$3:A$502<>"")*Income!C$3:C$502) | F6: =SUMPRODUCT((Expenses!E$3:E$999="GBP")*(Expenses!A$3:A$999=B6)*(Expenses!A$3:A$999<>"")*Expenses!D$3:D$999) | G6: =C6+D6
A7: 2 | B7: 46027 | C7: =G6 | D7: =E7-F7 | E7: =SUMPRODUCT((Income!D$3:D$502="GBP")*(Income!A$3:A$502=B7)*(Income!A$3:A$502<>"")*Income!C$3:C$502) | F7: =SUMPRODUCT((Expenses!E$3:E$999="GBP")*(Expenses!A$3:A$999=B7)*(Expenses!A$3:A$999<>"")*Expenses!D$3:D$999) | G7: =C7+D7
A8: 2 | B8: 46028 | C8: =G7 | D8: =E8-F8 | E8: =SUMPRODUCT((Income!D$3:D$502="GBP")*(Income!A$3:A$502=B8)*(Income!A$3:A$502<>"")*Income!C$3:C$502) | F8: =SUMPRODUCT((Expenses!E$3:E$999="GBP")*(Expenses!A$3:A$999=B8)*(Expenses!A$3:A$999<>"")*Expenses!D$3:D$999) | G8: =C8+D8
A9: 2 | B9: 46029 | C9: =G8 | D9: =E9-F9 | E9: =SUMPRODUCT((Income!D$3:D$502="GBP")*(Income!A$3:A$502=B9)*(Income!A$3:A$502<>"")*Income!C$3:C$502) | F9: =SUMPRODUCT((Expenses!E$3:E$999="GBP")*(Expenses!A$3:A$999=B9)*(Expenses!A$3:A$999<>"")*Expenses!D$3:D$999) | G9: =C9+D9
A10: 2 | B10: 46030 | C10: =G9 | D10: =E10-F10 | E10: =SUMPRODUCT((Income!D$3:D$502="GBP")*(Income!A$3:A$502=B10)*(Income!A$3:A$502<>"")*Income!C$3:C$502) | F10: =SUMPRODUCT((Expenses!E$3:E$999="GBP")*(Expenses!A$3:A$999=B10)*(Expenses!A$3:A$999<>"")*Expenses!D$3:D$999) | G10: =C10+D10
A11: 2 | B11: 46031 | C11: =G10 | D11: =E11-F11 | E11: =SUMPRODUCT((Income!D$3:D$502="GBP")*(Income!A$3:A$502=B11)*(Income!A$3:A$502<>"")*Income!C$3:C$502) | F11: =SUMPRODUCT((Expenses!E$3:E$999="GBP")*(Expenses!A$3:A$999=B11)*(Expenses!A$3:A$999<>"")*Expenses!D$3:D$999) | G11: =C11+D11
A12: 2 | B12: 46032 | C12: =G11 | D12: =E12-F12 | E12: =SUMPRODUCT((Income!D$3:D$502="GBP")*(Income!A$3:A$502=B12)*(Income!A$3:A$502<>"")*Income!C$3:C$502) | F12: =SUMPRODUCT((Expenses!E$3:E$999="GBP")*(Expenses!A$3:A$999=B12)*(Expenses!A$3:A$999<>"")*Expenses!D$3:D$999) | G12: =C12+D12
A13: 2 | B13: 46033 | C13: =G12 | D13: =E13-F13 | E13: =SUMPRODUCT((Income!D$3:D$502="GBP")*(Income!A$3:A$502=B13)*(Income!A$3:A$502<>"")*Income!C$3:C$502) | F13: =SUMPRODUCT((Expenses!E$3:E$999="GBP")*(Expenses!A$3:A$999=B13)*(Expenses!A$3:A$999<>"")*Expenses!D$3:D$999) | G13: =C13+D13
A14: 3 | B14: 46034 | C14: =G13 | D14: =E14-F14 | E14: =SUMPRODUCT((Income!D$3:D$502="GBP")*(Income!A$3:A$502=B14)*(Income!A$3:A$502<>"")*Income!C$3:C$502) | F14: =SUMPRODUCT((Expenses!E$3:E$999="GBP")*(Expenses!A$3:A$999=B14)*(Expenses!A$3:A$999<>"")*Expenses!D$3:D$999) | G14: =C14+D14
A15: 3 | B15: 46035 | C15: =G14 | D15: =E15-F15 | E15: =SUMPRODUCT((Income!D$3:D$502="GBP")*(Income!A$3:A$502=B15)*(Income!A$3:A$502<>"")*Income!C$3:C$502) | F15: =SUMPRODUCT((Expenses!E$3:E$999="GBP")*(Expenses!A$3:A$999=B15)*(Expenses!A$3:A$999<>"")*Expenses!D$3:D$999) | G15: =C15+D15
... A367: 53 | B367: 46387 | C367: =G366 | D367: =E367-F367 | E367: =SUMPRODUCT((Income!D$3:D$502="GBP")*(Income!A$3:A$502=B367)*(Income!A$3:A$502<>"")*Income!C$3:C$502) | F367: =SUMPRODUCT((Expenses!E$3:E$999="GBP")*(Expenses!A$3:A$999=B367)*(Expenses!A$3:A$999<>"")*Expenses!D$3:D$999) | G367: =C367+D367

Sheet Cashflow INR
A1: CASHFLOW (INR) - Daily Running Balance
A2: Week | B2: Date | C2: Starting Balance | D2: Day Total +/- | E2: Income (+) | F2: Expenses (-) | G2: Ending Balance | H2: Notes
A3: 1 | B3: 46023 | D3: =E3-F3 | E3: =SUMPRODUCT((Income!D$3:D$502="INR")*(Income!A$3:A$502=B3)*(Income!A$3:A$502<>"")*Income!C$3:C$502) | F3: =SUMPRODUCT((Expenses!E$3:E$999="INR")*(Expenses!A$3:A$999=B3)*(Expenses!A$3:A$999<>"")*Expenses!D$3:D$999) | G3: =C3+D3
A4: 1 | B4: 46024 | C4: =G3 | D4: =E4-F4 | E4: =SUMPRODUCT((Income!D$3:D$502="INR")*(Income!A$3:A$502=B4)*(Income!A$3:A$502<>"")*Income!C$3:C$502) | F4: =SUMPRODUCT((Expenses!E$3:E$999="INR")*(Expenses!A$3:A$999=B4)*(Expenses!A$3:A$999<>"")*Expenses!D$3:D$999) | G4: =C4+D4
A5: 1 | B5: 46025 | C5: =G4 | D5: =E5-F5 | E5: =SUMPRODUCT((Income!D$3:D$502="INR")*(Income!A$3:A$502=B5)*(Income!A$3:A$502<>"")*Income!C$3:C$502) | F5: =SUMPRODUCT((Expenses!E$3:E$999="INR")*(Expenses!A$3:A$999=B5)*(Expenses!A$3:A$999<>"")*Expenses!D$3:D$999) | G5: =C5+D5
A6: 1 | B6: 46026 | C6: =G5 | D6: =E6-F6 | E6: =SUMPRODUCT((Income!D$3:D$502="INR")*(Income!A$3:A$502=B6)*(Income!A$3:A$502<>"")*Income!C$3:C$502) | F6: =SUMPRODUCT((Expenses!E$3:E$999="INR")*(Expenses!A$3:A$999=B6)*(Expenses!A$3:A$999<>"")*Expenses!D$3:D$999) | G6: =C6+D6
A7: 2 | B7: 46027 | C7: =G6 | D7: =E7-F7 | E7: =SUMPRODUCT((Income!D$3:D$502="INR")*(Income!A$3:A$502=B7)*(Income!A$3:A$502<>"")*Income!C$3:C$502) | F7: =SUMPRODUCT((Expenses!E$3:E$999="INR")*(Expenses!A$3:A$999=B7)*(Expenses!A$3:A$999<>"")*Expenses!D$3:D$999) | G7: =C7+D7
A8: 2 | B8: 46028 | C8: =G7 | D8: =E8-F8 | E8: =SUMPRODUCT((Income!D$3:D$502="INR")*(Income!A$3:A$502=B8)*(Income!A$3:A$502<>"")*Income!C$3:C$502) | F8: =SUMPRODUCT((Expenses!E$3:E$999="INR")*(Expenses!A$3:A$999=B8)*(Expenses!A$3:A$999<>"")*Expenses!D$3:D$999) | G8: =C8+D8
A9: 2 | B9: 46029 | C9: =G8 | D9: =E9-F9 | E9: =SUMPRODUCT((Income!D$3:D$502="INR")*(Income!A$3:A$502=B9)*(Income!A$3:A$502<>"")*Income!C$3:C$502) | F9: =SUMPRODUCT((Expenses!E$3:E$999="INR")*(Expenses!A$3:A$999=B9)*(Expenses!A$3:A$999<>"")*Expenses!D$3:D$999) | G9: =C9+D9
A10: 2 | B10: 46030 | C10: =G9 | D10: =E10-F10 | E10: =SUMPRODUCT((Income!D$3:D$502="INR")*(Income!A$3:A$502=B10)*(Income!A$3:A$502<>"")*Income!C$3:C$502) | F10: =SUMPRODUCT((Expenses!E$3:E$999="INR")*(Expenses!A$3:A$999=B10)*(Expenses!A$3:A$999<>"")*Expenses!D$3:D$999) | G10: =C10+D10
A11: 2 | B11: 46031 | C11: =G10 | D11: =E11-F11 | E11: =SUMPRODUCT((Income!D$3:D$502="INR")*(Income!A$3:A$502=B11)*(Income!A$3:A$502<>"")*Income!C$3:C$502) | F11: =SUMPRODUCT((Expenses!E$3:E$999="INR")*(Expenses!A$3:A$999=B11)*(Expenses!A$3:A$999<>"")*Expenses!D$3:D$999) | G11: =C11+D11
A12: 2 | B12: 46032 | C12: =G11 | D12: =E12-F12 | E12: =SUMPRODUCT((Income!D$3:D$502="INR")*(Income!A$3:A$502=B12)*(Income!A$3:A$502<>"")*Income!C$3:C$502) | F12: =SUMPRODUCT((Expenses!E$3:E$999="INR")*(Expenses!A$3:A$999=B12)*(Expenses!A$3:A$999<>"")*Expenses!D$3:D$999) | G12: =C12+D12
A13: 2 | B13: 46033 | C13: =G12 | D13: =E13-F13 | E13: =SUMPRODUCT((Income!D$3:D$502="INR")*(Income!A$3:A$502=B13)*(Income!A$3:A$502<>"")*Income!C$3:C$502) | F13: =SUMPRODUCT((Expenses!E$3:E$999="INR")*(Expenses!A$3:A$999=B13)*(Expenses!A$3:A$999<>"")*Expenses!D$3:D$999) | G13: =C13+D13
A14: 3 | B14: 46034 | C14: =G13 | D14: =E14-F14 | E14: =SUMPRODUCT((Income!D$3:D$502="INR")*(Income!A$3:A$502=B14)*(Income!A$3:A$502<>"")*Income!C$3:C$502) | F14: =SUMPRODUCT((Expenses!E$3:E$999="INR")*(Expenses!A$3:A$999=B14)*(Expenses!A$3:A$999<>"")*Expenses!D$3:D$999) | G14: =C14+D14
A15: 3 | B15: 46035 | C15: =G14 | D15: =E15-F15 | E15: =SUMPRODUCT((Income!D$3:D$502="INR")*(Income!A$3:A$502=B15)*(Income!A$3:A$502<>"")*Income!C$3:C$502) | F15: =SUMPRODUCT((Expenses!E$3:E$999="INR")*(Expenses!A$3:A$999=B15)*(Expenses!A$3:A$999<>"")*Expenses!D$3:D$999) | G15: =C15+D15
... A367: 53 | B367: 46387 | C367: =G366 | D367: =E367-F367 | E367: =SUMPRODUCT((Income!D$3:D$502="INR")*(Income!A$3:A$502=B367)*(Income!A$3:A$502<>"")*Income!C$3:C$502) | F367: =SUMPRODUCT((Expenses!E$3:E$999="INR")*(Expenses!A$3:A$999=B367)*(Expenses!A$3:A$999<>"")*Expenses!D$3:D$999) | G367: =C367+D367

Sheet Itemised GBP
A1: ITEMISED WEEKLY VIEW (GBP)
A2: Week Commencing | B2: Week | C2: Monday | E2: Tuesday | G2: Wednesday | I2: Thursday | K2: Friday | M2: Saturday | O2: Sunday | Q2: Week No | R2: Total for Week
C3: Amount | D3: Description | E3: Amount | F3: Description | G3: Amount | H3: Description | I3: Amount | J3: Description | K3: Amount | L3: Description | M3: Amount | N3: Description | O3: Amount | P3: Description
A4: 46020 | B4: 1 | C4: {=IF(IFERROR(-INDEX(Expenses!D$3:D$999,SMALL(IF((Expenses!E$3:E$999="GBP")*(Expenses!A$3:A$999=DATE(2025,12,29)),ROW(Expenses!A$3:A$999)-2),1)),0)+IFERROR(INDEX(Income!C$3:C$502,SMALL(IF((Income!D$3:D$502="GBP")*(Income!A$3:A$502=DATE(2025,12,29)),ROW(Income!A$3:A$502)-2),1)),0)=0,"",IFERROR(-INDEX(Expenses!D$3:D$999,SMALL(IF((Expenses!E$3:E$999="GBP")*(Expenses!A$3:A$999=DATE(2025,12,29)),ROW(Expenses!A$3:A$999)-2),1)),0)+IFERROR(INDEX(Income!C$3:C$502,SMALL(IF((Income!D$3:D$502="GBP")*(Income!A$3:A$502=DATE(2025,12,29)),ROW(Income!A$3:A$502)-2),1)),0))} | D4: {=IF(IFERROR(INDEX(Expenses!B$3:B$999,SMALL(IF((Expenses!E$3:E$999="GBP")*(Expenses!A$3:A$999=DATE(2025,12,29)),ROW(Expenses!A$3:A$999)-2),1)),"")<>"",IFERROR(INDEX(Expenses!B$3:B$999,SMALL(IF((Expenses!E$3:E$999="GBP")*(Expenses!A$3:A$999=DATE(2025,12,29)),ROW(Expenses!A$3:A$999)-2),1)),""),IF(IFERROR(INDEX(Income!B$3:B$502,SMALL(IF((Income!D$3:D$502="GBP")*(Income!A$3:A$502=DATE(2025,12,29)),ROW(Income!A$3:A$502)-2),1)),"")<>"",IFERROR(INDEX(Income!B$3:B$502,SMALL(IF((Income!D$3:D$502="GBP")*(Income!A$3:A$502=DATE(2025,12,29)),ROW(Income!A$3:A$502)-2),1)),""),""))} | E4: {=IF(IFERROR(-INDEX(Expenses!D$3:D$999,SMALL(IF((Expenses!E$3:E$999="GBP")*(Expenses!A$3:A$999=DATE(2025,12,30)),ROW(Expenses!A$3:A$999)-2),1)),0)+IFERROR(INDEX(Income!C$3:C$502,SMALL(IF((Income!D$3:D$502="GBP")*(Income!A$3:A$502=DATE(2025,12,30)),ROW(Income!A$3:A$502)-2),1)),0)=0,"",IFERROR(-INDEX(Expenses!D$3:D$999,SMALL(IF((Expenses!E$3:E$999="GBP")*(Expenses!A$3:A$999=DATE(2025,12,30)),ROW(Expenses!A$3:A$999)-2),1)),0)+IFERROR(INDEX(Income!C$3:C$502,SMALL(IF((Income!D$3:D$502="GBP")*(Income!A$3:A$502=DATE(2025,12,30)),ROW(Income!A$3:A$502)-2),1)),0))} | F4: {=IF(IFERROR(INDEX(Expenses!B$3:B$999,SMALL(IF((Expenses!E$3:E$999="GBP")*(Expenses!A$3:A$999=DATE(2025,12,30)),ROW(Expenses!A$3:A$999)-2),1)),"")<>"",IFERROR(INDEX(Expenses!B$3:B$999,SMALL(IF((Expenses!E$3:E$999="GBP")*(Expenses!A$3:A$999=DATE(2025,12,30)),ROW(Expenses!A$3:A$999)-2),1)),""),IF(IFERROR(INDEX(Income!B$3:B$502,SMALL(IF((Income!D$3:D$502="GBP")*(Income!A$3:A$502=DATE(2025,12,30)),ROW(Income!A$3:A$502)-2),1)),"")<>"",IFERROR(INDEX(Income!B$3:B$502,SMALL(IF((Income!D$3:D$502="GBP")*(Income!A$3:A$502=DATE(2025,12,30)),ROW(Income!A$3:A$502)-2),1)),""),""))} | G4: {=IF(IFERROR(-INDEX(Expenses!D$3:D$999,SMALL(IF((Expenses!E$3:E$999="GBP")*(Expenses!A$3:A$999=DATE(2025,12,31)),ROW(Expenses!A$3:A$999)-2),1)),0)+IFERROR(INDEX(Income!C$3:C$502,SMALL(IF((Income!D$3:D$502="GBP")*(Income!A$3:A$502=DATE(2025,12,31)),ROW(Income!A$3:A$502)-2),1)),0)=0,"",IFERROR(-INDEX(Expenses!D$3:D$999,SMALL(IF((Expenses!E$3:E$999="GBP")*(Expenses!A$3:A$999=DATE(2025,12,31)),ROW(Expenses!A$3:A$999)-2),1)),0)+IFERROR(INDEX(Income!C$3:C$502,SMALL(IF((Income!D$3:D$502="GBP")*(Income!A$3:A$502=DATE(2025,12,31)),ROW(Income!A$3:A$502)-2),1)),0))} | H4: {=IF(IFERROR(INDEX(Expenses!B$3:B$999,SMALL(IF((Expenses!E$3:E$999="GBP")*(Expenses!A$3:A$999=DATE(2025,12,31)),ROW(Expenses!A$3:A$999)-2),1)),"")<>"",IFERROR(INDEX(Expenses!B$3:B$999,SMALL(IF((Expenses!E$3:E$999="GBP")*(Expenses!A$3:A$999=DATE(2025,12,31)),ROW(Expenses!A$3:A$999)-2),1)),""),IF(IFERROR(INDEX(Income!B$3:B$502,SMALL(IF((Income!D$3:D$502="GBP")*(Income!A$3:A$502=DATE(2025,12,31)),ROW(Income!A$3:A$502)-2),1)),"")<>"",IFERROR(INDEX(Income!B$3:B$502,SMALL(IF((Income!D$3:D$502="GBP")*(Income!A$3:A$502=DATE(2025,12,31)),ROW(Income!A$3:A$502)-2),1)),""),""))} | I4: {=IF(IFERROR(-INDEX(Expenses!D$3:D$999,SMALL(IF((Expenses!E$3:E$999="GBP")*(Expenses!A$3:A$999=DATE(2026,1,1)),ROW(Expenses!A$3:A$999)-2),1)),0)+IFERROR(INDEX(Income!C$3:C$502,SMALL(IF((Income!D$3:D$502="GBP")*(Income!A$3:A$502=DATE(2026,1,1)),ROW(Income!A$3:A$502)-2),1)),0)=0,"",IFERROR(-INDEX(Expenses!D$3:D$999,SMALL(IF((Expenses!E$3:E$999="GBP")*(Expenses!A$3:A$999=DATE(2026,1,1)),ROW(Expenses!A$3:A$999)-2),1)),0)+IFERROR(INDEX(Income!C$3:C$502,SMALL(IF((Income!D$3:D$502="GBP")*(Income!A$3:A$502=DATE(2026,1,1)),ROW(Income!A$3:A$502)-2),1)),0))} | J4: {=IF(IFERROR(INDEX(Expenses!B$3:B$999,SMALL(IF((Expenses!E$3:E$999="GBP")*(Expenses!A$3:A$999=DATE(2026,1,1)),ROW(Expenses!A$3:A$999)-2),1)),"")<>"",IFERROR(INDEX(Expenses!B$3:B$999,SMALL(IF((Expenses!E$3:E$999="GBP")*(Expenses!A$3:A$999=DATE(2026,1,1)),ROW(Expenses!A$3:A$999)-2),1)),""),IF(IFERROR(INDEX(Income!B$3:B$502,SMALL(IF((Income!D$3:D$502="GBP")*(Income!A$3:A$502=DATE(2026,1,1)),ROW(Income!A$3:A$502)-2),1)),"")<>"",IFERROR(INDEX(Income!B$3:B$502,SMALL(IF((Income!D$3:D$502="GBP")*(Income!A$3:A$502=DATE(2026,1,1)),ROW(Income!A$3:A$502)-2),1)),""),""))} | K4: {=IF(IFERROR(-INDEX(Expenses!D$3:D$999,SMALL(IF((Expenses!E$3:E$999="GBP")*(Expenses!A$3:A$999=DATE(2026,1,2)),ROW(Expenses!A$3:A$999)-2),1)),0)+IFERROR(INDEX(Income!C$3:C$502,SMALL(IF((Income!D$3:D$502="GBP")*(Income!A$3:A$502=DATE(2026,1,2)),ROW(Income!A$3:A$502)-2),1)),0)=0,"",IFERROR(-INDEX(Expenses!D$3:D$999,SMALL(IF((Expenses!E$3:E$999="GBP")*(Expenses!A$3:A$999=DATE(2026,1,2)),ROW(Expenses!A$3:A$999)-2),1)),0)+IFERROR(INDEX(Income!C$3:C$502,SMALL(IF((Income!D$3:D$502="GBP")*(Income!A$3:A$502=DATE(2026,1,2)),ROW(Income!A$3:A$502)-2),1)),0))} | L4: {=IF(IFERROR(INDEX(Expenses!B$3:B$999,SMALL(IF((Expenses!E$3:E$999="GBP")*(Expenses!A$3:A$999=DATE(2026,1,2)),ROW(Expenses!A$3:A$999)-2),1)),"")<>"",IFERROR(INDEX(Expenses!B$3:B$999,SMALL(IF((Expenses!E$3:E$999="GBP")*(Expenses!A$3:A$999=DATE(2026,1,2)),ROW(Expenses!A$3:A$999)-2),1)),""),IF(IFERROR(INDEX(Income!B$3:B$502,SMALL(IF((Income!D$3:D$502="GBP")*(Income!A$3:A$502=DATE(2026,1,2)),ROW(Income!A$3:A$502)-2),1)),"")<>"",IFERROR(INDEX(Income!B$3:B$502,SMALL(IF((Income!D$3:D$502="GBP")*(Income!A$3:A$502=DATE(2026,1,2)),ROW(Income!A$3:A$502)-2),1)),""),""))} | M4: {=IF(IFERROR(-INDEX(Expenses!D$3:D$999,SMALL(IF((Expenses!E$3:E$999="GBP")*(Expenses!A$3:A$999=DATE(2026,1,3)),ROW(Expenses!A$3:A$999)-2),1)),0)+IFERROR(INDEX(Income!C$3:C$502,SMALL(IF((Income!D$3:D$502="GBP")*(Income!A$3:A$502=DATE(2026,1,3)),ROW(Income!A$3:A$502)-2),1)),0)=0,"",IFERROR(-INDEX(Expenses!D$3:D$999,SMALL(IF((Expenses!E$3:E$999="GBP")*(Expenses!A$3:A$999=DATE(2026,1,3)),ROW(Expenses!A$3:A$999)-2),1)),0)+IFERROR(INDEX(Income!C$3:C$502,SMALL(IF((Income!D$3:D$502="GBP")*(Income!A$3:A$502=DATE(2026,1,3)),ROW(Income!A$3:A$502)-2),1)),0))} | N4: {=IF(IFERROR(INDEX(Expenses!B$3:B$999,SMALL(IF((Expenses!E$3:E$999="GBP")*(Expenses!A$3:A$999=DATE(2026,1,3)),ROW(Expenses!A$3:A$999)-2),1)),"")<>"",IFERROR(INDEX(Expenses!B$3:B$999,SMALL(IF((Expenses!E$3:E$999="GBP")*(Expenses!A$3:A$999=DATE(2026,1,3)),ROW(Expenses!A$3:A$999)-2),1)),""),IF(IFERROR(INDEX(Income!B$3:B$502,SMALL(IF((Income!D$3:D$502="GBP")*(Income!A$3:A$502=DATE(2026,1,3)),ROW(Income!A$3:A$502)-2),1)),"")<>"",IFERROR(INDEX(Income!B$3:B$502,SMALL(IF((Income!D$3:D$502="GBP")*(Income!A$3:A$502=DATE(2026,1,3)),ROW(Income!A$3:A$502)-2),1)),""),""))} | O4: {=IF(IFERROR(-INDEX(Expenses!D$3:D$999,SMALL(IF((Expenses!E$3:E$999="GBP")*(Expenses!A$3:A$999=DATE(2026,1,4)),ROW(Expenses!A$3:A$999)-2),1)),0)+IFERROR(INDEX(Income!C$3:C$502,SMALL(IF((Income!D$3:D$502="GBP")*(Income!A$3:A$502=DATE(2026,1,4)),ROW(Income!A$3:A$502)-2),1)),0)=0,"",IFERROR(-INDEX(Expenses!D$3:D$999,SMALL(IF((Expenses!E$3:E$999="GBP")*(Expenses!A$3:A$999=DATE(2026,1,4)),ROW(Expenses!A$3:A$999)-2),1)),0)+IFERROR(INDEX(Income!C$3:C$502,SMALL(IF((Income!D$3:D$502="GBP")*(Income!A$3:A$502=DATE(2026,1,4)),ROW(Income!A$3:A$502)-2),1)),0))} | P4: {=IF(IFERROR(INDEX(Expenses!B$3:B$999,SMALL(IF((Expenses!E$3:E$999="GBP")*(Expenses!A$3:A$999=DATE(2026,1,4)),ROW(Expenses!A$3:A$999)-2),1)),"")<>"",IFERROR(INDEX(Expenses!B$3:B$999,SMALL(IF((Expenses!E$3:E$999="GBP")*(Expenses!A$3:A$999=DATE(2026,1,4)),ROW(Expenses!A$3:A$999)-2),1)),""),IF(IFERROR(INDEX(Income!B$3:B$502,SMALL(IF((Income!D$3:D$502="GBP")*(Income!A$3:A$502=DATE(2026,1,4)),ROW(Income!A$3:A$502)-2),1)),"")<>"",IFERROR(INDEX(Income!B$3:B$502,SMALL(IF((Income!D$3:D$502="GBP")*(Income!A$3:A$502=DATE(2026,1,4)),ROW(Income!A$3:A$502)-2),1)),""),""))} | Q4: 1 | R4: =SUM(C4:C8)+SUM(E4:E8)+SUM(G4:G8)+SUM(I4:I8)+SUM(K4:K8)+SUM(M4:M8)+SUM(O4:O8)
C5: {=IF(IFERROR(-INDEX(Expenses!D$3:D$999,SMALL(IF((Expenses!E$3:E$999="GBP")*(Expenses!A$3:A$999=DATE(2025,12,29)),ROW(Expenses!A$3:A$999)-2),2)),0)+IFERROR(INDEX(Income!C$3:C$502,SMALL(IF((Income!D$3:D$502="GBP")*(Income!A$3:A$502=DATE(2025,12,29)),ROW(Income!A$3:A$502)-2),2)),0)=0,"",IFERROR(-INDEX(Expenses!D$3:D$999,SMALL(IF((Expenses!E$3:E$999="GBP")*(Expenses!A$3:A$999=DATE(2025,12,29)),ROW(Expenses!A$3:A$999)-2),2)),0)+IFERROR(INDEX(Income!C$3:C$502,SMALL(IF((Income!D$3:D$502="GBP")*(Income!A$3:A$502=DATE(2025,12,29)),ROW(Income!A$3:A$502)-2),2)),0))} | D5: {=IF(IFERROR(INDEX(Expenses!B$3:B$999,SMALL(IF((Expenses!E$3:E$999="GBP")*(Expenses!A$3:A$999=DATE(2025,12,29)),ROW(Expenses!A$3:A$999)-2),2)),"")<>"",IFERROR(INDEX(Expenses!B$3:B$999,SMALL(IF((Expenses!E$3:E$999="GBP")*(Expenses!A$3:A$999=DATE(2025,12,29)),ROW(Expenses!A$3:A$999)-2),2)),""),IF(IFERROR(INDEX(Income!B$3:B$502,SMALL(IF((Income!D$3:D$502="GBP")*(Income!A$3:A$502=DATE(2025,12,29)),ROW(Income!A$3:A$502)-2),2)),"")<>"",IFERROR(INDEX(Income!B$3:B$502,SMALL(IF((Income!D$3:D$502="GBP")*(Income!A$3:A$502=DATE(2025,12,29)),ROW(Income!A$3:A$502)-2),2)),""),""))} | E5: {=IF(IFERROR(-INDEX(Expenses!D$3:D$999,SMALL(IF((Expenses!E$3:E$999="GBP")*(Expenses!A$3:A$999=DATE(2025,12,30)),ROW(Expenses!A$3:A$999)-2),2)),0)+IFERROR(INDEX(Income!C$3:C$502,SMALL(IF((Income!D$3:D$502="GBP")*(Income!A$3:A$502=DATE(2025,12,30)),ROW(Income!A$3:A$502)-2),2)),0)=0,"",IFERROR(-INDEX(Expenses!D$3:D$999,SMALL(IF((Expenses!E$3:E$999="GBP")*(Expenses!A$3:A$999=DATE(2025,12,30)),ROW(Expenses!A$3:A$999)-2),2)),0)+IFERROR(INDEX(Income!C$3:C$502,SMALL(IF((Income!D$3:D$502="GBP")*(Income!A$3:A$502=DATE(2025,12,30)),ROW(Income!A$3:A$502)-2),2)),0))} | F5: {=IF(IFERROR(INDEX(Expenses!B$3:B$999,SMALL(IF((Expenses!E$3:E$999="GBP")*(Expenses!A$3:A$999=DATE(2025,12,30)),ROW(Expenses!A$3:A$999)-2),2)),"")<>"",IFERROR(INDEX(Expenses!B$3:B$999,SMALL(IF((Expenses!E$3:E$999="GBP")*(Expenses!A$3:A$999=DATE(2025,12,30)),ROW(Expenses!A$3:A$999)-2),2)),""),IF(IFERROR(INDEX(Income!B$3:B$502,SMALL(IF((Income!D$3:D$502="GBP")*(Income!A$3:A$502=DATE(2025,12,30)),ROW(Income!A$3:A$502)-2),2)),"")<>"",IFERROR(INDEX(Income!B$3:B$502,SMALL(IF((Income!D$3:D$502="GBP")*(Income!A$3:A$502=DATE(2025,12,30)),ROW(Income!A$3:A$502)-2),2)),""),""))} | G5: {=IF(IFERROR(-INDEX(Expenses!D$3:D$999,SMALL(IF((Expenses!E$3:E$999="GBP")*(Expenses!A$3:A$999=DATE(2025,12,31)),ROW(Expenses!A$3:A$999)-2),2)),0)+IFERROR(INDEX(Income!C$3:C$502,SMALL(IF((Income!D$3:D$502="GBP")*(Income!A$3:A$502=DATE(2025,12,31)),ROW(Income!A$3:A$502)-2),2)),0)=0,"",IFERROR(-INDEX(Expenses!D$3:D$999,SMALL(IF((Expenses!E$3:E$999="GBP")*(Expenses!A$3:A$999=DATE(2025,12,31)),ROW(Expenses!A$3:A$999)-2),2)),0)+IFERROR(INDEX(Income!C$3:C$502,SMALL(IF((Income!D$3:D$502="GBP")*(Income!A$3:A$502=DATE(2025,12,31)),ROW(Income!A$3:A$502)-2),2)),0))} | H5: {=IF(IFERROR(INDEX(Expenses!B$3:B$999,SMALL(IF((Expenses!E$3:E$999="GBP")*(Expenses!A$3:A$999=DATE(2025,12,31)),ROW(Expenses!A$3:A$999)-2),2)),"")<>"",IFERROR(INDEX(Expenses!B$3:B$999,SMALL(IF((Expenses!E$3:E$999="GBP")*(Expenses!A$3:A$999=DATE(2025,12,31)),ROW(Expenses!A$3:A$999)-2),2)),""),IF(IFERROR(INDEX(Income!B$3:B$502,SMALL(IF((Income!D$3:D$502="GBP")*(Income!A$3:A$502=DATE(2025,12,31)),ROW(Income!A$3:A$502)-2),2)),"")<>"",IFERROR(INDEX(Income!B$3:B$502,SMALL(IF((Income!D$3:D$502="GBP")*(Income!A$3:A$502=DATE(2025,12,31)),ROW(Income!A$3:A$502)-2),2)),""),""))} | I5: {=IF(IFERROR(-INDEX(Expenses!D$3:D$999,SMALL(IF((Expenses!E$3:E$999="GBP")*(Expenses!A$3:A$999=DATE(2026,1,1)),ROW(Expenses!A$3:A$999)-2),2)),0)+IFERROR(INDEX(Income!C$3:C$502,SMALL(IF((Income!D$3:D$502="GBP")*(Income!A$3:A$502=DATE(2026,1,1)),ROW(Income!A$3:A$502)-2),2)),0)=0,"",IFERROR(-INDEX(Expenses!D$3:D$999,SMALL(IF((Expenses!E$3:E$999="GBP")*(Expenses!A$3:A$999=DATE(2026,1,1)),ROW(Expenses!A$3:A$999)-2),2)),0)+IFERROR(INDEX(Income!C$3:C$502,SMALL(IF((Income!D$3:D$502="GBP")*(Income!A$3:A$502=DATE(2026,1,1)),ROW(Income!A$3:A$502)-2),2)),0))} | J5: {=IF(IFERROR(INDEX(Expenses!B$3:B$999,SMALL(IF((Expenses!E$3:E$999="GBP")*(Expenses!A$3:A$999=DATE(2026,1,1)),ROW(Expenses!A$3:A$999)-2),2)),"")<>"",IFERROR(INDEX(Expenses!B$3:B$999,SMALL(IF((Expenses!E$3:E$999="GBP")*(Expenses!A$3:A$999=DATE(2026,1,1)),ROW(Expenses!A$3:A$999)-2),2)),""),IF(IFERROR(INDEX(Income!B$3:B$502,SMALL(IF((Income!D$3:D$502="GBP")*(Income!A$3:A$502=DATE(2026,1,1)),ROW(Income!A$3:A$502)-2),2)),"")<>"",IFERROR(INDEX(Income!B$3:B$502,SMALL(IF((Income!D$3:D$502="GBP")*(Income!A$3:A$502=DATE(2026,1,1)),ROW(Income!A$3:A$502)-2),2)),""),""))} | K5: {=IF(IFERROR(-INDEX(Expenses!D$3:D$999,SMALL(IF((Expenses!E$3:E$999="GBP")*(Expenses!A$3:A$999=DATE(2026,1,2)),ROW(Expenses!A$3:A$999)-2),2)),0)+IFERROR(INDEX(Income!C$3:C$502,SMALL(IF((Income!D$3:D$502="GBP")*(Income!A$3:A$502=DATE(2026,1,2)),ROW(Income!A$3:A$502)-2),2)),0)=0,"",IFERROR(-INDEX(Expenses!D$3:D$999,SMALL(IF((Expenses!E$3:E$999="GBP")*(Expenses!A$3:A$999=DATE(2026,1,2)),ROW(Expenses!A$3:A$999)-2),2)),0)+IFERROR(INDEX(Income!C$3:C$502,SMALL(IF((Income!D$3:D$502="GBP")*(Income!A$3:A$502=DATE(2026,1,2)),ROW(Income!A$3:A$502)-2),2)),0))} | L5: {=IF(IFERROR(INDEX(Expenses!B$3:B$999,SMALL(IF((Expenses!E$3:E$999="GBP")*(Expenses!A$3:A$999=DATE(2026,1,2)),ROW(Expenses!A$3:A$999)-2),2)),"")<>"",IFERROR(INDEX(Expenses!B$3:B$999,SMALL(IF((Expenses!E$3:E$999="GBP")*(Expenses!A$3:A$999=DATE(2026,1,2)),ROW(Expenses!A$3:A$999)-2),2)),""),IF(IFERROR(INDEX(Income!B$3:B$502,SMALL(IF((Income!D$3:D$502="GBP")*(Income!A$3:A$502=DATE(2026,1,2)),ROW(Income!A$3:A$502)-2),2)),"")<>"",IFERROR(INDEX(Income!B$3:B$502,SMALL(IF((Income!D$3:D$502="GBP")*(Income!A$3:A$502=DATE(2026,1,2)),ROW(Income!A$3:A$502)-2),2)),""),""))} | M5: {=IF(IFERROR(-INDEX(Expenses!D$3:D$999,SMALL(IF((Expenses!E$3:E$999="GBP")*(Expenses!A$3:A$999=DATE(2026,1,3)),ROW(Expenses!A$3:A$999)-2),2)),0)+IFERROR(INDEX(Income!C$3:C$502,SMALL(IF((Income!D$3:D$502="GBP")*(Income!A$3:A$502=DATE(2026,1,3)),ROW(Income!A$3:A$502)-2),2)),0)=0,"",IFERROR(-INDEX(Expenses!D$3:D$999,SMALL(IF((Expenses!E$3:E$999="GBP")*(Expenses!A$3:A$999=DATE(2026,1,3)),ROW(Expenses!A$3:A$999)-2),2)),0)+IFERROR(INDEX(Income!C$3:C$502,SMALL(IF((Income!D$3:D$502="GBP")*(Income!A$3:A$502=DATE(2026,1,3)),ROW(Income!A$3:A$502)-2),2)),0))} | N5: {=IF(IFERROR(INDEX(Expenses!B$3:B$999,SMALL(IF((Expenses!E$3:E$999="GBP")*(Expenses!A$3:A$999=DATE(2026,1,3)),ROW(Expenses!A$3:A$999)-2),2)),"")<>"",IFERROR(INDEX(Expenses!B$3:B$999,SMALL(IF((Expenses!E$3:E$999="GBP")*(Expenses!A$3:A$999=DATE(2026,1,3)),ROW(Expenses!A$3:A$999)-2),2)),""),IF(IFERROR(INDEX(Income!B$3:B$502,SMALL(IF((Income!D$3:D$502="GBP")*(Income!A$3:A$502=DATE(2026,1,3)),ROW(Income!A$3:A$502)-2),2)),"")<>"",IFERROR(INDEX(Income!B$3:B$502,SMALL(IF((Income!D$3:D$502="GBP")*(Income!A$3:A$502=DATE(2026,1,3)),ROW(Income!A$3:A$502)-2),2)),""),""))} | O5: {=IF(IFERROR(-INDEX(Expenses!D$3:D$999,SMALL(IF((Expenses!E$3:E$999="GBP")*(Expenses!A$3:A$999=DATE(2026,1,4)),ROW(Expenses!A$3:A$999)-2),2)),0)+IFERROR(INDEX(Income!C$3:C$502,SMALL(IF((Income!D$3:D$502="GBP")*(Income!A$3:A$502=DATE(2026,1,4)),ROW(Income!A$3:A$502)-2),2)),0)=0,"",IFERROR(-INDEX(Expenses!D$3:D$999,SMALL(IF((Expenses!E$3:E$999="GBP")*(Expenses!A$3:A$999=DATE(2026,1,4)),ROW(Expenses!A$3:A$999)-2),2)),0)+IFERROR(INDEX(Income!C$3:C$502,SMALL(IF((Income!D$3:D$502="GBP")*(Income!A$3:A$502=DATE(2026,1,4)),ROW(Income!A$3:A$502)-2),2)),0))} | P5: {=IF(IFERROR(INDEX(Expenses!B$3:B$999,SMALL(IF((Expenses!E$3:E$999="GBP")*(Expenses!A$3:A$999=DATE(2026,1,4)),ROW(Expenses!A$3:A$999)-2),2)),"")<>"",IFERROR(INDEX(Expenses!B$3:B$999,SMALL(IF((Expenses!E$3:E$999="GBP")*(Expenses!A$3:A$999=DATE(2026,1,4)),ROW(Expenses!A$3:A$999)-2),2)),""),IF(IFERROR(INDEX(Income!B$3:B$502,SMALL(IF((Income!D$3:D$502="GBP")*(Income!A$3:A$502=DATE(2026,1,4)),ROW(Income!A$3:A$502)-2),2)),"")<>"",IFERROR(INDEX(Income!B$3:B$502,SMALL(IF((Income!D$3:D$502="GBP")*(Income!A$3:A$502=DATE(2026,1,4)),ROW(Income!A$3:A$502)-2),2)),""),""))}
